{
  "generatedAt": "2026-07-06T11:12:52.473351+00:00",
  "stats": {
    "feeds_total": 43,
    "feeds_succeeded": 26,
    "feeds_failed": 17,
    "items_collected": 604,
    "items_after_dedupe": 60,
    "items_scored": 60,
    "items_high_score": 9
  },
  "fetchedFeeds": [
    {
      "source": "NOS",
      "url": "https://feeds.nos.nl/nosnieuwsalgemeen",
      "count": 20
    },
    {
      "source": "NOS",
      "url": "https://feeds.nos.nl/nosnieuwsbinnenland",
      "count": 20
    },
    {
      "source": "NOS",
      "url": "https://feeds.nos.nl/nosnieuwspolitiek",
      "count": 1
    },
    {
      "source": "NOS",
      "url": "https://feeds.nos.nl/nosnieuwsopmerkelijk",
      "count": 2
    },
    {
      "source": "NU.nl",
      "url": "https://www.nu.nl/rss/algemeen",
      "count": 30
    },
    {
      "source": "Telegraaf",
      "url": "https://www.telegraaf.nl/rss",
      "count": 50
    },
    {
      "source": "Telegraaf",
      "url": "https://www.telegraaf.nl/binnenland/rss",
      "count": 45
    },
    {
      "source": "AD",
      "url": "https://www.ad.nl/home/rss.xml",
      "count": 30
    },
    {
      "source": "AD",
      "url": "https://www.ad.nl/binnenland/rss.xml",
      "count": 30
    },
    {
      "source": "Volkskrant",
      "url": "https://www.volkskrant.nl/nieuws-achtergrond/rss.xml",
      "count": 0
    },
    {
      "source": "Trouw",
      "url": "https://www.trouw.nl/home/rss.xml",
      "count": 42
    },
    {
      "source": "BN De Stem",
      "url": "https://www.bndestem.nl/home/rss.xml",
      "count": 30
    },
    {
      "source": "De Stentor",
      "url": "https://www.destentor.nl/home/rss.xml",
      "count": 30
    },
    {
      "source": "PZC",
      "url": "https://www.pzc.nl/home/rss.xml",
      "count": 30
    },
    {
      "source": "Gooi- en Eemlander",
      "url": "https://www.gooieneemlander.nl/rss",
      "count": 50
    },
    {
      "source": "Omroep Brabant",
      "url": "https://www.omroepbrabant.nl/rss",
      "count": 25
    },
    {
      "source": "RTV Noord",
      "url": "https://www.rtvnoord.nl/rss",
      "count": 20
    },
    {
      "source": "Crimesite",
      "url": "https://www.crimesite.nl/feed/",
      "count": 8
    },
    {
      "source": "Regio 15 (Den Haag)",
      "url": "https://regio15.nl/feed/",
      "count": 0
    },
    {
      "source": "AD Den Haag",
      "url": "https://www.ad.nl/den-haag/rss.xml",
      "count": 25
    },
    {
      "source": "AD Rotterdam",
      "url": "https://www.ad.nl/rotterdam/rss.xml",
      "count": 30
    },
    {
      "source": "Dagblad010",
      "url": "https://dagblad010.nl/feed/",
      "count": 45
    },
    {
      "source": "Den Haag Centraal",
      "url": "https://www.denhaagcentraal.net/feed/",
      "count": 1
    },
    {
      "source": "Dordt Centraal",
      "url": "https://dordtcentraal.nl/feed/",
      "count": 9
    },
    {
      "source": "OPEN Rotterdam",
      "url": "https://openrotterdam.nl/feed/",
      "count": 8
    },
    {
      "source": "Sleutelstad",
      "url": "https://sleutelstad.nl/feed/",
      "count": 23
    }
  ],
  "failedFeeds": [
    {
      "source": "RTL",
      "url": "https://www.rtlnieuws.nl/service/rss/nieuws/index.xml",
      "error": "http: 404 Client Error: Not Found for url: https://www.rtl.nl/service/rss/nieuws/index.xml"
    },
    {
      "source": "Hart van Nederland",
      "url": "https://www.hartvannederland.nl/nieuws/rss.xml",
      "error": "http: 404 Client Error: Not Found for url: https://www.hartvannederland.nl/nieuws/rss.xml"
    },
    {
      "source": "Omroep West",
      "url": "https://www.omroepwest.nl/rss",
      "error": "http: 404 Client Error: Not Found for url: https://www.omroepwest.nl/rss"
    },
    {
      "source": "NH Nieuws",
      "url": "https://www.nhnieuws.nl/rss",
      "error": "parse: <unknown>:2:5449: not well-formed (invalid token)"
    },
    {
      "source": "L1 Limburg",
      "url": "https://www.l1.nl/rss",
      "error": "http: 404 Client Error: Not Found for url: https://www.l1.nl/rss"
    },
    {
      "source": "AT5",
      "url": "https://www.at5.nl/rss",
      "error": "parse: <unknown>:2:4802: not well-formed (invalid token)"
    },
    {
      "source": "Rijnmond",
      "url": "https://www.rijnmond.nl/rss",
      "error": "http: 404 Client Error: Not Found for url: https://www.rijnmond.nl/rss"
    },
    {
      "source": "RTV Utrecht",
      "url": "https://www.rtvutrecht.nl/rss",
      "error": "parse: <unknown>:2:0: syntax error"
    },
    {
      "source": "Politie",
      "url": "https://www.politie.nl/rss/nieuws/",
      "error": "http: 404 Client Error: Not Found for url: https://www.politie.nl/rss/nieuws/"
    },
    {
      "source": "De Havenloods",
      "url": "https://www.dehavenloods.nl/feed/",
      "error": "http: 404 Client Error: Not Found for url: https://www.dehavenloods.nl/feed"
    },
    {
      "source": "Leidsch Dagblad",
      "url": "https://www.leidschdagblad.nl/rss.xml",
      "error": "http: 403 Client Error: Forbidden for url: https://www.leidschdagblad.nl/rss.xml"
    },
    {
      "source": "Hart van Holland",
      "url": "https://www.hartvanzuidplas.nl/feed/",
      "error": "http: 404 Client Error: Not Found for url: https://www.hartvanzuidplas.nl/feed"
    },
    {
      "source": "Briels Nieuwsland",
      "url": "https://www.brielsnieuwsland.nl/feed/",
      "error": "http: 404 Client Error: Not Found for url: https://www.brielsnieuwsland.nl/feed"
    },
    {
      "source": "Delft op Zondag",
      "url": "https://www.delftopzondag.nl/feed/",
      "error": "http: 404 Client Error: Not Found for url: https://www.delftopzondag.nl/feed"
    },
    {
      "source": "Het Kontakt",
      "url": "https://www.hetkontakt.nl/feed/",
      "error": "http: 404 Client Error: Not Found for url: https://www.hetkontakt.nl/feed"
    },
    {
      "source": "Kijk op Zuid-Holland",
      "url": "https://www.kijkopzuid-holland.nl/feed/",
      "error": "http: HTTPSConnectionPool(host='www.kijkopzuid-holland.nl', port=443): Max retries exceeded with url: /feed/ (Caused by NewConnectionError(\"HTTPSConnection(host='www.kijkopzuid-holland.nl', port=443): Failed to establish a new connection: [Errno 101] Network is unreachable\"))"
    },
    {
      "source": "RTV Dordrecht",
      "url": "https://www.rtvdordrecht.nl/feed/",
      "error": "http: 404 Client Error: Not Found for url: https://www.rtvdordrecht.nl/404"
    }
  ],
  "items": [
    {
      "id": "dagblad010-4477350636",
      "source": "Dagblad010",
      "title": "Renners beginnen aan derde etappe Tour zonder publiek in slotfase",
      "description": "Renners beginnen aan derde etappe Tour zonder publiek in slotfase",
      "url": "https://dagblad010.nl/sport/renners-beginnen-aan-derde-etappe-tour-zonder-publiek-in-slotfase",
      "pubDate": "2026-07-06T12:52:00+00:00",
      "image": "https://media.digitaaldagblad.nl/files/shares/dagblad070/tourdefrance6a4b88f75e673.jpg",
      "score": 5,
      "category": "Overig",
      "location": "Internationaal",
      "reason": "Tour de France-verslaglegging zonder Nederlands politieke of maatschappelijk relevantie.",
      "summary": "De derde etappe van de Tour de France begint zonder publiek in de slotfase. Renners vertrekken naar de Pyreneeën."
    },
    {
      "id": "dagblad010-3318917438",
      "source": "Dagblad010",
      "title": "Rotterdam City Swim 2026 levert ruim 392.000 euro op",
      "description": "Rotterdam City Swim 2026 levert ruim 392.000 euro op",
      "url": "https://dagblad010.nl/rotterdam%20%26%20regio/rotterdam-city-swim-2026-levert-ruim-392000-euro-op",
      "pubDate": "2026-07-06T12:47:00+00:00",
      "image": "https://media.digitaaldagblad.nl/files/shares/dagblad010/cityswim6a4b87921e623.jpg",
      "score": 8,
      "category": "Overig",
      "location": "Zuid-Holland",
      "reason": "Lokaal evenement in Rotterdam met minimale maatschappelijke impact of controverse.",
      "summary": "Rotterdam City Swim 2026 heeft ruim 392.000 euro opgeleverd. Het event draagt bij aan goede doelen."
    },
    {
      "id": "dagblad010-3000452683",
      "source": "Dagblad010",
      "title": "DENK stelt vragen over ME-optreden tijdens voetbalfeest in Rotterdam",
      "description": "DENK stelt vragen over ME-optreden tijdens voetbalfeest in Rotterdam",
      "url": "https://dagblad010.nl/politiek/denk-stelt-vragen-over-me-optreden-tijdens-voetbalfeest-in-rotterdam",
      "pubDate": "2026-07-06T11:37:00+00:00",
      "image": "https://media.digitaaldagblad.nl/files/shares/dagblad010/aanhoudingmarok6a4a1b08a548f.jpg",
      "score": 72,
      "category": "Misdaad",
      "location": "Zuid-Holland",
      "reason": "DENK stelt vragen over politieoptreden; potentieel politieke controverse rond ordhandhavers.",
      "summary": "DENK wil opheldering over ME-optreden tijdens voetbalfeest in Rotterdam. Partij stelt kamervragen."
    },
    {
      "id": "dagblad010-6722122571",
      "source": "Dagblad010",
      "title": "Rotterdam: nog geen aanleiding voor fatbikeverbod zoals in Enschede",
      "description": "Rotterdam: nog geen aanleiding voor fatbikeverbod zoals in Enschede",
      "url": "https://dagblad010.nl/politiek/rotterdam-nog-geen-aanleiding-voor-fatbikeverbod-zoals-in-enschede",
      "pubDate": "2026-07-06T11:23:00+00:00",
      "image": "https://media.digitaaldagblad.nl/files/shares/dagblad070/fatbikers6926f8281dd74.jpg",
      "score": 65,
      "category": "Misdaad",
      "location": "Zuid-Holland",
      "reason": "Fatbike-problematiek relevant; Rotterdam-beleid contrasteert met Enschede-verbod.",
      "summary": "Rotterdam ziet nog geen aanleiding voor fatbikeverbod zoals in Enschede. Gemeente monitort situatie."
    },
    {
      "id": "ad-8685746227",
      "source": "AD",
      "title": "Na crash Max Verstappen wint Michael van Gerwen wél op Silverstone: ‘Toch nog een Dutchie die wint’",
      "description": "Max Verstappen beleefde bij de Grand Prix van Groot-Brittannië een nachtmerrie, maar een andere Nederlander nam ‘s avonds wél een beker mee naar huis: Michael van Gerwen won een dartstoernooitje, midden op het Formule 1-circuit. „Ik heb nog nooit iets gewonnen op Silverstone.”",
      "url": "https://www.ad.nl/darts/na-crash-max-verstappen-wint-michael-van-gerwen-wel-op-silverstone-toch-nog-een-dutchie-die-wint~a1ccea1e/",
      "pubDate": "2026-07-06T11:08:45+00:00",
      "image": "https://images.ad.nl/NjhmMjRmNjFmYWY1MWYyZjIyYmMvZGlvLzI3NTYyMjU1Mi9maXQtd2lkdGgvNDAw/michael-van-gerwen-links-met-lewis-capaldi-rechts-met-onder-anderen-goede-vriend-vincent-van-der-voort",
      "duplicate_sources": [
        "BN De Stem",
        "De Stentor",
        "PZC"
      ],
      "score": 15,
      "category": "Overig",
      "location": "Internationaal",
      "reason": "Sport-mengelmoes zonder Nederlandse politieke of maatschappelijke relevantie voor PowNed.",
      "summary": "Michael van Gerwen wint dartstoernooitje op Silverstone. Max Verstappen crasht in Grand Prix."
    },
    {
      "id": "ad-9215127682",
      "source": "AD",
      "title": "Van der Poel mengt zich in strijd om juiste vlucht, ook Bernal en Carapaz mee",
      "description": "Na twee dagen in Catalonië zegt het peloton maandag gedag tegen Spanje. De derde etappe voert de renners van Granollers via de Pyreneeën naar het Franse Les Angles. Met bijna 3.900 hoogtemeters en een finish bergop wacht meteen de eerste bergrit van deze Tour. Volg de derde etappe, met de finish rond 17.10 uur, in ons liveblog.",
      "url": "https://www.ad.nl/tour-de-france/van-der-poel-mengt-zich-in-strijd-om-juiste-vlucht-ook-bernal-en-carapaz-mee~a56c53c2/",
      "pubDate": "2026-07-06T11:06:00+00:00",
      "image": "https://images.ad.nl/MzUwZmI4YTdmMWFkYjIwNDE4ZWIvZGlvLzI3NTYyNTcxMS9maXQtd2lkdGgvNDAw/caja-rural-seguros-rga-team-s-dutch-rider-alex-molenaar-wearing-the-climber-s-dotted-jersey-awaits-the-start-of-the-3rd-stage-of-the-113th-edition-of-the-tour-de-france-cycling-race-196-km-between-granollers-and-les-angles-in-southern-france-on-july-6-2026-photo-by-loic-venance-afp",
      "score": 5,
      "category": "Overig",
      "location": "Internationaal",
      "reason": "Standaard Tour de France-verslaglegging zonder Nederlandse politieke/maatschappelijke element.",
      "summary": "Derde etappe Tour de France voert renners door Pyreneeën naar Les Angles. Van der Poel mengt zich in strijd."
    },
    {
      "id": "open-rotterdam-5446454993",
      "source": "OPEN Rotterdam",
      "title": "Speeltuin de Vuurklip op Kop van Zuid is gered: vier nieuwe vrijwilligers en negentig nieuwe leden",
      "description": "Het tij is gekeerd voor Speeltuin de Vuurklip, want ze hebben eindelijk weer vrijwilligers. Begin dit jaar ging de speeltuin dicht voor een grote renovatie, maar de heropening stond onder druk doordat ze maar geen vrijwilligers konden vinden. Dat probleem is nu eindelijk opgelost. Het resultaat: vier nieuwe vrijwilligers, meer dan negentig nieuwe leden en [&#8230;] Het bericht Speeltuin de Vuurkli",
      "url": "https://openrotterdam.nl/speeltuin-de-vuurklip-op-kop-van-zuid-is-gered-vier-nieuwe-vrijwilligers-en-negentig-nieuwe-leden/",
      "pubDate": "2026-07-06T11:04:49+00:00",
      "image": "",
      "score": 12,
      "category": "Overig",
      "location": "Zuid-Holland",
      "reason": "Positief lokaal nieuwsje over speeltuin; geen controverse of maatschappelijke relevantie.",
      "summary": "Speeltuin de Vuurklip op Kop van Zuid is gered met vier nieuwe vrijwilligers. Speeltuin herstart activiteiten."
    },
    {
      "id": "telegraaf-7689554029",
      "source": "Telegraaf",
      "title": "LIVE Tour de France | Aanvallers ruiken hun kansen, al vroeg grote valpartij in peloton",
      "description": "De derde etappe van de Tour de France staat alweer voor de deur. Dit keer gaat het richting de Pyreneeën. Grijpt Tadej Pogacar de kans om zelf toe te slaan? Volg het op de voet via ons liveblog.",
      "url": "https://www.telegraaf.nl/sport/wielrennen/live-tour-de-france-aanvallers-ruiken-hun-kansen-al-vroeg-grote-valpartij-in-peloton/158319923.html",
      "pubDate": "2026-07-06T11:04:00+00:00",
      "image": "https://prod-img.telegraaf.nl/public/sport/4b5j9l-gettyimages-2284864647.jpg/alternates/BASE_SIXTEEN_NINE/GettyImages-2284864647.jpg",
      "score": 5,
      "category": "Overig",
      "location": "Internationaal",
      "reason": "Standaard Tour de France-liveblog zonder Nederlandse politieke of controversiële element.",
      "summary": "Derde etappe Tour de France richting Pyreneeën; vroege valpartij in peloton. Pogacar onder druk."
    },
    {
      "id": "telegraaf-3337781580",
      "source": "Telegraaf",
      "title": "LIVE | Oekraïne meldt nieuwe aanvallen op Russische olieraffinaderijen",
      "description": "De Oekraïense bevolking leeft al ruim vier jaar in onzekerheid door de Russische terreur. Vredesgesprekken leverden tot nu toe weinig op, de gevechten gaan door. Volg de laatste ontwikkelingen rond de oorlog in Oekraïne in ons liveblog.",
      "url": "https://www.telegraaf.nl/buitenland/live-oekrane-meldt-nieuwe-aanvallen-op-russische-olieraffinaderijen/158308605.html",
      "pubDate": "2026-07-06T11:03:00+00:00",
      "image": "https://prod-img.telegraaf.nl/public/incoming/4au0jf-gettyimages-2281551936.jpg/alternates/BASE_SIXTEEN_NINE/GettyImages-2281551936.jpg",
      "score": 15,
      "category": "Overig",
      "location": "Internationaal",
      "reason": "Oekraïne-oorlog zonder Nederlandse hoek relevant voor PowNed.",
      "summary": "Oekraïne meldt nieuwe aanvallen op Russische olieraffinaderijen. De gevechten gaan door ondanks vredesgesprekken."
    },
    {
      "id": "sleutelstad-1412536825",
      "source": "Sleutelstad",
      "title": "Nieuw beeld van Tinga speelt iedereen uit",
      "description": "Een man met vele gezichten. Als activist surft Merijn Tinga over rivieren en oceanen, maar hij staat net zo lief te bikken in een massieve klomp hardsteen. De afgelopen maanden wilde iedereen met de Leidse kunstenaar op de foto, van prins Albert van Monaco tot de paus. Tinga was te gast in de seizoensafsluiting van [&#8230;]",
      "url": "https://sleutelstad.nl/2026/07/06/nieuw-beeld-van-tinga-speelt-iedereen-uit/",
      "pubDate": "2026-07-06T11:01:22+00:00",
      "image": "",
      "score": 62,
      "category": "Opmerkelijk",
      "location": "Zuid-Holland",
      "reason": "Excentrieke kunstenaar met media-aandacht past in 'Opmerkelijk'-rubriek.",
      "summary": "Merijn Tinga is een kunstenaar met vele gezichten die internationale aandacht trekt. Hij combineert activisme met kunstwerken in natuursteen."
    },
    {
      "id": "telegraaf-5430617225",
      "source": "Telegraaf",
      "title": "School rouwt om twee verongelukte jongens (15): ’Hun toekomst moest nog beginnen’",
      "description": "De twee 15-jarige jongens die zondagochtend om het leven kwamen bij een ernstig auto-ongeluk in het Brabantse dorp Zeeland, reden volgens de politie zonder toestemming in de auto van een familielid. Op hun school, het Fioretti College in Veghel, overheerst maandag het verdriet.",
      "url": "https://www.telegraaf.nl/binnenland/school-rouwt-om-twee-verongelukte-jongens-15-hun-toekomst-moest-nog-beginnen/158321169.html",
      "pubDate": "2026-07-06T11:01:20+00:00",
      "image": "https://prod-img.telegraaf.nl/public/incoming/odfp0g-anp-562860320.jpg/alternates/BASE_SIXTEEN_NINE/ANP-562860320.jpg",
      "score": 68,
      "category": "Misdaad",
      "location": "Noord-Brabant",
      "reason": "Dodelijk auto-ongeluk met minderjarigen in Brabant; omroep herhaalt verhaal.",
      "summary": "Twee 15-jarige jongens verongelukten bij eenzijdig auto-ongeluk in Zeeland. Ze reden zonder toestemming in auto van familielid."
    },
    {
      "id": "de-stentor-1838448530",
      "source": "De Stentor",
      "title": "Twee 15-jarige slachtoffers fatale crash reden zonder toestemming in auto familielid",
      "description": "De twee 15-jarige jongens die zondagochtend overleden bij een eenzijdig auto-ongeluk in het dorp Zeeland, reden zonder toestemming in de auto van een familielid. Dat bevestigt een politiewoordvoerder.",
      "url": "https://www.destentor.nl/binnenland/twee-15-jarige-slachtoffers-fatale-crash-reden-zonder-toestemming-in-auto-familielid~a9be11e0/",
      "pubDate": "2026-07-06T11:00:51+00:00",
      "image": "https://images.destentor.nl/NTBhYWNjMTNlN2Q2MDg0MDMxNjgvZGlvLzI3NTU4NDk4MC9maXQtd2lkdGgvNDAw/een-auto-is-zondagochtend-hard-tegen-een-boom-gebotst-en-vervolgens-in-brand-gevlogen-aan-de-boekelsedijk-in-zeeland",
      "duplicate_sources": [
        "BN De Stem"
      ],
      "score": 68,
      "category": "Misdaad",
      "location": "Noord-Brabant",
      "reason": "Dezelfde crash-story als Telegraaf; lokale bron herhaalt al gemeld nieuws.",
      "summary": "Twee 15-jarige jongens verongelukten bij eenzijdig auto-ongeluk in Zeeland. Ze reden zonder toestemming in auto van familielid."
    },
    {
      "id": "telegraaf-4615426156",
      "source": "Telegraaf",
      "title": "Regering Israël negeert vonnis hooggerechtshof: dreigt anarchie in Tel Aviv?",
      "description": "Met relatieve stilte aan drie fronten heeft de Israëlische regering nu haar aandacht verlegd naar een andere oorlog: die tegen de democratische rechtsstaat. Zij opende deze week de frontale aanval op het hooggerechtshof door, voor het eerst in de geschiedenis, aan te kondigen dat zij zich niet zal houden aan een besluit van ’s lands hoogste juridische orgaan. Anarchie dreigt.",
      "url": "https://www.telegraaf.nl/buitenland/regering-israel-negeert-vonnis-hooggerechtshof-dreigt-anarchie-in-tel-aviv/158312955.html",
      "pubDate": "2026-07-06T11:00:00+00:00",
      "image": "https://prod-img.telegraaf.nl/public/incoming/1q6pza-file86hxi3xvfnk8wod1ch8/alternates/BASE_SIXTEEN_NINE/file86hxi3xvfnk8wod1ch8",
      "score": 35,
      "category": "Overig",
      "location": "Internationaal",
      "reason": "Israëlische politiek zonder Nederlandse relevantie betreft buitenland.",
      "summary": "Israëlische regering kondigde aan zich niet te houden aan hooggerechtshofbesluit. Dit dreigt democratische rechtsstaat onderuit te halen."
    },
    {
      "id": "nu.nl-8153028318",
      "source": "NU.nl",
      "title": "Hamas ontbindt na twintig jaar eigen bestuur in Gazastrook",
      "description": "Hamas ontbindt na bijna twintig jaar aan de macht te zijn geweest zijn leiderschap in de Gazastrook, meldt het mediakantoor van de extremistische Palestijnse beweging maandag aan persbureau AFP .",
      "url": "https://www.nu.nl/midden-oostenconflict/6402081/hamas-ontbindt-na-twintig-jaar-eigen-bestuur-in-gazastrook.html",
      "pubDate": "2026-07-06T10:59:35+00:00",
      "image": "https://images.nu.nl/m/oekxh9hazfep_sqr256/698/0/2682/2682/hamas-ontbindt-na-twintig-jaar-eigen-bestuur-in-gazastrook.jpg",
      "duplicate_sources": [
        "Gooi- en Eemlander"
      ],
      "score": 20,
      "category": "Overig",
      "location": "Internationaal",
      "reason": "Hamas-bestuur Gaza zonder Nederlandse hoek; zuiver buitenlands nieuws.",
      "summary": "Hamas ontbindt na twintig jaar zijn leiderschap in de Gazastrook. Reden onbekend in korte persbericht."
    },
    {
      "id": "nos-9198467380",
      "source": "NOS",
      "title": "Minister Sjoerdsma naar China: een beladen bezoek",
      "description": "Minister van Handel en Ontwikkelingssamenwerking Sjoerd Sjoerdsma begint morgen aan zijn bezoek aan China. Tegen een achtergrond van een sluimerende Europees-Chinese handelsoorlog, zitten tussen Nederland en China ook hete hangijzers in de relatie. Zoals rond chipmaker Nexperia, waar de Nederlandse overheid vorig jaar tot grote woede van China drastisch ingreep. En door de technologische machtsstr",
      "url": "https://nos.nl/artikel/2621881-minister-sjoerdsma-naar-china-een-beladen-bezoek",
      "pubDate": "2026-07-06T10:55:00+00:00",
      "image": "https://images.cdn.nos.nl/3/E/d/C/d/E/Z6MErBzGFXWD5T3k1TZH4kzPaHZoZFNRECQkHwH/0x73x4000x2250-1024x576.webp",
      "score": 78,
      "category": "Politiek",
      "location": "Landelijk",
      "reason": "Nederlands ministers China-bezoek met handelsbelangen; beladen relatie relevant.",
      "summary": "Minister Sjoerdsma bezoekt China tegen achtergrond Europees-Chinese spanningen. Nexperia-kwestie blijft belangrijk struikelblok."
    },
    {
      "id": "dagblad010-9945353775",
      "source": "Dagblad010",
      "title": "Kabinet trekt extra geld uit voor gezamenlijke ouderenwoningen",
      "description": "Kabinet trekt extra geld uit voor gezamenlijke ouderenwoningen",
      "url": "https://dagblad010.nl/landelijk/kabinet-trekt-extra-geld-uit-voor-gezamenlijke-ouderenwoningen",
      "pubDate": "2026-07-06T10:55:00+00:00",
      "image": "https://media.digitaaldagblad.nl/files/shares/ridderkerksdagblad/ouderenhelpen6a213351acd6a.jpg",
      "score": 45,
      "category": "Politiek",
      "location": "Landelijk",
      "reason": "Kabinetsbeleid ouderenwoningen landelijk relevant; onderwerp enigszins saai.",
      "summary": "Kabinet trekt extra geld uit voor gezamenlijke ouderenwoningen. Exact bedrag niet duidelijk uit korte melding."
    },
    {
      "id": "telegraaf-9178215920",
      "source": "Telegraaf",
      "title": "Nottingham Forest gaat het proberen met vijfde trainer in een jaar tijd",
      "description": "In de rubriek Sport Kort besteedt Telesport aandacht aan het dagelijkse nieuws. Deze rubriek wordt gedurende de dag continu ververst met het laatste nieuws.",
      "url": "https://www.telegraaf.nl/sport/nottingham-forest-gaat-het-proberen-met-vijfde-trainer-in-een-jaar-tijd/158279901.html",
      "pubDate": "2026-07-06T10:53:00+00:00",
      "image": "https://prod-img.telegraaf.nl/public/sport/1w0b45-sport-kort-de-geode-1.jpg/alternates/BASE_SIXTEEN_NINE/sport%20kort%20de%20geode%201.jpg",
      "score": 5,
      "category": "Overig",
      "location": "Internationaal",
      "reason": "Sport zonder Nederlands angle, niet relevant voor PowNed.",
      "summary": "Nottingham Forest wijzigt trainersbeleid. Club benoemt vijfde trainer in een jaar."
    },
    {
      "id": "gooi--en-eemlander-7122116512",
      "source": "Gooi- en Eemlander",
      "title": "Vaccinatietempo hing af van eenvoud strategie, zegt oud-RIVM’er",
      "description": "Om tempo te houden in de coronavaccinaties, was het zaak de operatie zo eenvoudig mogelijk te maken. Grote groepen voorrang geven hielp daar niet bij. Dat zei Jaap van Delden, destijds als programmadirecteur bij het RIVM verantwoordelijk voor de vaccinaties, in een verhoor door de parlementaire enquêtecommissie corona.",
      "url": "https://www.gooieneemlander.nl/binnenland/vaccinatietempo-hing-af-van-eenvoud-strategie-zegt-oud-rivmer/158323436.html",
      "pubDate": "2026-07-06T10:52:53+00:00",
      "image": "https://prod-img.noordhollandsdagblad.nl/public/binnenland/e2phv0-3900338a-2a71-4e02-8d02-5e22b37c4f92-tmg-webfeed-bin-anp060726115-1.jpeg/alternates/BASE_SIXTEEN_NINE/3900338a-2a71-4e02-8d02-5e22b37c4f92_tmg-webfeed-bin_ANP060726115-1.jpeg",
      "score": 72,
      "category": "Politiek",
      "location": "Landelijk",
      "reason": "Corona-enquête relevantie, RIVM-getuigenis over vaccinatiebeleid interessant.",
      "summary": "Oud-RIVM'er Jaap van Delden getuigt voor coronacommissie over vaccinatietempo. Hij benadrukt belang van eenvoudige operationele strategie."
    },
    {
      "id": "telegraaf-8452358695",
      "source": "Telegraaf",
      "title": "Bondgenoten-Anouk over flinke relatieproblemen: ‘Ik ben nu aan het vluchten’",
      "description": "Bondgenoten-deelneemster Anouk heeft problemen met haar vriend na de omstreden afleveringen van haar en flirterige mede-deelnemer Diederik. Haar vriend was duidelijk: als Anouk nu niet naar huis komt, is het klaar. Echter is ze zelf nog niet zeker of ze naar huis komt. De bondgenoten is vanavond om 21.00 uur te zien op SBS6.",
      "url": "https://www.telegraaf.nl/video/bondgenoten-anouk-over-flinke-relatieproblemen-ik-ben-nu-aan-het-vluchten/158322938.html",
      "pubDate": "2026-07-06T10:52:00+00:00",
      "image": "https://prod-img.telegraaf.nl/public/incoming/dm39p1-6.jpeg/alternates/BASE_SIXTEEN_NINE/6.jpeg",
      "score": 25,
      "category": "Opmerkelijk",
      "location": "Landelijk",
      "reason": "BN'er-relationeel drama, maar oppervlakkig realityshow-kletspraatje.",
      "summary": "Bondgenoten-deelnemer Anouk kampt met relatieproblemen na flirtscènes. Partner eist huiskomst."
    },
    {
      "id": "gooi--en-eemlander-3008925252",
      "source": "Gooi- en Eemlander",
      "title": "Mensenrechtenraad VN wil spoedonderzoek naar situatie el-Obeid",
      "description": "De Mensenrechtenraad van de Verenigde Naties laat met spoed een onderzoek instellen naar de situatie in het Soedanese el-Obeid. Die strategisch gelegen stad wordt belegerd door de paramilitaire RSF en er wordt gevreesd voor grootschalige gruweldaden.",
      "url": "https://www.gooieneemlander.nl/buitenland/mensenrechtenraad-vn-wil-spoedonderzoek-naar-situatie-el-obeid/158323409.html",
      "pubDate": "2026-07-06T10:50:26+00:00",
      "image": "https://prod-img.gooieneemlander.nl/public/buitenland/d4z3t0-3900338a-2a71-4e02-8d02-5e22b37c4f92-tmg-webfeed-bui-anp060726113-1.jpeg/alternates/BASE_SIXTEEN_NINE/3900338a-2a71-4e02-8d02-5e22b37c4f92_tmg-webfeed-bui_ANP060726113-1.jpeg",
      "score": 8,
      "category": "Overig",
      "location": "Internationaal",
      "reason": "Soedaans conflict zonder Nederlandse hoek, routinematig buitenland.",
      "summary": "VN-mensenrechtenraad start onderzoek naar belegerde stad el-Obeid. Gevreesd wordt voor gruweldaden."
    },
    {
      "id": "gooi--en-eemlander-3188470567",
      "source": "Gooi- en Eemlander",
      "title": "Dierenbeschermers vinden nieuwe wolvenregels ’gebakken lucht’",
      "description": "Dierenbeschermers hebben aangekondigd naar de rechter te stappen als provincies al op voorhand een vergunning klaarleggen om wolven af te schieten, voor het geval een wolf een mens aanvalt. Staatssecretaris Silvio Erkens (Landbouw, VVD) heeft de regels hiervoor versoepeld, zodat provincies sneller kunnen ingrijpen bij ernstige incidenten. Volgens Erkens is het noodzakelijk om dit nog voor de zomer",
      "url": "https://www.gooieneemlander.nl/binnenland/dierenbeschermers-vinden-nieuwe-wolvenregels-gebakken-lucht/158323167.html",
      "pubDate": "2026-07-06T10:46:24+00:00",
      "image": "https://prod-img.noordhollandsdagblad.nl/public/binnenland/xv869x-8777a3ef-b8fd-44a3-8841-13f224b8b893-tmg-webfeed-bin-anp060726111-1.jpeg/alternates/BASE_SIXTEEN_NINE/8777a3ef-b8fd-44a3-8841-13f224b8b893_tmg-webfeed-bin_ANP060726111-1.jpeg",
      "score": 68,
      "category": "Politiek",
      "location": "Landelijk",
      "reason": "Staatssecretaris-beleid, wolvenregels, dierenbescherming versus veiligheid controverse.",
      "summary": "Dierenbeschermers willen rechtsgang tegen versoepelde wolvenregels van VVD-staatssecretaris Erkens. Provincies krijgen sneller vergunning voor afschot."
    },
    {
      "id": "gooi--en-eemlander-7328739630",
      "source": "Gooi- en Eemlander",
      "title": "Oud-RIVM-directeur voelde ’enorme druk’ over vaccinatiegraad",
      "description": "Jaap van Delden voelde een „enorme druk” over hoe het met de vaccinatiegraad ging in Nederland ten opzichte van andere landen. Dat zei de oud-RIVM-vaccinatiedirecteur tegen de parlementaire enquêtecommissie corona.",
      "url": "https://www.gooieneemlander.nl/binnenland/oud-rivm-directeur-voelde-enorme-druk-over-vaccinatiegraad/158323146.html",
      "pubDate": "2026-07-06T10:44:53+00:00",
      "image": "https://prod-img.noordhollandsdagblad.nl/public/binnenland/psqvd8-8777a3ef-b8fd-44a3-8841-13f224b8b893-tmg-webfeed-bin-anp060726110-1.jpeg/alternates/BASE_SIXTEEN_NINE/8777a3ef-b8fd-44a3-8841-13f224b8b893_tmg-webfeed-bin_ANP060726110-1.jpeg",
      "score": 71,
      "category": "Politiek",
      "location": "Landelijk",
      "reason": "Corona-enquête, RIVM-directeur voelt druk over vaccinatiegraad, politiek-relevant.",
      "summary": "Jaap van Delden zegt enorme druk gevoeld te hebben over Nederlandse vaccinatiegraad versus buitenland. Getuigenis voor parlementaire coronacommissie."
    },
    {
      "id": "gooi--en-eemlander-9639805275",
      "source": "Gooi- en Eemlander",
      "title": "Provincies mogen bij wolf sneller ingrijpen: veiligheid mens op 1",
      "description": "Provincies zijn positief over de nieuwe regels rond wolven, waardoor ze sneller kunnen ingrijpen bij ernstige incidenten. „Het heeft veel inzet gekost, maar eindelijk wordt erkend dat de veiligheid van mensen altijd op de eerste plaats moet staan”, aldus de Gelderse BBB-gedeputeerde Harold Zoet, die al jaren pleit voor meer mogelijkheden om maatregelen te nemen. In Gelderland leven de meeste wolve",
      "url": "https://www.gooieneemlander.nl/binnenland/provincies-mogen-bij-wolf-sneller-ingrijpen-veiligheid-mens-op-1/158322845.html",
      "pubDate": "2026-07-06T10:43:33+00:00",
      "image": "https://prod-img.noordhollandsdagblad.nl/public/binnenland/t24vew-9908677e-eeb9-4adf-8256-5ea5de7a1d91-tmg-webfeed-bin-anp060726109-1.jpeg/alternates/BASE_SIXTEEN_NINE/9908677e-eeb9-4adf-8256-5ea5de7a1d91_tmg-webfeed-bin_ANP060726109-1.jpeg",
      "score": 69,
      "category": "Politiek",
      "location": "Gelderland",
      "reason": "Wolfenbeleid Erkens, provincies bevoegd, BBB-politicus, veiligheid-debat relevant.",
      "summary": "Gelderse provincies positief over nieuwe wolvenregels die sneller ingrijpen mogelijk maken. BBB-gedeputeerde Zoet ziet veiligheid als prioriteit."
    },
    {
      "id": "gooi--en-eemlander-6751266439",
      "source": "Gooi- en Eemlander",
      "title": "Brussel helpt Frankrijk met vier blusvliegtuigen voor bosbranden",
      "description": "Brussel heeft vier blusvliegtuigen geregeld om Frankrijk bij te staan bij de bosbranden in het zuiden van het land, meldt de Europese Commissie. De vliegtuigen komen uit EU-lidstaten Cyprus en Zweden en arriveren maandag in de stad Perpignan, niet ver van de grootste brand.",
      "url": "https://www.gooieneemlander.nl/buitenland/brussel-helpt-frankrijk-met-vier-blusvliegtuigen-voor-bosbranden/158322814.html",
      "pubDate": "2026-07-06T10:42:26+00:00",
      "image": "https://prod-img.gooieneemlander.nl/public/buitenland/pz4qzj-9908677e-eeb9-4adf-8256-5ea5de7a1d91-tmg-webfeed-bui-anp060726108-1.jpeg/alternates/BASE_SIXTEEN_NINE/9908677e-eeb9-4adf-8256-5ea5de7a1d91_tmg-webfeed-bui_ANP060726108-1.jpeg",
      "score": 12,
      "category": "Overig",
      "location": "Internationaal",
      "reason": "Frans bosbranden zonder Nederlandse connectie, routinematig EU-bericht.",
      "summary": "Europese Commissie stuurt vier blusvliegtuigen naar zuid-Frankrijk voor bosbranden. Toestellen uit Cyprus en Zweden."
    },
    {
      "id": "nu.nl-7358399565",
      "source": "NU.nl",
      "title": "Miljoenen Iraniërs lopen mee met begrafenisstoet omgekomen leider Khamenei",
      "description": "Miljoenen Iraniërs liepen maandag mee met de begrafenisstoet voor de omgekomen opperste leider Ali Khamenei in Teheran. Ze droegen vlaggen en spandoeken en riepen leuzen over wraak. Het is de grootste opkomst tot nu toe in deze week vol afscheidsceremonies.",
      "url": "https://www.nu.nl/midden-oostenconflict/6402077/miljoenen-iraniers-lopen-mee-met-begrafenisstoet-omgekomen-leider-khamenei.html",
      "pubDate": "2026-07-06T10:41:17+00:00",
      "image": "https://images.nu.nl/m/va2xxwfaa0fv_sqr256/398/0/3519/3519/miljoenen-iraniers-lopen-mee-met-begrafenisstoet-omgekomen-leider-khamenei.jpg",
      "score": 15,
      "category": "Overig",
      "location": "Internationaal",
      "reason": "Zuiver buitenlands nieuws zonder Nederlandse relevantie of link.",
      "summary": "Miljoenen Iraniërs hebben deelgenomen aan de begrafenisstoet van opperste leider Ali Khamenei in Teheran. De stoet was de grootste samenkomst van deze week met afscheidsceremonies."
    },
    {
      "id": "telegraaf-8387229144",
      "source": "Telegraaf",
      "title": "Summer McIntosh (19) zwemt historisch wereldrecord op 200 meter vlinderslag: ’Ik had gedacht het nóóit te verbreken’",
      "description": "Zwemster Summer McIntosh heeft het wereldrecord op de 200 meter vlinderslag verbeterd. De 19-jarige Canadese noteerde bij wedstrijden in Montreal een tijd van 2.01,65. Ze was daarmee 0,16 sneller dan de Chinese Liu Zige in 2009.",
      "url": "https://www.telegraaf.nl/sport/summer-mcintosh-19-zwemt-historisch-wereldrecord-op-200-meter-vlinderslag-ik-had-gedacht-het-nooit-te-verbreken/158322126.html",
      "pubDate": "2026-07-06T10:40:00+00:00",
      "image": "https://prod-img.telegraaf.nl/public/sport/wielrennen/15tsem-anp-562907565.jpg/alternates/BASE_SIXTEEN_NINE/ANP-562907565.jpg",
      "score": 5,
      "category": "Overig",
      "location": "Internationaal",
      "reason": "Sport zonder Nederlandse betrokkenheid valt buiten PowNed-profiel.",
      "summary": "Canadese zwemster Summer McIntosh heeft het wereldrecord op 200 meter vlinderslag verbeterd tot 2.01,65. Ze verbeterde het vorige record van Chinese Liu Zige uit 2009."
    },
    {
      "id": "ad-rotterdam-2460649331",
      "source": "AD Rotterdam",
      "title": "Flixbus rijdt zich vast op tunneltraverse, flinke schade",
      "description": "De dubbeldekker bus heeft zich maandagochtend vastgereden op de tunneltraverse voor de Maastunnel. De tunnel heeft, in tegenstelling tot de bus, geen schade opgelopen en is inmiddels alweer vrijgegeven.",
      "url": "https://www.ad.nl/rotterdam/flixbus-rijdt-zich-vast-op-tunneltraverse-flinke-schade~a3674ecc/",
      "pubDate": "2026-07-06T10:32:00+00:00",
      "image": "https://images.ad.nl/NmRiZDA3MDU3ZjNiNDU5ZDBmYjkvZGlvLzI3NTYyNjUzOC9maXQtd2lkdGgvNDAw/",
      "score": 62,
      "category": "Opmerkelijk",
      "location": "Zuid-Holland",
      "reason": "Lokaal incident met bizarre situatie: bus vast op tunnel. Geschikt voor PowNed-rubriek.",
      "summary": "Een Flixbus raakte maandagochtend vastgeklemd op de tunneltraverse van de Maastunnel in Rotterdam. De tunnel bleef onbeschadigd en kon snel vrijgegeven worden."
    },
    {
      "id": "pzc-6061073661",
      "source": "PZC",
      "title": "Onderzoek naar meest ingewikkelde kruising van Middelburg: ‘Spoorbomen blijven hier wel erg lang dicht’",
      "description": "Middelburg gaat opnieuw bekijken of het nodig is het kruispunt tussen de Schroebrug en de spoorwegovergang veiliger te maken. Ook gaat de gemeente in gesprek met ProRail over de spoorbomen die daar soms tot wel vijf minuten dichtblijven. „Dat zorgt voor onoverzichtelijke situaties en ongelukken.”",
      "url": "https://www.pzc.nl/middelburg/onderzoek-naar-meest-ingewikkelde-kruising-van-middelburg-spoorbomen-blijven-hier-wel-erg-lang-dicht~a0051490/",
      "pubDate": "2026-07-06T10:30:30+00:00",
      "image": "https://images.pzc.nl/MjFkNGFlNWFlMDdmZjc2MGUwMGYvZGlvLzI3NTUxMjQ3Ni9maXQtd2lkdGgvNDAw/pz20260703-3471-middelburg-03-07-2026-onderzoek-naar-ingewikkeldste-kruispunt-van-middelburg",
      "score": 48,
      "category": "Overig",
      "location": "Zeeland",
      "reason": "Lokale infrastructuurproblematiek zonder grotere maatschappelijke impact of controverse.",
      "summary": "Middelburg onderzoekt veiligheidsmogelijkheden op het kruispunt tussen Schroebrug en spoorwegovergang. De gemeente gaat ook met ProRail praten over spoorbomen die tot vijf minuten gesloten kunnen blijven."
    },
    {
      "id": "telegraaf-1265150821",
      "source": "Telegraaf",
      "title": "Elines zoontje Chez stapte op gloeiend hete zwarte tuintegels: ’Zijn voetjes zaten direct aan de grond vastgebrand’",
      "description": "De schrik slaat Eline Eman-Jonk (33) om het hart als ze op haar werk tegen vijf uur een telefoontje krijgt: haar zoontje van anderhalf jaar heeft zijn blote voetjes verbrand op bloedhete, zwarte tuintegels. „Ik hoorde hem schreeuwen op de achtergrond en ben meteen in mijn auto gesprongen.”",
      "url": "https://www.telegraaf.nl/vrouw/elines-zoontje-chez-stapte-op-gloeiend-hete-zwarte-tuintegels-zijn-voetjes-zaten-direct-aan-de-grond-vastgebrand/158316129.html",
      "pubDate": "2026-07-06T10:30:00+00:00",
      "image": "https://prod-img.telegraaf.nl/public/incoming/v40npp-b0031797fjacn40391330c43h172hasbl.jpg/alternates/BASE_SIXTEEN_NINE/B0031797FJACN40391330C43H172HASBL.JPG",
      "duplicate_sources": [
        "Gooi- en Eemlander"
      ],
      "score": 58,
      "category": "Opmerkelijk",
      "location": "Landelijk",
      "reason": "BN'er-incident met veel menselijk drama; past in Opmerkelijk-rubriek.",
      "summary": "Het zoontje van mediapersoondheid Eline Eman-Jonk heeft zijn voetjes ernstig verbrand op bloedhete zwarte tuintegels. Het kind werd naar het ziekenhuis vervoerd."
    },
    {
      "id": "ad-6581645944",
      "source": "AD",
      "title": "TransferTalk | Feyenoord heeft technische staf rond, Glasner tekent bij Nottingham Forest",
      "description": "Het WK is in volle gang, maar er is ook het nodige transfernieuws. Welke spelers en trainers maken een overstap? Hier blijf je op de hoogte van alle ontwikkelingen.",
      "url": "https://www.ad.nl/voetbal/transfertalk-feyenoord-heeft-technische-staf-rond-glasner-tekent-bij-nottingham-forest~ad10f02c/",
      "pubDate": "2026-07-06T10:30:00+00:00",
      "image": "https://images.ad.nl/OWVjODZhYTkxMTY2ZDRkODFmNjYvZGlvLzI3NTIyMzc5MC9maXQtd2lkdGgvNDAw/mika-godts-crysencio-summerville-en-anis-hadj-moussa",
      "score": 2,
      "category": "Overig",
      "location": "Landelijk",
      "reason": "Sportnieuws (transfermarkt) valt buiten PowNed-focus.",
      "summary": "Transferupdate met onder meer Feyenoord dat de technische staf compleet maakt. Trainer Glasner ondertekent contract bij Nottingham Forest."
    },
    {
      "id": "sleutelstad-9013310539",
      "source": "Sleutelstad",
      "title": "Vrouw aangereden door racefietser",
      "description": "Een vrouw die over de Rosenburgherlaan in Voorschoten liep is daar maandagochtend aangereden door een racefietser. Door de klap viel de vrouw en kwam op haar achterhoofd terecht. In verband met de hoge leeftijd van het slachtoffer is ze met de ambulance naar het ziekenhuis vervoerd om daar te worden gecontroleerd en zo nodig te [&#8230;]",
      "url": "https://sleutelstad.nl/2026/07/06/vrouw-aangereden-door-racefietser/",
      "pubDate": "2026-07-06T10:23:04+00:00",
      "image": "",
      "score": 52,
      "category": "Misdaad",
      "location": "Zuid-Holland",
      "reason": "Lokaal misdaad/incident; bejaarde vrouw aangereden door racefietser.",
      "summary": "Een bejaarde vrouw werd maandagochtend aangereden door een racefietser op de Rosenburgherlaan in Voorschoten. Ze kwam op haar achterhoofd terecht en werd ter controle naar het ziekenhuis gebracht."
    },
    {
      "id": "ad-7432976748",
      "source": "AD",
      "title": "Hamas ontbindt bestuursorgaan dat al bijna twintig jaar over de Gazastrook regeert",
      "description": "Hamas heeft het bestuursorgaan ontbonden, waarmee al bijna twee decennia de Gazastrook wordt bestuurd. Dat maakt de groepering maandag bekend tijdens een persconferentie. Daarmee wordt een nieuwe stap gezet in het vredesproces in de regio.",
      "url": "https://www.ad.nl/buitenland/hamas-ontbindt-bestuursorgaan-dat-al-bijna-twintig-jaar-over-de-gazastrook-regeert~ac470a66/",
      "pubDate": "2026-07-06T10:23:00+00:00",
      "image": "https://images.ad.nl/MjBiNjk2ZTFjZWEzODJmNzY3YmIvZGlvLzI3NTYyNjIyOC9maXQtd2lkdGgvNDAw/ismail-al-thawabta-head-of-hamas-government-media-office-addresses-a-press-conference-at-the-al-aqsa-hospital-in-deir-al-balah-central-gaza-strip-on-july-6-2026-palestinian-islamist-movement-hamas-announced-on-july-6-the-dissolution-of-the-body-that-has-governed-the-gaza-strip-for-nearly-two-decades-clearing-the-way-for-a-technocratic-committee-to-implement-civilian-rule-photo-by-eyad-baba-afp",
      "duplicate_sources": [
        "BN De Stem",
        "De Stentor",
        "PZC"
      ],
      "score": 18,
      "category": "Overig",
      "location": "Internationaal",
      "reason": "Buitenlands politiek nieuws zonder Nederlandse relevantie.",
      "summary": "Hamas heeft het bestuursorgaan dat bijna twee decennia de Gazastrook regeert ontbonden. De groepering presenteerde de stap als onderdeel van het vredesproces in de regio."
    },
    {
      "id": "ad-den-haag-7933160604",
      "source": "AD Den Haag",
      "title": "Foreign Tongues releaseparty en een kijkje terug in de tijd met de Rolling Stones in Den Haag",
      "description": "Voor fans van The Rolling Stones is er goed nieuws: vrijdag 10 juli komt het nieuwe album van de Stones, Foreign Tongues, uit. De mannen hebben een mooie band met Den Haag.",
      "url": "https://www.ad.nl/den-haag/foreign-tongues-releaseparty-en-een-kijkje-terug-in-de-tijd-met-de-rolling-stones-in-den-haag~a29d9884/",
      "pubDate": "2026-07-06T10:22:33+00:00",
      "image": "https://images.ad.nl/OWNiNDcxMjk0ZWZlMjc5MTc2MTYvZGlvLzI3NTYyMzE4My9maXQtd2lkdGgvNDAw/het-nieuwe-album-van-rolling-stones-foreign-tongues-komt-10-juli-uit",
      "score": 15,
      "category": "Overig",
      "location": "Zuid-Holland",
      "reason": "Muziekrelease en concertaankondiging; geen politiek of controversieel nieuws.",
      "summary": "The Rolling Stones brengen nieuw album 'Foreign Tongues' uit op 10 juli. De band heeft een sterke binding met Den Haag."
    },
    {
      "id": "de-stentor-5710722982",
      "source": "De Stentor",
      "title": "Camera’s moeten eind maken aan vechtpartijen en vernielingen bij zomeravondbraderie in Ermelo",
      "description": "Vechtpartijen, vernielingen... Het is niet alleen maar gezellig tijdens de jaarlijkse zomeravondbraderie in Ermelo. Daarom neemt de gemeente maatregelen. Er komt onder meer cameratoezicht.",
      "url": "https://www.destentor.nl/ermelo/cameras-moeten-eind-maken-aan-vechtpartijen-en-vernielingen-bij-zomeravondbraderie-in-ermelo~a3e68ca9/",
      "pubDate": "2026-07-06T10:21:00+00:00",
      "image": "https://images.destentor.nl/MzcwMDZiOTYxNTQ4ZDc0OWVmODMvZGlvLzI3NTM2MTA1Ny9maXQtd2lkdGgvNDAw/tijdelijk-cameratoezicht-bij-de-stier-vanwege-risico-op-ongeregeldheden-amersfoort-burgemeester-lucas-bolsius-van-amersfoort-heeft-besloten-tijdelijk-cameratoezicht-in-te-stellen-bij-rotonde-de-stier-de-camera-is-geplaatst-vanwege-het-risico-op-mogelijke-ongeregeldheden-rond-de-wk-wedstrijd-tussen-nederland-en-marokko-die-vannacht-om-03-00-uur-wordt-gespeeld-de-rotonde-is-na-belangrijke-voetbalwedstrijden-vaker-een-verzamelplek-voor-grote-groepen-supporters-met-het-cameratoezicht-wil-de-gemeente-de-situatie-in-de-gaten-houden-en-snel-kunnen-ingrijpen-wanneer-de-openbare-orde-wordt-verstoord-de-camera-biedt-zicht-op-de-rotonde-en-delen-van-onder-meer-de-kamp-de-van-randwijcklaan-de-flierbeeksingel-en-de-scheltussingel-volgens-de-gemeente-wordt-de-camera-alleen-tijdens-de-wedstrijd-en-in-de-periode-daaromheen-gebruikt-buiten-deze-tijden-staat-het-systeem-uit-cameratoezicht-mag-niet-zonder-duidelijke-aanleiding-worden-ingesteld-omdat-het-een-ingrijpend-middel-is-moet-de-gemeente-kunnen-aantonen-dat-er-een-risico-bestaat-voor-de-rust-veiligheid-en-openbare-orde-eerdere-ervaringen-tijdens-internationale-voetbaltoernooien-zijn-voor-de-burgemeester-aanleiding-om-de-maatregel-deze-keer-in-te-zetten",
      "score": 72,
      "category": "Misdaad",
      "location": "Gelderland",
      "reason": "Vechtpartijen en vernielingen op lokaal evenement; misdrijven en burgerveiligheid relevant.",
      "summary": "De zomeravondbraderie in Ermelo wordt geteisterd door vechtpartijen en vernielingen. De gemeente installeert cameratoezicht als preventieve maatregel."
    },
    {
      "id": "nu.nl-6121116236",
      "source": "NU.nl",
      "title": "UEFA haalt hard uit naar FIFA in zaak-Balogun op WK: 'Grens overschreden'",
      "description": "De UEFA heeft maandag in een verklaring uitgehaald naar de FIFA. De Europese voetbalbond begrijpt niets van het besluit om de schorsing van de Amerikaanse spits Folarin Balogun op het WK op te schorten .",
      "url": "https://www.nu.nl/wk-voetbal/6402078/uefa-haalt-hard-uit-naar-fifa-in-zaak-balogun-op-wk-grens-overschreden.html",
      "pubDate": "2026-07-06T10:19:20+00:00",
      "image": "https://images.nu.nl/m/ywwxnyda7zf2_sqr256/525/0/1905/1905/uefa-haalt-hard-uit-naar-fifa-in-zaak-balogun-op-wk-grens-overschreden.jpg",
      "score": 8,
      "category": "Overig",
      "location": "Internationaal",
      "reason": "Voetbalschandaal zonder Nederlandse link; sport is laag prioriteit voor PowNed.",
      "summary": "De UEFA kritiseert de FIFA over de behandeling van speler Folarin Balogun op het WK. De Europese bond betwijfelt het besluit om de schorsing op te schorten."
    },
    {
      "id": "telegraaf-2011557601",
      "source": "Telegraaf",
      "title": "ING neemt minderheidsbelang in Spaanse Singular Bank",
      "description": "ING neemt een minderheidsbelang van ongeveer 40 procent in de Spaanse vermogensbeheerder Singular Bank. Daarmee wil de bank zijn groei in private banking en vermogensbeheer in de Spaanse markt versnellen.",
      "url": "https://www.telegraaf.nl/net-binnen/ing-neemt-minderheidsbelang-in-spaanse-singular-bank/158320283.html",
      "pubDate": "2026-07-06T10:18:41+00:00",
      "image": "https://prod-img.telegraaf.nl/public/incoming/ozwxt-anp-530251565.jpg/alternates/BASE_SIXTEEN_NINE/ANP-530251565.jpg",
      "score": 12,
      "category": "Overig",
      "location": "Landelijk",
      "reason": "Routinematige bedrijfsfinanciering zonder controverse of maatschappelijk belang.",
      "summary": "ING neemt minderheidsbelang van circa 40 procent in Spaanse vermogensbeheerder Singular Bank. De Nederlandse bank wil groei in private banking versnellen."
    },
    {
      "id": "bn-de-stem-8122446310",
      "source": "BN De Stem",
      "title": "Reinier de Ridder weet nu tegen wie hij vecht in volgende UFC-partij: debuut in nieuwe gewichtsklasse",
      "description": "Reinier de Ridder gaat de kooi weer in. De UFC-vechter uit Breda vecht eind augustus zijn tweede gevecht van dit jaar. Het zal een unicum voor De Ridder worden: voor het eerst zal hij in een gewichtsklasse hoger uitkomen.",
      "url": "https://www.bndestem.nl/vechtsport/reinier-de-ridder-weet-nu-tegen-wie-hij-vecht-in-volgende-ufc-partij-debuut-in-nieuwe-gewichtsklasse~ad02feda/",
      "pubDate": "2026-07-06T10:15:19+00:00",
      "image": "https://images.bndestem.nl/MWI3N2Y2MzY3M2UxNmI1NWMyMTYvZGlvLzI3MDkwMjI0OC9maXQtd2lkdGgvNDAw/las-vegas-nevada-march-07-reinier-de-ridder-of-the-netherlands-r-punches-caio-borralho-of-brazil-during-their-middleweight-bout-at-t-mobile-arena-on-march-07-2026-in-las-vegas-nevada-sean-m-haffey-getty-images-afp-photo-by-sean-m-haffey-getty-images-north-america-getty-images-via-afp",
      "score": 25,
      "category": "Overig",
      "location": "Noord-Brabant",
      "reason": "Sportnieuws over UFC-gevecht; sport heeft lage prioriteit voor PowNed.",
      "summary": "UFC-vechter Reinier de Ridder uit Breda vecht eind augustus in een zwaardere gewichtsklasse. Dit wordt zijn tweede gevecht dit jaar."
    },
    {
      "id": "ad-2224717564",
      "source": "AD",
      "title": "Geld moet rollen op Navo-top in Ankara: Europese veiligheid hangt af van lucratieve deals met VS",
      "description": "Tijdens de top in Ankara wil de Navo na een ultiem crisisjaar de diepe interne scheuren lijmen. Het bondgenootschap wordt onder leiding van Mark Rutte steeds meer een soort Marktplaats, waar Amerikaanse veiligheidsgaranties worden gekocht met defensie-orders. Europa heeft zich erbij neergelegd.",
      "url": "https://www.ad.nl/buitenland/geld-moet-rollen-op-navo-top-in-ankara-europese-veiligheid-hangt-af-van-lucratieve-deals-met-vs~a81cade4/",
      "pubDate": "2026-07-06T10:15:18+00:00",
      "image": "https://images.ad.nl/MmM0NjNmYjM1NDI5ZGZmNWZhMzMvZGlvLzI3NTYyMzY0OS9maXQtd2lkdGgvNDAw/prime-minister-bart-de-wever-first-row-3l-dutch-prime-minister-dick-schoof-5l-nato-secretary-general-mark-rutte-c-and-us-president-donald-trump-5r-pose-for-a-family-portrait-at-a-head-of-states-summit-of-the-nato-north-atlantic-treaty-organization-military-alliance-wednesday-25-june-2025-in-the-hague-the-netherlands-belga-photo-eric-lalmand",
      "duplicate_sources": [
        "BN De Stem",
        "De Stentor",
        "PZC"
      ],
      "score": 78,
      "category": "Politiek",
      "location": "Landelijk",
      "reason": "Navo-top onder Rutte-leiding, Amerikaanse veiligheid en Europese defensie-afhankelijkheid.",
      "summary": "De Navo-top in Ankara onder voorzitterschap van Mark Rutte richt zich op interne scheuren na crisisjaar. Europa koopt Amerikaanse veiligheidsgaranties met defensie-orders."
    },
    {
      "id": "ad-1523780797",
      "source": "AD",
      "title": "Vakantie haalt je uit je vertrouwde dagelijkse routine, en dat is maar goed ook",
      "description": "Ga jij binnenkort op vakantie? Leuk, toch? Of zie je er misschien ook tegenop dat je vertrouwde dagelijkse routine op z’n kop wordt gezet? Psycholoog Thijs Launspach vertelt waarom het toch gezond is huis en haard eventjes te verlaten.",
      "url": "https://www.ad.nl/werk/vakantie-haalt-je-uit-je-vertrouwde-dagelijkse-routine-en-dat-is-maar-goed-ook~acf0232a/",
      "pubDate": "2026-07-06T10:15:17+00:00",
      "image": "https://images.ad.nl/MjNjNDhlZjUzYzFiM2E2MDU3YzUvZGlvLzI3NTQ2NzkxNS9maXQtd2lkdGgvNDAw/close-up-of-a-woman-sitting-on-the-airport-chairs-leaning-on-suitcase-front-view-columnist-thijs-launspach",
      "duplicate_sources": [
        "BN De Stem",
        "De Stentor",
        "PZC"
      ],
      "score": 5,
      "category": "Overig",
      "location": "Landelijk",
      "reason": "Psychologisch lifestyleadvies over vakanties; geen nieuws, geen controverse.",
      "summary": "Psycholoog Thijs Launspach bespreekt voordelen van vakantie voor psychologisch welzijn. Hij betoogt dat verandering van routine gezond is."
    },
    {
      "id": "telegraaf-1947695594",
      "source": "Telegraaf",
      "title": "Astrid Holleeder emotioneel op Instagram: ’Vandaag 5 jaar geleden dat de aanslag op Peter plaatsvond’",
      "description": "Astrid Holleeder staat maandag in een bericht op Instagram stil bij de aanslag op Peter R. de Vries, vijf jaar geleden. De schrijfster deelt dat zij de overleden misdaadverslaggever mist, en dat dat ook geldt voor de mensen die hij tijdens zijn leven heeft geholpen.",
      "url": "https://www.telegraaf.nl/entertainment/media/astrid-holleeder-emotioneel-op-instagram-vandaag-5-jaar-geleden-dat-de-aanslag-op-peter-plaatsvond/158320015.html",
      "pubDate": "2026-07-06T10:14:14+00:00",
      "image": "https://prod-img.telegraaf.nl/public/entertainment/media/bzl3r3-anp-534643054.jpg/alternates/BASE_SIXTEEN_NINE/ANP-534643054.jpg",
      "score": 48,
      "category": "Opmerkelijk",
      "location": "Landelijk",
      "reason": "Herdenking misdaadverslaggever Peter R. de Vries; BN'er en misdaadschandaal relevant.",
      "summary": "Astrid Holleeder herdenkt vijf jaar na de aanslag op misdaadverslaggever Peter R. de Vries. Zij deelt op Instagram haar emoties en erkent zijn impact."
    },
    {
      "id": "ad-2946180104",
      "source": "AD",
      "title": "Het grinniken verging mij toen ik die verschrikkelijke Pierre van Hooijdonk hoorde spreken bij de NOS",
      "description": "Onze nationale chagrijn Pierre van Hooijdonk bedacht gisteravond live op tv het perfecte argument tégen een vrouwelijke bondscoach, zag Angela de Jong. Al die spelers van tegenwoordig uit andere culturen zouden het niet aankunnen.",
      "url": "https://www.ad.nl/binnenland/het-grinniken-verging-mij-toen-ik-die-verschrikkelijke-pierre-van-hooijdonk-hoorde-spreken-bij-de-nos~ab2fe83d2/",
      "pubDate": "2026-07-06T10:14:00+00:00",
      "image": "https://images.ad.nl/ZDRjYzQwZTk3NjM2NWY1YTYxMTcvZGlvLzI2MjQ0OTAyOC9maXQtd2lkdGgvNDAw/07-04-2025-angela-de-jong-foto-shody-careman",
      "duplicate_sources": [
        "BN De Stem",
        "De Stentor",
        "PZC"
      ],
      "score": 72,
      "category": "Media",
      "location": "Landelijk",
      "reason": "Cancel culture/omroep-kritiek: commentaar op NOS-uitzending en controversiële uitspraken voetbalanalyticus.",
      "summary": "Angela de Jong kritiseert voetbalanalyticus Pierre van Hooijdonk voor zijn commentaar op vrouwelijke bondscoach tijdens NOS-uitzending. Van Hooijdonk zou discriminerende opmerkingen hebben gemaakt over spelers uit andere culturen."
    },
    {
      "id": "nu.nl-4139191197",
      "source": "NU.nl",
      "title": "Toeristen gaan deze zomer ondanks hitte 'gewoon' massaal naar Spanje",
      "description": "Spanje bereikt dit jaar waarschijnlijk de grens van honderd miljoen buitenlandse toeristen. Dat heeft de minister van Toerisme Jordi Hereu maandag gezegd. De Spaanse zomer wordt weliswaar steeds heter en droger, met bosbranden tot gevolg, maar dat staat het massatoerisme niet in de weg.",
      "url": "https://www.nu.nl/economie/6402079/toeristen-gaan-deze-zomer-ondanks-hitte-gewoon-massaal-naar-spanje.html",
      "pubDate": "2026-07-06T10:13:20+00:00",
      "image": "https://images.nu.nl/m/mwfxhrfavtn2_sqr256/1976/0/3936/3936/toeristen-gaan-deze-zomer-ondanks-hitte-gewoon-massaal-naar-spanje.jpg",
      "score": 15,
      "category": "Overig",
      "location": "Internationaal",
      "reason": "Routinematig buitenland zonder Nederlandse link of maatschappelijk impact voor PowNed-lezers.",
      "summary": "Spanje bereikt dit jaar waarschijnlijk de grens van honderd miljoen buitenlandse toeristen. Dat heeft de minister van Toerisme Jordi Hereu maandag gezegd. De Spaanse zomer wordt weliswaar steeds heter"
    },
    {
      "id": "sleutelstad-1516580475",
      "source": "Sleutelstad",
      "title": "Leidse poes Ollie reist onder motorkap naar Vlaardings kunstenaarsstraatje",
      "description": "Ollie, een tweejarige kat uit Leiden, heeft vorige week de reis van zijn leven gemaakt. Het beestje belandde onder de motorkap van een auto en kwam pas in Vlaardingen, vlak bij Rotterdam, weer tevoorschijn. De poes legde ruim vijftig kilometer af bij een draaiende motor, maar kwam er zonder kleerscheuren vanaf. De Leidse fotokunstenaar Willem [&#8230;]",
      "url": "https://sleutelstad.nl/2026/07/06/leidse-poes-ollie-reist-onder-motorkap-naar-vlaardings-kunstenaarsstraatje/",
      "pubDate": "2026-07-06T10:12:02+00:00",
      "image": "",
      "score": 68,
      "category": "Opmerkelijk",
      "location": "Zuid-Holland",
      "reason": "Bizarre dierenschiedenis: kat reist 50km onder motorkap van Leiden naar Vlaardingen zonder letsel.",
      "summary": "Ollie, een tweejarige kat uit Leiden, heeft vorige week de reis van zijn leven gemaakt. Het beestje belandde onder de motorkap van een auto en kwam pas in Vlaardingen, vlak bij Rotterdam, weer tevoors"
    },
    {
      "id": "telegraaf-8216703878",
      "source": "Telegraaf",
      "title": "UEFA schaart zich achter België in rode kaart-affaire, Blatter valt Trump en Infantino aan: ’Maak van voetbal geen speelterrein voor politieke macht’",
      "description": "De Europese voetbalbond spreekt zich in een officieel statement ferm uit tegen het besluit van de FIFA om de rode kaart van Floralin Balogun te seponeren. De Amerikaanse spits werd van het veld gestuurd tegen Bosnië & Herzegovina, maar lijkt na inmenging van de Amerikaanse president Donald Trump toch beschikbaar voor de kwartfinale van het WK 2026. UEFA schaart zich achter België, de eerstvolgende",
      "url": "https://www.telegraaf.nl/sport/voetbal/uefa-schaart-zich-achter-belgie-in-rode-kaart-affaire-blatter-valt-trump-en-infantino-aan-maak-van-voetbal-geen-speelterrein-voor-politieke-macht/158316620.html",
      "pubDate": "2026-07-06T10:11:00+00:00",
      "image": "https://prod-img.telegraaf.nl/public/incoming/5dioxw-file86l7kks43disn7d2ech/alternates/BASE_SIXTEEN_NINE/file86l7kks43disn7d2ech",
      "score": 8,
      "category": "Overig",
      "location": "Internationaal",
      "reason": "Buitenlands voetbal zonder Nederlandse directe relevantie; geen PowNed-kernthema's.",
      "summary": "De Europese voetbalbond spreekt zich in een officieel statement ferm uit tegen het besluit van de FIFA om de rode kaart van Floralin Balogun te seponeren. De Amerikaanse spits werd van het veld gestuu"
    },
    {
      "id": "telegraaf-3818429799",
      "source": "Telegraaf",
      "title": "LIVE | Hamas ontbindt eigen bestuursorgaan in de Gazastrook",
      "description": "De Verenigde Staten en Iran voeren opnieuw aanvallen op elkaar uit. De vredesonderhandelingen tussen de twee landen staan op losse schroeven en de onrust in het Midden-Oosten groeit. Volg de laatste ontwikkelingen in het Midden-Oosten in ons liveblog.",
      "url": "https://www.telegraaf.nl/buitenland/live-hamas-ontbindt-eigen-bestuursorgaan-in-de-gazastrook/158308847.html",
      "pubDate": "2026-07-06T10:11:00+00:00",
      "image": "https://prod-img.telegraaf.nl/public/incoming/73s6uf-file86k6f416yjoz14xvi26/alternates/BASE_SIXTEEN_NINE/file86k6f416yjoz14xvi26",
      "score": 10,
      "category": "Overig",
      "location": "Internationaal",
      "reason": "Routinematig Midden-Oosten-conflict zonder Nederlandse link of unieke hoek.",
      "summary": "De Verenigde Staten en Iran voeren opnieuw aanvallen op elkaar uit. De vredesonderhandelingen tussen de twee landen staan op losse schroeven en de onrust in het Midden-Oosten groeit. Volg de laatste o"
    },
    {
      "id": "nos-9377735388",
      "source": "NOS",
      "title": "Man die acht dagen onder puin in Venezuela lag doet verhaal: 'Waarom ik?'",
      "description": "Hij groeide in korte tijd uit tot een symbool van hoop voor Venezuela: Hernán Gil, de man die acht dagen na de verwoestende aardbevingen levend onder het puin vandaan werd gehaald. Drie dagen na de spectaculaire reddingsactie doet hij zijn verhaal. Het gaat naar omstandigheden goed met Gil. Hij zit alweer in een stoel, zijn arm nog in een mitella. De afgelopen dagen zijn meerdere journalisten bij ",
      "url": "https://nos.nl/artikel/2621877-man-die-acht-dagen-onder-puin-in-venezuela-lag-doet-verhaal-waarom-ik",
      "pubDate": "2026-07-06T10:10:26+00:00",
      "image": "https://images.cdn.nos.nl/3/j/K/a/v/W/DkQXP3PqjaAa2rcndSJMrvYbD6ki7y7jexT2J8/5x423x3984x2241-1024x576.webp",
      "score": 12,
      "category": "Overig",
      "location": "Internationaal",
      "reason": "Buitenlands humanitair nieuwsfeit zonder Nederlandse hoek of relevantie.",
      "summary": "Hij groeide in korte tijd uit tot een symbool van hoop voor Venezuela: Hernán Gil, de man die acht dagen na de verwoestende aardbevingen levend onder het puin vandaan werd gehaald. Drie dagen na de sp"
    },
    {
      "id": "open-rotterdam-1078038362",
      "source": "OPEN Rotterdam",
      "title": "Proefpark De Punt groeide uit tot groene ontmoetingsplek in Bospolder-Tussendijken",
      "description": "Zo’n twintig jaar geleden was Proefpark de Punt in Bospolder-Tussendijken een plek waar buurtbewoners samenkwamen en kinderen volop konden buitenspelen. In het tweede deel van aflevering drie van Cult, Underground en Avant Garde in de jaren 0-10 zien we enthousiaste gebruikers en nog enthousiastere kinderen. Iedereen wil toch een Proefpark voor de deur. Rini Biemans [&#8230;] Het bericht Proefpark",
      "url": "https://openrotterdam.nl/proefpark-de-punt-groeide-uit-tot-groene-ontmoetingsplek-in-bospolder-tussendijken/",
      "pubDate": "2026-07-06T10:06:32+00:00",
      "image": "",
      "score": 25,
      "category": "Overig",
      "location": "Zuid-Holland",
      "reason": "Lokaal cultureel-historisch stuk; te specifiek lokaal zonder politieke/controversiële kant.",
      "summary": "Zo’n twintig jaar geleden was Proefpark de Punt in Bospolder-Tussendijken een plek waar buurtbewoners samenkwamen en kinderen volop konden buitenspelen. In het tweede deel van aflevering drie van Cult"
    },
    {
      "id": "nos-2174577685",
      "source": "NOS",
      "title": "Zeker 25 doden bij gevangenisopstand in Sri Lanka",
      "description": "Bij een opstand in een gevangenis in Sri Lanka zijn tot nu toe 25 mensen om het leven gekomen. Dat melden lokale functionarissen aan persbureau Reuters. Ook raakten zo'n honderd mensen gewond. Onder de slachtoffers zijn zowel gevangenen als gevangenispersoneel, zeggen lokale media. De opstand begon zondagochtend lokale tijd en duurde tot vanochtend. Reuters schrijft dat de politie en bewakers nog ",
      "url": "https://nos.nl/artikel/2621875-zeker-25-doden-bij-gevangenisopstand-in-sri-lanka",
      "pubDate": "2026-07-06T10:04:19+00:00",
      "image": "https://images.cdn.nos.nl/1/4/J/3/m/D/9YZEtesprjr2pUW13h1z8xmEyMQb9333RwCaHRF/48x4x560x315-560x315.webp",
      "score": 8,
      "category": "Overig",
      "location": "Internationaal",
      "reason": "Buitenlands misdaad-feit zonder Nederlandse link of specifieke PowNed-relevantie.",
      "summary": "Bij een opstand in een gevangenis in Sri Lanka zijn tot nu toe 25 mensen om het leven gekomen. Dat melden lokale functionarissen aan persbureau Reuters. Ook raakten zo'n honderd mensen gewond. Onder d"
    },
    {
      "id": "telegraaf-2659988204",
      "source": "Telegraaf",
      "title": "Mysterieuze ’ruimteballen’ spoelen aan op Australisch strand en kunnen resten van giftige raketbrandstof bevatten",
      "description": "Op stranden in het noorden van Queensland zijn zes mysterieuze ’ruimteballen’ aangespoeld die mogelijk afkomstig zijn van raketlanceringen. De Australische ruimtevaartorganisatie onderzoekt de herkomst.",
      "url": "https://www.telegraaf.nl/buitenland/mysterieuze-ruimteballen-spoelen-aan-op-australisch-strand-en-kunnen-resten-van-giftige-raketbrandstof-bevatten/158318840.html",
      "pubDate": "2026-07-06T10:01:35+00:00",
      "image": "https://prod-img.telegraaf.nl/public/incoming/4mq5yj-bal1.jpg/alternates/BASE_SIXTEEN_NINE/Bal1.jpg",
      "score": 15,
      "category": "Overig",
      "location": "Internationaal",
      "reason": "Buitenlands ruimtevaartnieuws zonder Nederlandse relevantie of controversiële hoek.",
      "summary": "Zes mysterieuze ballen gespoeld op Australisch strand mogelijk van raketlanceringen. Australische ruimtevaartorganisatie onderzoekt herkomst."
    },
    {
      "id": "telegraaf-58285584",
      "source": "Telegraaf",
      "title": "‘Terecht dat MAFS met pauze gaat’",
      "description": "Het realityprogramma Married at first sight gaat een seizoen overslaan. In deze aflevering van Strikt Privé bespreken Jan Uriot en Wilson Boldewijn waarom dit terecht is. Verder gaat Dave Roelvink professioneel boksen. Op 19 september maakt hij zijn debuut bij Boxing Gladiators tijdens een evenement in Rotterdam. Gaat hij dit redden? En: volgens de Privé-icoon moet Robbert ten Brink op zoek naar e",
      "url": "https://www.telegraaf.nl/podcast/terecht-dat-mafs-met-pauze-gaat/158318190.html",
      "pubDate": "2026-07-06T10:01:00+00:00",
      "image": "https://prod-img.telegraaf.nl/public/incoming/sj33b1-369.jpeg/alternates/BASE_SIXTEEN_NINE/369.jpeg",
      "score": 35,
      "category": "Media",
      "location": "Zuid-Holland",
      "reason": "Realityshow-onderwerpen relevanter dan sport, maar MAFS-pauze zwak; Roelvink-boksen matig.",
      "summary": "Married at first sight gaat seizoen overslaan, redactie bespreekt waarom. Dave Roelvink debuteert als bokser 19 september in Rotterdam."
    },
    {
      "id": "telegraaf-5060954399",
      "source": "Telegraaf",
      "title": "Oud tegen nieuw bij burenstrijd op WK 2026: duel met Lamine Yamal (18) kan zomaar Cristiano Ronaldo’s (41) zwanenzang worden",
      "description": "Het is een van de meest aansprekende affiches in de achtste finales van het WK 2026. De derby tussen de Iberische buurlanden Spanje en Portugal in Dallas, op respectievelijk 7956 en 7625 kilometer van de hoofdsteden Madrid en Lissabon. De Iberische broederstrijd is ook een duel tussen de 41-jarige wereldster Cristiano Ronaldo, die aan de vooravond van zijn voetbalpensioen staat, en de 18-jarige La",
      "url": "https://www.telegraaf.nl/sport/voetbal/oud-tegen-nieuw-bij-burenstrijd-op-wk-2026-duel-met-lamine-yamal-18-kan-zomaar-cristiano-ronaldos-41-zwanenzang-worden/158287692.html",
      "pubDate": "2026-07-06T10:00:00+00:00",
      "image": "https://prod-img.telegraaf.nl/public/incoming/oxijdt-collage-flexible-20260705.jpg/alternates/BASE_SIXTEEN_NINE/collage-flexible-20260705.jpg",
      "score": 8,
      "category": "Overig",
      "location": "Internationaal",
      "reason": "Voetbaljournaalistiek over WK 2026; niet PowNed's kernthema's, geen Nederlands hoek.",
      "summary": "Spanje-Portugal achtste finale WK 2026 in Dallas mogelijk Ronaldo's afscheidstoernooi. Duel tussen 41-jarige Ronaldo en 18-jarige Yamal."
    },
    {
      "id": "de-stentor-832478499",
      "source": "De Stentor",
      "title": "Vorige week benoemd, nu al opgestapt: omstreden Ton Koenderink vertrekt als wethouder",
      "description": "De vorige week benoemde en in opspraak geraakte wethouder Ton Koederink van de gemeente Berkelland stapt per direct op. Hij heeft ook per direct het lidmaatschap van zijn partij Samen voor Berkelland opgezegd.",
      "url": "https://www.destentor.nl/berkelland/vorige-week-benoemd-nu-al-opgestapt-omstreden-ton-koenderink-vertrekt-als-wethouder~a58668c8/",
      "pubDate": "2026-07-06T09:59:00+00:00",
      "image": "https://images.destentor.nl/NTI1ODcxOTlkODY5NTU4NWNkZGEvZGlvLzI3NTQwMDMwNS9maXQtd2lkdGgvNDAw/nlbeeld-tt20260630-37219-borculo-ton-koenderink-wordt-benoemd-tot-wethouder-van-de-gemeente-berkelland-foto-ingrid-sweers-isf20260630",
      "score": 72,
      "category": "Politiek",
      "location": "Gelderland",
      "reason": "Lokale politieke botsing: omstreden wethouder treedt af na benoeming—regionaal schandaal sterk.",
      "summary": "Wethouder Ton Koenderink van gemeente Berkelland stapt op dag na benoeming. Hij zegt ook lidmaatschap partij Samen voor Berkelland op."
    },
    {
      "id": "nos-8547849240",
      "source": "NOS",
      "title": "Sterrenkundigen komen met ruimtetelescoop dichter bij 'kindertijd van het heelal'",
      "description": "Wetenschappers hebben 31 extreem verre quasars ontdekt met ruimtetelescoop Euclid. Dat zijn heldere kernen van sterrenstelsels. Niet eerder werden quasars op zulke afstanden ontdekt. Twee van deze kernen schenen toen het heelal pas 670 miljoen jaar oud was. Dat is zo'n 5 procent van de huidige leeftijd van het heelal. Ze liggen op ruim 13 miljard lichtjaar afstand van de aarde. De ontdekking, waar",
      "url": "https://nos.nl/artikel/2621874-sterrenkundigen-komen-met-ruimtetelescoop-dichter-bij-kindertijd-van-het-heelal",
      "pubDate": "2026-07-06T09:58:27+00:00",
      "image": "https://images.cdn.nos.nl/3/A/J/K/B/K/ewTV3sHjPJLzw38QMwWEXn71Ff5KwqabWkvxNPj/2x31x1504x846-1024x576.webp",
      "score": 5,
      "category": "Overig",
      "location": "Internationaal",
      "reason": "Zuivere wetenschap zonder Nederlandse hoek, controverse of politieke relevantie.",
      "summary": "Sterrenkundigen ontdekken 31 verre quasars met ruimtetelescoop Euclid. Twee kernen dateren van toen heelal 670 miljoen jaar oud was."
    },
    {
      "id": "telegraaf-4202895806",
      "source": "Telegraaf",
      "title": "Hartverwarmende beelden: papegaai overleeft 10 dagen onder puin in Venezuela",
      "description": "Brandweerlieden in de Venezolaanse kuststaat La Guaira hebben een papegaai gered uit het puin nadat zware aardbevingen het gebied hadden verwoest.",
      "url": "https://www.telegraaf.nl/video/hartverwarmende-beelden-papegaai-overleeft-10-dagen-onder-puin-in-venezuela/158319351.html",
      "pubDate": "2026-07-06T09:56:00+00:00",
      "image": "https://prod-img.telegraaf.nl/public/incoming/r8ykfh-vogel.jpg/alternates/BASE_SIXTEEN_NINE/Vogel.jpg",
      "score": 12,
      "category": "Overig",
      "location": "Internationaal",
      "reason": "Hartverwarmend dierenverhaal uit Venezuela; geen PowNed-thema's, geen Nederlandse link.",
      "summary": "Brandweerlieden in Venezuela redden papegaai uit puin na zware aardbevingen. Vogel overleefde 10 dagen onder het verwoeste materiaal."
    },
    {
      "id": "telegraaf-527524885",
      "source": "Telegraaf",
      "title": "Spectaculaire goudroof Rotterdam: verdachten blijven weg uit Nederland",
      "description": "De twee mannen die verdacht worden van een spectaculaire goudroof in 2018 of 2019 in Rotterdam, zijn niet van plan zich in de rechtbank te komen melden. Tjeerd K. (45) en Thomas B. (44) zijn spoorloos sinds de roof aan het licht kwam. De buit is destijds geschat op 40 miljoen euro, maar door de fors gestegen goudprijs wordt inmiddels gesproken over mogelijk 100 miljoen euro.",
      "url": "https://www.telegraaf.nl/binnenland/spectaculaire-goudroof-rotterdam-verdachten-blijven-weg-uit-nederland/158311210.html",
      "pubDate": "2026-07-06T09:56:00+00:00",
      "image": "https://prod-img.telegraaf.nl/public/incoming/8fmqi4-file86jypm7uzt0143e9ohpj/alternates/BASE_SIXTEEN_NINE/file86jypm7uzt0143e9ohpj",
      "score": 78,
      "category": "Misdaad",
      "location": "Zuid-Holland",
      "reason": "Spectaculaire openstaande goudroof Rotterdam (100 mln euro); verdachten voortvluchtig—hard misdaadverhaal.",
      "summary": "Twee verdachten van spectaculaire goudroof Rotterdam (2018/2019) zijn spoorloos. Buit geschat op 40–100 miljoen euro afhankelijk goudprijzen."
    },
    {
      "id": "gooi--en-eemlander-1745679305",
      "source": "Gooi- en Eemlander",
      "title": "Macron betuigt solidariteit met getroffenen bosbranden",
      "description": "De Franse president Emmanuel Macron heeft zijn solidariteit getoond met de getroffenen van de bosbranden in het zuiden van Frankrijk. Daar zijn duizenden mensen geëvacueerd. Macron laat via X ook weten dankbaar te zijn voor de inzet van veiligheids- en hulpdiensten en lokale bestuurders. „Laten we overal alert blijven en de veiligheidsvoorschriften strikt opvolgen”, aldus de president.",
      "url": "https://www.gooieneemlander.nl/buitenland/macron-betuigt-solidariteit-met-getroffenen-bosbranden/158319612.html",
      "pubDate": "2026-07-06T09:49:32+00:00",
      "image": "https://prod-img.gooieneemlander.nl/public/buitenland/z9yxn3-41e39735-86fc-475e-9989-ca0acf33b5a2-tmg-webfeed-bui-anp060726097-1.jpeg/alternates/BASE_SIXTEEN_NINE/41e39735-86fc-475e-9989-ca0acf33b5a2_tmg-webfeed-bui_ANP060726097-1.jpeg",
      "score": 10,
      "category": "Overig",
      "location": "Internationaal",
      "reason": "Routinematig buitenlands noodweer zonder Nederlandse hoek of controversiële relevantie.",
      "summary": "Macron betuigt solidariteit met slachtoffers bosbranden in Zuid-Frankrijk. Duizenden geëvacueerd; president prijst veiligheids- en hulpdiensten."
    },
    {
      "id": "nos-2358603899",
      "source": "NOS",
      "title": "Gelijkvloers en in een hofje: 420 miljoen extra voor seniorenwoningen",
      "description": "Het kabinet geeft in de komende jaren 420 miljoen euro extra uit aan nieuwe woningen voor ouderen. Veel senioren willen verhuizen naar een kleinere, gelijkvloerse woning, maar kunnen geen geschikte plek vinden. De bouw van nieuwe huizen gaat niet snel genoeg, volgens onderzoek van het ministerie van Binnenlandse Zaken. De nieuwe bouwsubsidie moet dat veranderen. Volgens het ministerie is er vooral",
      "url": "https://nos.nl/artikel/2621872-gelijkvloers-en-in-een-hofje-420-miljoen-extra-voor-seniorenwoningen",
      "pubDate": "2026-07-06T09:48:04+00:00",
      "image": "https://images.cdn.nos.nl/5/7/k/G/K/D/NbgSntrjka1cdGe1boKoGca1NzRWhEfujsxTJ4y/0x327x4000x2250-1024x576.webp",
      "score": 68,
      "category": "Politiek",
      "location": "Landelijk",
      "reason": "Kabinetsbesluit over seniorenwoningen relevant, maar beperkt controversieel of eigenzinnig.",
      "summary": "Het kabinet investeert 420 miljoen euro extra in seniorenwoningen vanwege tekort aan gelijkvloerse huizen. De subsidie moet de bouwsnelheid versnellen."
    },
    {
      "id": "ad-583838673",
      "source": "AD",
      "title": "Waarom je zonnepanelen niet werken als de stroom er ineens af gaat en nog vier vragen",
      "description": "Poef! Ineens ging de televisie uit, het internet deed het niet meer en buiten vielen stoplichten uit. Er was al tijden voor gewaarschuwd. Zondag gebeurde het rond Tilburg voor het eerst. Om overbelasting te voorkomen zette Enexis de stroom uit.",
      "url": "https://www.ad.nl/binnenland/waarom-je-zonnepanelen-niet-werken-als-de-stroom-er-ineens-af-gaat-en-nog-vier-vragen~a981248a/",
      "pubDate": "2026-07-06T09:46:00+00:00",
      "image": "https://images.ad.nl/ZTAyNGM4NjQ2YzZlNjkyOGMxMjAvZGlvLzI1NjYwMzg5NC9maXQtd2lkdGgvNDAw/flikkerend-licht",
      "duplicate_sources": [
        "De Stentor",
        "PZC"
      ],
      "score": 64,
      "category": "Misdaad",
      "location": "Noord-Brabant",
      "reason": "Stroomuitval Tilburg heeft maatschappelijke impact, maar geen scandaal of controversieel element.",
      "summary": "Enexis zette zondagavond rond Tilburg de stroom uit om overbelasting te voorkomen. Veel huishoudens waren onvoorbereid op het gevolg."
    },
    {
      "id": "bn-de-stem-2095836975",
      "source": "BN De Stem",
      "title": "Waarom Enexis de stroom meteen moest uitzetten en nog vier vragen",
      "description": "Poef! Ineens ging de televisie uit, het internet deed het niet meer en buiten vielen stoplichten uit. Er was al tijden voor gewaarschuwd. Zondag gebeurde het rond Tilburg voor het eerst. Om overbelasting te voorkomen zette Enexis de stroom uit.",
      "url": "https://www.bndestem.nl/tilburg/waarom-enexis-de-stroom-meteen-moest-uitzetten-en-nog-vier-vragen~a981248a/",
      "pubDate": "2026-07-06T09:46:00+00:00",
      "image": "https://images.bndestem.nl/ZTAyNGM4NjQ2YzZlNjkyOGMxMjAvZGlvLzI1NjYwMzg5NC9maXQtd2lkdGgvNDAw/flikkerend-licht",
      "score": 64,
      "category": "Misdaad",
      "location": "Noord-Brabant",
      "reason": "Lokaal stroomuitval-verhaal, dubbel met AD-artikel; regionale relevantie maar geen bijzonder PowNed-angle.",
      "summary": "Enexis zette zondag rond Tilburg noodgedwongen stroom uit tegen overbelasting. Gevolgen voor huishoudens en verkeer waren direct merkbaar."
    },
    {
      "id": "ad-rotterdam-1372598858",
      "source": "AD Rotterdam",
      "title": "Favorieten van Rotterdammers: 6 x tips van locals",
      "description": "De beste tips in de stad? Die krijg je van de mensen die er wonen! Van een vegan kaascroissant op de Rotterdamse Oogstmarkt tot betaalbare dimsum: zes locals delen hun favoriete plekken in Rotterdam.",
      "url": "https://www.ad.nl/rotterdam/favorieten-van-rotterdammers-6-x-tips-van-locals~a2858bf3/",
      "pubDate": "2026-07-06T09:45:00+00:00",
      "image": "https://images.ad.nl/NjQ4NjQ0MzQ0MmRmNWZjNWFkYzQvZGlvLzI3NTQyNDU1MC9maXQtd2lkdGgvNDAw/deze-locals-delen-hun-rotterdamse-tips-op-indebuurt",
      "score": 12,
      "category": "Overig",
      "location": "Zuid-Holland",
      "reason": "Lifestyle-tips zonder nieuws, schandaal of maatschappelijke relevantie voor PowNed.",
      "summary": "Zes Rotterdammers delen hun favoriete plekken in de stad. Artikel bevat tips voor vegan eten en dimsum."
    }
  ]
}