{
  "generatedAt": "2026-07-05T09:28:02.114609+00:00",
  "stats": {
    "feeds_total": 43,
    "feeds_succeeded": 26,
    "feeds_failed": 17,
    "items_collected": 654,
    "items_after_dedupe": 60,
    "items_scored": 60,
    "items_high_score": 11
  },
  "fetchedFeeds": [
    {
      "source": "NOS",
      "url": "https://feeds.nos.nl/nosnieuwsalgemeen",
      "count": 20
    },
    {
      "source": "NOS",
      "url": "https://feeds.nos.nl/nosnieuwsbinnenland",
      "count": 20
    },
    {
      "source": "NOS",
      "url": "https://feeds.nos.nl/nosnieuwspolitiek",
      "count": 9
    },
    {
      "source": "NOS",
      "url": "https://feeds.nos.nl/nosnieuwsopmerkelijk",
      "count": 3
    },
    {
      "source": "NU.nl",
      "url": "https://www.nu.nl/rss/algemeen",
      "count": 30
    },
    {
      "source": "Telegraaf",
      "url": "https://www.telegraaf.nl/rss",
      "count": 50
    },
    {
      "source": "Telegraaf",
      "url": "https://www.telegraaf.nl/binnenland/rss",
      "count": 43
    },
    {
      "source": "AD",
      "url": "https://www.ad.nl/home/rss.xml",
      "count": 30
    },
    {
      "source": "AD",
      "url": "https://www.ad.nl/binnenland/rss.xml",
      "count": 30
    },
    {
      "source": "Volkskrant",
      "url": "https://www.volkskrant.nl/nieuws-achtergrond/rss.xml",
      "count": 0
    },
    {
      "source": "Trouw",
      "url": "https://www.trouw.nl/home/rss.xml",
      "count": 60
    },
    {
      "source": "BN De Stem",
      "url": "https://www.bndestem.nl/home/rss.xml",
      "count": 30
    },
    {
      "source": "De Stentor",
      "url": "https://www.destentor.nl/home/rss.xml",
      "count": 30
    },
    {
      "source": "PZC",
      "url": "https://www.pzc.nl/home/rss.xml",
      "count": 30
    },
    {
      "source": "Gooi- en Eemlander",
      "url": "https://www.gooieneemlander.nl/rss",
      "count": 49
    },
    {
      "source": "Omroep Brabant",
      "url": "https://www.omroepbrabant.nl/rss",
      "count": 25
    },
    {
      "source": "RTV Noord",
      "url": "https://www.rtvnoord.nl/rss",
      "count": 23
    },
    {
      "source": "Crimesite",
      "url": "https://www.crimesite.nl/feed/",
      "count": 11
    },
    {
      "source": "Regio 15 (Den Haag)",
      "url": "https://regio15.nl/feed/",
      "count": 0
    },
    {
      "source": "AD Den Haag",
      "url": "https://www.ad.nl/den-haag/rss.xml",
      "count": 30
    },
    {
      "source": "AD Rotterdam",
      "url": "https://www.ad.nl/rotterdam/rss.xml",
      "count": 30
    },
    {
      "source": "Dagblad010",
      "url": "https://dagblad010.nl/feed/",
      "count": 56
    },
    {
      "source": "Den Haag Centraal",
      "url": "https://www.denhaagcentraal.net/feed/",
      "count": 2
    },
    {
      "source": "Dordt Centraal",
      "url": "https://dordtcentraal.nl/feed/",
      "count": 10
    },
    {
      "source": "OPEN Rotterdam",
      "url": "https://openrotterdam.nl/feed/",
      "count": 8
    },
    {
      "source": "Sleutelstad",
      "url": "https://sleutelstad.nl/feed/",
      "count": 25
    }
  ],
  "failedFeeds": [
    {
      "source": "RTL",
      "url": "https://www.rtlnieuws.nl/service/rss/nieuws/index.xml",
      "error": "http: 404 Client Error: Not Found for url: https://www.rtl.nl/service/rss/nieuws/index.xml"
    },
    {
      "source": "Hart van Nederland",
      "url": "https://www.hartvannederland.nl/nieuws/rss.xml",
      "error": "http: 404 Client Error: Not Found for url: https://www.hartvannederland.nl/nieuws/rss.xml"
    },
    {
      "source": "Omroep West",
      "url": "https://www.omroepwest.nl/rss",
      "error": "http: 404 Client Error: Not Found for url: https://www.omroepwest.nl/rss"
    },
    {
      "source": "NH Nieuws",
      "url": "https://www.nhnieuws.nl/rss",
      "error": "parse: <unknown>:2:5449: not well-formed (invalid token)"
    },
    {
      "source": "L1 Limburg",
      "url": "https://www.l1.nl/rss",
      "error": "http: 404 Client Error: Not Found for url: https://www.l1.nl/rss"
    },
    {
      "source": "AT5",
      "url": "https://www.at5.nl/rss",
      "error": "parse: <unknown>:2:4802: not well-formed (invalid token)"
    },
    {
      "source": "Rijnmond",
      "url": "https://www.rijnmond.nl/rss",
      "error": "http: 404 Client Error: Not Found for url: https://www.rijnmond.nl/rss"
    },
    {
      "source": "RTV Utrecht",
      "url": "https://www.rtvutrecht.nl/rss",
      "error": "parse: <unknown>:2:0: syntax error"
    },
    {
      "source": "Politie",
      "url": "https://www.politie.nl/rss/nieuws/",
      "error": "http: 404 Client Error: Not Found for url: https://www.politie.nl/rss/nieuws/"
    },
    {
      "source": "De Havenloods",
      "url": "https://www.dehavenloods.nl/feed/",
      "error": "http: 404 Client Error: Not Found for url: https://www.dehavenloods.nl/feed"
    },
    {
      "source": "Leidsch Dagblad",
      "url": "https://www.leidschdagblad.nl/rss.xml",
      "error": "http: 403 Client Error: Forbidden for url: https://www.leidschdagblad.nl/rss.xml"
    },
    {
      "source": "Hart van Holland",
      "url": "https://www.hartvanzuidplas.nl/feed/",
      "error": "http: 404 Client Error: Not Found for url: https://www.hartvanzuidplas.nl/feed"
    },
    {
      "source": "Briels Nieuwsland",
      "url": "https://www.brielsnieuwsland.nl/feed/",
      "error": "http: 404 Client Error: Not Found for url: https://www.brielsnieuwsland.nl/feed"
    },
    {
      "source": "Delft op Zondag",
      "url": "https://www.delftopzondag.nl/feed/",
      "error": "http: 404 Client Error: Not Found for url: https://www.delftopzondag.nl/feed"
    },
    {
      "source": "Het Kontakt",
      "url": "https://www.hetkontakt.nl/feed/",
      "error": "http: 404 Client Error: Not Found for url: https://www.hetkontakt.nl/feed"
    },
    {
      "source": "Kijk op Zuid-Holland",
      "url": "https://www.kijkopzuid-holland.nl/feed/",
      "error": "http: HTTPSConnectionPool(host='www.kijkopzuid-holland.nl', port=443): Max retries exceeded with url: /feed/ (Caused by NewConnectionError(\"HTTPSConnection(host='www.kijkopzuid-holland.nl', port=443): Failed to establish a new connection: [Errno 101] Network is unreachable\"))"
    },
    {
      "source": "RTV Dordrecht",
      "url": "https://www.rtvdordrecht.nl/feed/",
      "error": "http: 404 Client Error: Not Found for url: https://www.rtvdordrecht.nl/404"
    }
  ],
  "items": [
    {
      "id": "dagblad010-5618478253",
      "source": "Dagblad010",
      "title": "Tien aanhoudingen in Rotterdam en Dordrecht na Marokko-Canada",
      "description": "Tien aanhoudingen in Rotterdam en Dordrecht na Marokko-Canada",
      "url": "https://dagblad010.nl/rotterdam%20%26%20regio/tien-aanhoudingen-in-rotterdam-en-dordrecht-na-marokko-canada",
      "pubDate": "2026-07-05T10:51:00+00:00",
      "image": "https://media.digitaaldagblad.nl/files/shares/dagblad010/aanhoudingmarok6a4a1b08a548f.jpg",
      "duplicate_sources": [
        "Gooi- en Eemlander"
      ],
      "score": 75,
      "category": "Misdaad",
      "location": "Zuid-Holland",
      "reason": "Lokale ordeverstoringen na voetbalwedstrijd; relevante incidenten in twee steden.",
      "summary": "Tien personen werden aangehouden in Rotterdam en Dordrecht naar aanleiding van ongeregeldheden na de voetbalwedstrijd Marokko-Canada. De arrestaties vonden plaats tijdens feestelijkheden van Marokko-supporters."
    },
    {
      "id": "dagblad010-3492158407",
      "source": "Dagblad010",
      "title": "Publiek onder de 16 jaar mag in Nederland niet naar The Odyssey",
      "description": "Publiek onder de 16 jaar mag in Nederland niet naar The Odyssey",
      "url": "https://dagblad010.nl/landelijk/publiek-onder-de-16-jaar-mag-in-nederland-niet-naar-the-odyssey",
      "pubDate": "2026-07-05T10:49:00+00:00",
      "image": "https://media.digitaaldagblad.nl/files/shares/dagblad070/regisseurnolan6a4a1a74b087e.jpg",
      "score": 35,
      "category": "Opmerkelijk",
      "location": "Landelijk",
      "reason": "Routineuze filmclassificatie; beperkte nieuwswaarde zonder context.",
      "summary": "De film The Odyssey heeft in Nederland een leeftijdsclassificatie gekregen waarbij kinderen onder de 16 jaar niet zijn toegelaten. Dit is een standaard bioscoopclassificatiemaatregel."
    },
    {
      "id": "dagblad010-1467629057",
      "source": "Dagblad010",
      "title": "Drie gewonden bij aanrijding te midden van feestende Marokko-fans",
      "description": "Drie gewonden bij aanrijding te midden van feestende Marokko-fans",
      "url": "https://dagblad010.nl/landelijk/drie-gewonden-bij-aanrijding-te-midden-van-feestende-marokko-fans",
      "pubDate": "2026-07-05T10:46:00+00:00",
      "image": "https://media.digitaaldagblad.nl/files/shares/dagblad070/amsterdammarokko6a4a19dbb9fa5.jpg",
      "duplicate_sources": [
        "Gooi- en Eemlander"
      ],
      "score": 70,
      "category": "Misdaad",
      "location": "Landelijk",
      "reason": "Verkeersongeluk tijdens festiviteiten; gewonden maar locatie onduidelijk.",
      "summary": "Drie personen raakten gewond bij een aanrijding te midden van feestende Marokko-supporters. Het incident speelde zich af in de context van ongeregeldheden rond voetbalwedstrijdresultaten."
    },
    {
      "id": "dagblad010-6297207981",
      "source": "Dagblad010",
      "title": "Kind overleden na botsing op rijksweg A13 bij Delft",
      "description": "Kind overleden na botsing op rijksweg A13 bij Delft",
      "url": "https://dagblad010.nl/landelijk/kind-overleden-na-botsing-op-rijksweg-a13-bij-delft",
      "pubDate": "2026-07-05T10:43:00+00:00",
      "image": "https://media.digitaaldagblad.nl/files/shares/dagblad070/kaars67ae0818da274.jpg",
      "score": 65,
      "category": "Misdaad",
      "location": "Zuid-Holland",
      "reason": "Ernstig verkeersongeluk met dodelijk slachtoffer; lokale relevantie Delft/A13.",
      "summary": "Een kind kwam om het leven bij een botsing op rijksweg A13 bij Delft. Het incident lijkt een ernstig verkeersongeval zonder relatie tot ongeregeldheden."
    },
    {
      "id": "dagblad010-4121660445",
      "source": "Dagblad010",
      "title": "Margreet Dolman krijgt na veertien jaar weer televisieprogramma",
      "description": "Margreet Dolman krijgt na veertien jaar weer televisieprogramma",
      "url": "https://dagblad010.nl/landelijk/margreet-dolman-krijgt-na-veertien-jaar-weer-televisieprogramma",
      "pubDate": "2026-07-05T09:59:00+00:00",
      "image": "https://media.digitaaldagblad.nl/files/shares/dagblad070/margreetdolman6a4a0ebc70ddb.jpg",
      "score": 45,
      "category": "Media",
      "location": "Landelijk",
      "reason": "BN'er-comeback interessant, maar zonder controversiële of satirische lading.",
      "summary": "Presentatrice Margreet Dolman keert na veertien jaar terug op televisie met een nieuw programma. Dit markeert een comeback voor de bekende televisiemaker."
    },
    {
      "id": "dagblad010-4806488994",
      "source": "Dagblad010",
      "title": "Feest na Marokkaanse overwinning slaat in Rotterdam-West om",
      "description": "Feest na Marokkaanse overwinning slaat in Rotterdam-West om",
      "url": "https://dagblad010.nl/rotterdam%20%26%20regio/feest-na-marokkaanse-overwinning-slaat-in-rotterdam-west-om",
      "pubDate": "2026-07-05T09:55:00+00:00",
      "image": "https://media.digitaaldagblad.nl/files/shares/dagblad010/marokkoaanhouding6a4a0dcb54fd3.jpg",
      "score": 78,
      "category": "Misdaad",
      "location": "Zuid-Holland",
      "reason": "Lokale ordeversteuring in Rotterdam-West; specifieke locatie en context duidelijk.",
      "summary": "Feestelijkheden na een Marokkaanse sportieve overwinning eskaleerden tot ongeregeldheden in Rotterdam-West. De situatie sloeg om naar verstoring van de openbare orde."
    },
    {
      "id": "dagblad010-6067667976",
      "source": "Dagblad010",
      "title": "Nog geen akkoord over korten EU-hulp Sierra Leone om 'Bolle Jos'",
      "description": "Nog geen akkoord over korten EU-hulp Sierra Leone om 'Bolle Jos'",
      "url": "https://dagblad010.nl/landelijk/nog-geen-akkoord-over-korten-eu-hulp-sierra-leone-om-bolle-jos",
      "pubDate": "2026-07-05T09:45:00+00:00",
      "image": "https://media.digitaaldagblad.nl/files/shares/dagblad070/vanweel69e1f7b79f9b8.jpg",
      "score": 25,
      "category": "Overig",
      "location": "Internationaal",
      "reason": "EU-buitenlandbeleid zonder directe Nederlands-politieke impact; marginale relevantie.",
      "summary": "Er is geen akkoord bereikt over een mogelijke korting van EU-hulp aan Sierra Leone in verband met 'Bolle Jos'. Dit betreft internationale EU-diplomatie."
    },
    {
      "id": "dagblad010-5312287199",
      "source": "Dagblad010",
      "title": "29 arrestaties bij Marokkaanse onrust in Den Haag, twee agenten gewond",
      "description": "29 arrestaties bij Marokkaanse onrust in Den Haag, twee agenten gewond",
      "url": "https://dagblad010.nl/landelijk/29-arrestaties-bij-marokkaanse-onrust-in-den-haag-twee-agenten-gewond",
      "pubDate": "2026-07-05T09:41:00+00:00",
      "image": "https://media.digitaaldagblad.nl/files/shares/dagblad070/mobieleeenheid6a4a0aa78f75e.jpg",
      "duplicate_sources": [
        "Gooi- en Eemlander"
      ],
      "score": 82,
      "category": "Misdaad",
      "location": "Zuid-Holland",
      "reason": "Significant: hoofdstad-onrust met aanhoudingen, gewonde agenten; hoog nieuwswaarde.",
      "summary": "In Den Haag vonden 29 arrestaties plaats tijdens onrust, met twee politieagenten die gewond raakten. De ongeregeldheden hadden verband met Marokkaanse feestelijkheden."
    },
    {
      "id": "bn-de-stem-8083820637",
      "source": "BN De Stem",
      "title": "Vreugde en verdriet bij familie Laros als Lars (23) Brabants kampioen wordt",
      "description": "Vreugde en verdriet zaterdagavond langs de lijn van de sterk bezette Chaamloop. De bijna voltallige familie Laros kon twee keer juichen, maar ook was er bezorgdheid over de blessure van jongste zoon Niels. Zijn afmelding voor de race in Amerika drukte de stemming. Toch werd het een feestelijke avond: Lars (23) liet zien dat ook hij indrukwekkend hard kan lopen. Hij won de Brabantse titel over 10 k",
      "url": "https://www.bndestem.nl/regiosport/vreugde-en-verdriet-bij-familie-laros-als-lars-23-brabants-kampioen-wordt~a3bada51/",
      "pubDate": "2026-07-05T09:22:47+00:00",
      "image": "https://images.bndestem.nl/OTZmZWFkZjUyYWFjMDg3YjA0MTkvZGlvLzI3NTU4Njg0OS9maXQtd2lkdGgvNDAw/nlbeeld-bd20260630-3104-chaam-foto-rob-pauel-pix4profs-chaamloop-lars-laros",
      "score": 15,
      "category": "Overig",
      "location": "Noord-Brabant",
      "reason": "Lokaal sportnieuws zonder politieke, maatschappelijke of controversiële relevantie.",
      "summary": "Lars Laros wint de Brabantse 10 kilometer titel. Zijn familie beleeft een gemengde avond vanwege een blessure van zijn jongste broer."
    },
    {
      "id": "telegraaf-8331218345",
      "source": "Telegraaf",
      "title": "Lichaam van Heulmeisje voor de vijfde keer opgegraven: onderkaak zoek",
      "description": "Al vijf keer zijn de stoffelijke resten van het lichaam van het Heulmeisje, dat in 1976 werd aangetroffen, opgegraven voor vervolgonderzoek. Bij een van de opgravingen bleek de schedel verdwenen, sinds de laatste opgraving in april is haar onderkaak zoek.",
      "url": "https://www.telegraaf.nl/binnenland/lichaam-van-heulmeisje-voor-de-vijfde-keer-opgegraven-onderkaak-zoek/158283512.html",
      "pubDate": "2026-07-05T09:21:00+00:00",
      "image": "https://prod-img.telegraaf.nl/public/incoming/macm1h-7x4x1088x612-1024x576.webp/alternates/BASE_SIXTEEN_NINE/7x4x1088x612-1024x576.webp",
      "score": 72,
      "category": "Misdaad",
      "location": "Limburg",
      "reason": "Klassieke cold case uit 1976; schedel en onderkaak zoek — mysterie en forensisch onderzoek trekken aandacht.",
      "summary": "Het lichaam van het Heulmeisje, gevonden in 1976, is voor de vijfde keer opgegraven. De onderkaak ontbreekt sinds de laatste opgraving in april."
    },
    {
      "id": "telegraaf-6366164072",
      "source": "Telegraaf",
      "title": "Duitse tennisster (15) op Wimbledon gediskwalificeerd nadat haar racket uit frustratie tussen het publiek belandt",
      "description": "Een opmerkelijk tafereel uit het juniorentoernooi bij de meisjes op Wimbledon. Daar werd de Duitse Ida Wobker uit het toernooi gezet. De reden: haar racket belandde in het publiek nadat ze dat uit frustratie op de grond had gekeild.",
      "url": "https://www.telegraaf.nl/sport/tennis/duitse-tennisster-15-op-wimbledon-gediskwalificeerd-nadat-haar-racket-uit-frustratie-tussen-het-publiek-belandt/158283990.html",
      "pubDate": "2026-07-05T09:14:29+00:00",
      "image": "https://prod-img.nieuwsblad.be/public/nieuws/w2i38v-wobker.png/alternates/BASE_SIXTEEN_NINE/Wobker.png",
      "score": 38,
      "category": "Opmerkelijk",
      "location": "Internationaal",
      "reason": "Bizarre Wimbledon-incident zonder Nederlandse link; laag PowNed-profiel.",
      "summary": "Duitse tennisster Ida Wobker (15) wordt gediskwalificeerd van juniorentoernooi. Reden: haar racket belandde in het publiek na frustratie."
    },
    {
      "id": "nos-886537873",
      "source": "NOS",
      "title": "Nieuwe natuurbrand bij Perpignan, vuur aan Costa Brava onder controle",
      "description": "In de buurt van de Zuid-Franse stad Perpignan heeft een nieuwe natuurbrand in korte tijd een gebied ter grootte van 930 hectare in de as gelegd. Er zijn 580 brandweerlieden ingezet om het vuur te bestrijden, meldt France Info . Aan de andere kant van de Pyreneeën is een natuurbrand aan de Spaanse Costa Brava inmiddels onder controle. De nieuwe brand bij Perpignan woedt sinds gisteravond op zo'n 35",
      "url": "https://nos.nl/artikel/2621719-nieuwe-natuurbrand-bij-perpignan-vuur-aan-costa-brava-onder-controle",
      "pubDate": "2026-07-05T09:13:20+00:00",
      "image": "https://images.cdn.nos.nl/8/C/J/C/E/R/w7GXc7SgeUSxTZRQq1VCSwSRVLVsMBQDCKWPz7Y/6x3x3488x1962-1024x576.webp",
      "score": 12,
      "category": "Overig",
      "location": "Internationaal",
      "reason": "Routine buitenlandse natuurrampen zonder Nederlandse hoek — ondergewaardeerd.",
      "summary": "Natuurbrand bij Perpignan heeft 930 hectare verwoest. Costa Brava-brand staat onder controle."
    },
    {
      "id": "ad-den-haag-9738130011",
      "source": "AD Den Haag",
      "title": "Heb jij Shaggy, Milo of Sokka gezien? Deze 39 huisdieren worden in Den Haag vermist",
      "description": "Afgelopen week raakten in Den Haag 39 huisdieren vermist die we hier op een rij zetten. Wie heeft Shaggy, Milo of Sokka gezien?",
      "url": "https://www.ad.nl/den-haag/heb-jij-shaggy-milo-of-sokka-gezien-deze-39-huisdieren-worden-in-den-haag-vermist~a4331c5c/",
      "pubDate": "2026-07-05T09:11:44+00:00",
      "image": "https://images.ad.nl/MGYwN2NkNTllY2EzYmFiZjNmZWMvZGlvLzI3NTU4NzYxNy9maXQtd2lkdGgvNDAw/heb-jij-shaggy-milo-of-sokka-gezien-deze-39-huisdieren-worden-in-den-haag-vermist",
      "score": 25,
      "category": "Overig",
      "location": "Zuid-Holland",
      "reason": "Rutinematig vermist-huisdieren bericht; geen PowNed-relevantie.",
      "summary": "39 huisdieren vermist in Den Haag afgelopen week. Onder hen Shaggy, Milo en Sokka."
    },
    {
      "id": "ad-rotterdam-8920187524",
      "source": "AD Rotterdam",
      "title": "Heb jij Alma, Zazu of Nala gezien? Deze 44 huisdieren worden in Rotterdam vermist",
      "description": "Afgelopen week raakten in Rotterdam 44 huisdieren vermist die we hier op een rij zetten. Wie heeft Alma, Zazu of Nala gezien?",
      "url": "https://www.ad.nl/rotterdam/heb-jij-alma-zazu-of-nala-gezien-deze-44-huisdieren-worden-in-rotterdam-vermist~a993eeb2/",
      "pubDate": "2026-07-05T09:10:56+00:00",
      "image": "https://images.ad.nl/Njc2YzU0M2Q5NTcyZGNjODZlZTIvZGlvLzI3NTU4NjkzNi9maXQtd2lkdGgvNDAw/heb-jij-alma-zazu-of-nala-gezien-deze-44-huisdieren-worden-in-rotterdam-vermist",
      "score": 25,
      "category": "Overig",
      "location": "Zuid-Holland",
      "reason": "Rutinematig vermist-huisdieren bericht; geen PowNed-relevantie.",
      "summary": "44 huisdieren vermist in Rotterdam afgelopen week. Onder hen Alma, Zazu en Nala."
    },
    {
      "id": "ad-7577715010",
      "source": "AD",
      "title": "Noorwegen kan geschiedenis schrijven tegen Brazilië en Engeland in actie: op deze WK-duels kun je je verheugen",
      "description": "Noorwegen bereikte nog nooit de kwartfinale op het WK. Tegen vijfvoudig wereldkampioen Brazilië kan het land daar zondagavond verandering in brengen. Engeland neemt het na een zeer lastig duel tegen DR Congo (2-1) om 02.00 uur op tegen gastland Mexico.",
      "url": "https://www.ad.nl/wk-voetbal/noorwegen-kan-geschiedenis-schrijven-tegen-brazilie-en-engeland-in-actie-op-deze-wk-duels-kun-je-je-verheugen~afe49d6a/",
      "pubDate": "2026-07-05T09:06:00+00:00",
      "image": "https://images.ad.nl/NjNhNTcyMWYyYjMwOTU1MmM4OTQvZGlvLzI3NTU2MzcwOC9maXQtd2lkdGgvNDAw/miami-gardens-florida-june-24-vinicius-junior-7-of-brazil-celebrates-scoring-his-team-s-second-goal-during-the-fifa-world-cup-2026-group-c-match-between-scotland-and-brazil-at-miami-stadium-on-june-24-2026-in-miami-gardens-florida-photo-by-hannah-peters-fifa-fifa-via-getty-images-atlanta-usa-july-1-harry-kane-of-england-celebrates-after-scoring-a-goal-during-2026-fifa-world-cup-round-of-32-match-between-england-and-dr-congo-at-mercedes-benz-stadium-atlanta-stadium-in-atlanta-georgia-united-states-on-july-1-2026-photo-by-evrim-aydin-anadolu-via-getty-images",
      "duplicate_sources": [
        "BN De Stem",
        "PZC"
      ],
      "score": 8,
      "category": "Overig",
      "location": "Internationaal",
      "reason": "Routine sportnieuws Noorwegen/WK voetbal — geen Nederlandse relevantie.",
      "summary": "Noorwegen speelt tegen Brazilië voor kwartfinale WK voetbal. Engeland neemt het op tegen Mexico."
    },
    {
      "id": "telegraaf-9807042342",
      "source": "Telegraaf",
      "title": "Grote natuurbrand dwingt inwoners Thessaloniki te vluchten",
      "description": "Een grote natuurbrand ten noorden van de Griekse stad Thessaloniki heeft geleid tot evacuaties. Bewoners van drie woonwijken moesten hun huizen verlaten en ook een zorginstelling werd uit voorzorg ontruimd.",
      "url": "https://www.telegraaf.nl/video/grote-natuurbrand-dwingt-inwoners-thessaloniki-te-vluchten/158283818.html",
      "pubDate": "2026-07-05T09:03:00+00:00",
      "image": "https://prod-img.telegraaf.nl/public/incoming/b8qura-582.jpeg/alternates/BASE_SIXTEEN_NINE/582.jpeg",
      "score": 18,
      "category": "Overig",
      "location": "Internationaal",
      "reason": "Routine buitenlandse natuurramp zonder Nederlandse hoek — ondergewaardeerd.",
      "summary": "Grote natuurbrand ten noorden van Thessaloniki veroorzaakt evacuaties. Drie woonwijken en zorginstelling ontruimd."
    },
    {
      "id": "gooi--en-eemlander-3494486525",
      "source": "Gooi- en Eemlander",
      "title": "Bistro Vieux: Franse sferen in hartje Hilversum",
      "description": "Het Hilversumse Weversplein lijkt op een zwoele zomeravond een verstild Frans dorpsplein, omlijst door prachtige lindebomen. Precies de juiste ambiance die past bij Bistro Vieux.",
      "url": "https://www.gooieneemlander.nl/regio/gooi-en-eemland/bistro-vieux-franse-sferen-in-hartje-hilversum/157867471.html",
      "pubDate": "2026-07-05T09:03:00+00:00",
      "image": "https://prod-img.gooieneemlander.nl/public/incoming/xjdx19-restaurant-vieux-over-de-tong/alternates/BASE_SIXTEEN_NINE/Restaurant%20Vieux%20Over%20de%20Tong",
      "score": 5,
      "category": "Overig",
      "location": "Noord-Holland",
      "reason": "Restaurantrecensie zonder maatschappelijk belang of controversiële hoek.",
      "summary": "Bistro Vieux opent in Hilversum en creëert Franse ambiance op het Weversplein. Het etablissement combineert Franse sfeer met lokale lindebomen."
    },
    {
      "id": "telegraaf-2459854801",
      "source": "Telegraaf",
      "title": "Zeker acht gewonden, onder wie vier kinderen, bij schietpartij in New York",
      "description": "Bij een schietincident in Coney Island, in New York City, zijn zeker acht mensen gewond geraakt. Volgens ABC News zijn onder de gewonden vier kinderen.",
      "url": "https://www.telegraaf.nl/buitenland/zeker-acht-gewonden-onder-wie-vier-kinderen-bij-schietpartij-in-new-york/158283708.html",
      "pubDate": "2026-07-05T09:01:19+00:00",
      "image": "https://prod-img.telegraaf.nl/public/incoming/yheumy-online-coney-island.jpg/alternates/BASE_SIXTEEN_NINE/ONLINE%20-%20Coney%20Island.jpg",
      "duplicate_sources": [
        "Gooi- en Eemlander"
      ],
      "score": 15,
      "category": "Misdaad",
      "location": "Internationaal",
      "reason": "Buitenlands schietincident zonder Nederlandse angle of relevantie.",
      "summary": "Bij een schietincident in Coney Island, in New York City, zijn zeker acht mensen gewond geraakt. Volgens ABC News zijn onder de gewonden vier kinderen."
    },
    {
      "id": "ad-rotterdam-1523273941",
      "source": "AD Rotterdam",
      "title": "Waarderingsoorkonde voor Tennisvereniging Barendrecht",
      "description": "Tennisvereniging Barendrecht heeft de Waarderingsoorkonde van de gemeente Barendrecht ontvangen. Burgemeester Ronald Schneider kwam zaterdagavond tijdens het jubileumfeest langs om de onderscheiding te overhandigen aan voorzitter Leon van der Wilk.",
      "url": "https://www.ad.nl/barendrecht/waarderingsoorkonde-voor-tennisvereniging-barendrecht~a83ca7c7/",
      "pubDate": "2026-07-05T09:00:45+00:00",
      "image": "https://images.ad.nl/ZDBjODZkOTQwZGZkNzFjNTk2OTQvZGlvLzI3NTU4NDU0OC9maXQtd2lkdGgvNDAw/",
      "score": 8,
      "category": "Overig",
      "location": "Zuid-Holland",
      "reason": "Routinematige gemeentelijke onderscheiding voor sportclub zonder nieuwtie.",
      "summary": "Tennisvereniging Barendrecht heeft de Waarderingsoorkonde van de gemeente Barendrecht ontvangen. Burgemeester Ronald Schneider kwam zaterdagavond tijdens het jubileumfeest langs om de onderscheiding t"
    },
    {
      "id": "ad-rotterdam-5761186166",
      "source": "AD Rotterdam",
      "title": "Kiki Bertens over eerste profwedstrijd: ‘Ik moest van mijn vader in het Engels vragen wat ze wilde drinken’",
      "description": "Kiki Bertens (34) is de succesvolste Nederlandse tennisster aller tijden. Op 14-jarige leeftijd maakt zij in 2006 haar internationale debuut tijdens een future bij het Vlaardingse Holy. Een terugblik met de voormalig nummer 4 van de wereld. „Ben ik al zo oud?”",
      "url": "https://www.ad.nl/vlaardingen/kiki-bertens-over-eerste-profwedstrijd-ik-moest-van-mijn-vader-in-het-engels-vragen-wat-ze-wilde-drinken~a9250eb5/",
      "pubDate": "2026-07-05T09:00:42+00:00",
      "image": "https://images.ad.nl/MjA5OGNhODQxOGUxYzczNjlkOTQvZGlvLzY2ODk3ODQxL2ZpdC13aWR0aC80MDA/02062016-a-thierry-schut-fotografie-wateringen-dames-enkel-finale-rabo-rhijenhof-open-kiki-bertens-in-actie-tegen-femke-strijbis-dd-09-07-2006-ad-haagsche-courant-westland",
      "score": 25,
      "category": "Opmerkelijk",
      "location": "Zuid-Holland",
      "reason": "Terugblik op Nederlandse tennisster; sportgeoriënteerd, geen scoop of controverse.",
      "summary": "Kiki Bertens (34) is de succesvolste Nederlandse tennisster aller tijden. Op 14-jarige leeftijd maakt zij in 2006 haar internationale debuut tijdens een future bij het Vlaardingse Holy. Een terugblik "
    },
    {
      "id": "telegraaf-1785331178",
      "source": "Telegraaf",
      "title": "Paul Haenen brengt Margreet Dolman terug met ’een vrolijk-optimistisch, cultureel-humoristisch programma’",
      "description": "Margreet Dolman, het alter ego van Paul Haenen, keert na een afwezigheid van veertien jaar met haar eigen programma terug op televisie. Het nieuwe programma heet Margreet Dolman begrijpt het en is vanaf 6 september om te beginnen zes weken op zondagochtend te zien op RTL4. De uitzendingen zijn daarna terug te kijken op Videoland, meldt RTL.",
      "url": "https://www.telegraaf.nl/entertainment/cultuur/paul-haenen-brengt-margreet-dolman-terug-met-een-vrolijk-optimistisch-cultureel-humoristisch-programma/158282549.html",
      "pubDate": "2026-07-05T09:00:00+00:00",
      "image": "https://prod-img.telegraaf.nl/public/entertainment/sterren/pfchbz-anp-549376476.jpg/alternates/BASE_SIXTEEN_NINE/ANP-549376476.jpg",
      "score": 45,
      "category": "Media",
      "location": "Landelijk",
      "reason": "Terugkeer cultuurpersonage op RTL; relevant voor media/cultuur maar geen hardnieuws.",
      "summary": "Margreet Dolman, het alter ego van Paul Haenen, keert na een afwezigheid van veertien jaar met haar eigen programma terug op televisie. Het nieuwe programma heet Margreet Dolman begrijpt het en is van"
    },
    {
      "id": "telegraaf-1473286990",
      "source": "Telegraaf",
      "title": "Voor kamperende luxepoezen, hondenbaasjes of senioren: strandhuisjes worden steeds een tandje luxer",
      "description": "Het traditionele strandhuisje van aleer ondergaat een metamorfose. Waar het ooit draaide om eenvoud en het geluid van de zee, combineert een nieuwe generatie strandhuisjes de magie van de kust met het gemak van een boutique-hotel.",
      "url": "https://www.telegraaf.nl/lifestyle/vrije-tijd/voor-kamperende-luxepoezen-hondenbaasjes-of-senioren-strandhuisjes-worden-steeds-een-tandje-luxer/150280034.html",
      "pubDate": "2026-07-05T09:00:00+00:00",
      "image": "https://prod-img.telegraaf.nl/public/incoming/5mlgu6-petten-landal-jean-pierre-jans.jpg/alternates/BASE_SIXTEEN_NINE/petten%20landal%20Jean%20Pierre%20Jans.jpg",
      "score": 12,
      "category": "Overig",
      "location": "Landelijk",
      "reason": "Lifestyle-trend zonder nieuws- of maatschappelijk belang voor PowNed.",
      "summary": "Het traditionele strandhuisje van aleer ondergaat een metamorfose. Waar het ooit draaide om eenvoud en het geluid van de zee, combineert een nieuwe generatie strandhuisjes de magie van de kust met het"
    },
    {
      "id": "rtv-noord-8713515925",
      "source": "RTV Noord",
      "title": "Quiz: Test je nieuwskennis van de afgelopen twee weken",
      "description": "Heb je goed gevolgd wat er in Stad en Ommeland is gebeurd de afgelopen twee weken? Met onderstaande quiz kun je testen of je je alles nog goed weet te herinneren. Om de week toetsen we wat jij weet van het nieuws in de regio.",
      "url": "https://www.rtvnoord.nl/cultuur/1418168/quiz-test-je-nieuwskennis-van-de-afgelopen-twee-weken",
      "pubDate": "2026-07-05T09:00:00+00:00",
      "image": "https://i.regiogroei.cloud/a46e2089-6303-344a-a7df-3ca9f570560c.jpg?width=552&height=310&aspect_ratio=552:310&cb=9c7b2e3bb906f050e073b4e09de235c6",
      "score": 0,
      "category": "Overig",
      "location": "Groningen",
      "reason": "Interactieve quiz zonder nieuws of informatieve waarde voor PowNed-lezers.",
      "summary": "Heb je goed gevolgd wat er in Stad en Ommeland is gebeurd de afgelopen twee weken? Met onderstaande quiz kun je testen of je je alles nog goed weet te herinneren. Om de week toetsen we wat jij weet va"
    },
    {
      "id": "nos-2660081153",
      "source": "NOS",
      "title": "Tienduizenden Albanezen bij 35e protest tegen de regering en een Trump-resort",
      "description": "In de Albanese hoofdstad Tirana hebben tienduizenden mensen geprotesteerd tegen de regering van premier Rama, tegen corruptie en voor een verandering van de grondwet. Het was de 35e avond achtereen dat Albanezen daarvoor de straat op gingen. In het begin ging dat protest nog tegen de bouw van een luxe toeristenresort door de familie Trump in een kwetsbaar natuurgebied, inmiddels is het gericht teg",
      "url": "https://nos.nl/artikel/2621718-tienduizenden-albanezen-bij-35e-protest-tegen-de-regering-en-een-trump-resort",
      "pubDate": "2026-07-05T08:58:25+00:00",
      "image": "https://images.cdn.nos.nl/1/D/P/g/W/i/kKeCh83G6KoFYiAGMEBoRvSiZCevJSCCTJmhm99/0x120x4000x2250-1024x576.webp",
      "score": 52,
      "category": "Event",
      "location": "Internationaal",
      "reason": "Massaprotesten tegen regering; relevant maar geen Nederlandse hoek of directe invloed.",
      "summary": "In de Albanese hoofdstad Tirana hebben tienduizenden mensen geprotesteerd tegen de regering van premier Rama, tegen corruptie en voor een verandering van de grondwet. Het was de 35e avond achtereen da"
    },
    {
      "id": "ad-6297713674",
      "source": "AD",
      "title": "Al meer dan 60.000 euro opgehaald voor peuter die in krokodillenverblijf werd gegooid",
      "description": "De driejarige jongen die half juni zwaargewond raakte toen hij in het krokodillenverblijf van een Britse dierentuin werd gegooid, heeft inmiddels al vijf operaties achter de rug. Volgens zijn ouders wachten hem nog minstens twee zware ingrepen en een erg lange revalidatie. Een online inzamelingsactie om het gezin financieel te steunen, heeft intussen al meer dan 60.000 euro opgeleverd.",
      "url": "https://www.ad.nl/buitenland/al-meer-dan-60-000-euro-opgehaald-voor-peuter-die-in-krokodillenverblijf-werd-gegooid~ab55af721/",
      "pubDate": "2026-07-05T08:56:58+00:00",
      "image": "https://images.ad.nl/ZTA4MmJjOGE0ZDFmNDI2Mjk0YWQvZGlvLzI3NTU4NTkyOS9maXQtd2lkdGgvNDAw/krokodil",
      "duplicate_sources": [
        "BN De Stem",
        "De Stentor",
        "PZC"
      ],
      "score": 15,
      "category": "Opmerkelijk",
      "location": "Internationaal",
      "reason": "Buitenlands incident zonder Nederlandse relevantie of link.",
      "summary": "Een driejarige jongen raakte zwaargewond in een Brits dierentuin en ondergaat meerdere operaties. Een online inzamelingsactie heeft al meer dan 60.000 euro opgeleverd."
    },
    {
      "id": "telegraaf-4150921547",
      "source": "Telegraaf",
      "title": "Volksfeest na zege Marokko eindigt in drama: drie zwaargewonden in Amsterdam door botsing met gestolen motorscooter",
      "description": "Een uitbundig volksfeest op Plein ’40-’45 in Slotermeer is in de nacht van zaterdag op zondag abrupt geëindigd in een ernstig ongeluk. Door een aanrijding tussen een motorscooter en een fatbike zijn drie mensen zwaargewond naar het ziekenhuis gebracht. De 18-jarige Amsterdamse bestuurder van de motorscooter is aangehouden. Een politiewoordvoerder laat weten dat het voertuig als gestolen te boek st",
      "url": "https://www.telegraaf.nl/binnenland/volksfeest-na-zege-marokko-eindigt-in-drama-drie-zwaargewonden-in-amsterdam-door-botsing-met-gestolen-motorscooter/158280989.html",
      "pubDate": "2026-07-05T08:56:00+00:00",
      "image": "https://prod-img.telegraaf.nl/public/incoming/fxjnwl-anp-562423463.jpg/alternates/BASE_SIXTEEN_NINE/ANP-562423463.jpg",
      "score": 78,
      "category": "Misdaad",
      "location": "Noord-Holland",
      "reason": "Serieus incident met gestolen voertuig en drie gewonden in Amsterdam, relevant voor PowNed-lezers.",
      "summary": "Een vieringsfeest in Amsterdam liep uit de hand toen een gestolen motorscooter drie mensen aanreed. De achttienjarige bestuurder werd aangehouden."
    },
    {
      "id": "sleutelstad-9444226877",
      "source": "Sleutelstad",
      "title": "Koninklijke onderscheiding voor Tilly Schrama-van Leeuwen",
      "description": "De Voorschotense burgemeester Nadine Stemerdink heeft zaterdag 4 juli een Koninklijke onderscheiding uitgereikt aan Tilly Schrama-van Leeuwen. Zij ontving de onderscheiding voor haar langdurige en veelzijdige inzet voor de zwemsport en het zwemonderwijs in Leiden. De uitreiking vond plaats tijdens het 140‑jarig jubileum van ZVL-1886 in Buitenbad De Vliet. Schrama-van Leeuwen werd in 1994 lid [&#82",
      "url": "https://sleutelstad.nl/2026/07/05/koninklijke-onderscheiding-voor-tilly-schrama-van-leeuwen/",
      "pubDate": "2026-07-05T08:55:52+00:00",
      "image": "",
      "score": 8,
      "category": "Overig",
      "location": "Zuid-Holland",
      "reason": "Routinematige ceremonie zonder controversie, schandaal of maatschappelijk belang.",
      "summary": "Burgermeester Stemerdink reikte een Koninklijke onderscheiding uit aan Tilly Schrama-van Leeuwen voor haar inzet voor zwemsport. De uitreiking gebeurde tijdens het 140-jarig jubileum van een zwemclub in Leiden."
    },
    {
      "id": "ad-777640229",
      "source": "AD",
      "title": "15-jarige Duitse gediskwalificeerd bij junioren na gooien van racket in publiek, Zverev naar vierde ronde",
      "description": "Het grootste grastennistoernooi is begonnen. Tussen 29 juni en 11 juli strijden de beste tennissers ter wereld om de titel op Wimbledon. Hier blijf je op de hoogte van alle ontwikkelingen.",
      "url": "https://www.ad.nl/tennis/15-jarige-duitse-gediskwalificeerd-bij-junioren-na-gooien-van-racket-in-publiek-zverev-naar-vierde-ronde~aff1a2be/",
      "pubDate": "2026-07-05T08:53:00+00:00",
      "image": "https://images.ad.nl/ZTg0YzZhNWMzYTZmY2Y3MjkxY2MvZGlvLzI3NTU1OTA3NC9maXQtd2lkdGgvNDAw/alexander-zverev-of-germany-reacts-after-winning-match-point-against-marcos-giron-of-the-united-states-in-their-third-round-men-s-singles-match-at-the-wimbledon-tennis-championships-in-london-saturday-july-4-2026-ap-photo-kirsty-wigglesworth",
      "score": 5,
      "category": "Overig",
      "location": "Internationaal",
      "reason": "Tennis-sportuitslagen zonder Nederlandse dimensie of maatschappelijk belang.",
      "summary": "Een Duitse tiener werd gediskwalificeerd bij Wimbledon voor het gooien van een racket. Het toernooi duurt van 29 juni tot 11 juli."
    },
    {
      "id": "nu.nl-1840809025",
      "source": "NU.nl",
      "title": "Van de hoofdredactie | Wantrouwen wordt alleen maar groter na zo'n nepvideo",
      "description": "De hoofdredactie van NU.nl vertelt wekelijks over wat zich op de redactie afspeelt. Deze week: hoe een deepfake van onze presentator onze integriteit aantast.",
      "url": "https://www.nu.nl/blog/6401775/wantrouwen-wordt-alleen-maar-groter-na-zon-nepvideo.html",
      "pubDate": "2026-07-05T08:52:37+00:00",
      "image": "https://images.nu.nl/m/7ftxri7agmm2_sqr256/433/0/1080/1080/wantrouwen-wordt-alleen-maar-groter-na-zon-nepvideo.jpg",
      "score": 72,
      "category": "Media",
      "location": "Landelijk",
      "reason": "Directe mediakritek over deepfakes en journalistieke integriteit, relevant voor PowNed's mediakritiek.",
      "summary": "NU.nl waarschuwt voor gevaren van deepfakes na een nepvideo van een presentator. Het artikel bespreekt hoe dit het publieke vertrouwen aantast."
    },
    {
      "id": "nu.nl-7112929099",
      "source": "NU.nl",
      "title": "Hoe krijgen we jongeren in beweging? 'Niet met wijzend vingertje'",
      "description": "Steeds meer jongeren en jongvolwassenen fietsen elektrisch. Het RIVM maakt zich zorgen: veel jongeren bewegen al niet genoeg, en nu gaat dat misschien nog harder achteruit. Hoe brengen we ze toch in beweging? Sluit je aan bij hun leefwereld, zeggen deskundigen.",
      "url": "https://www.nu.nl/nujij/6401784/hoe-krijgen-we-jongeren-in-beweging-niet-met-wijzend-vingertje.html",
      "pubDate": "2026-07-05T08:50:17+00:00",
      "image": "https://images.nu.nl/m/4etxor1acbnu_sqr256/527/0/2967/2967/hoe-krijgen-we-jongeren-in-beweging-niet-met-wijzend-vingertje.jpg",
      "score": 18,
      "category": "Overig",
      "location": "Landelijk",
      "reason": "Gezondheidsbeleid zonder schandaal of controverse, minder relevant voor PowNed.",
      "summary": "Het RIVM maakt zich zorgen dat e-fietsen jongeren nog minder doen bewegen. Deskundigen adviseren aansluiting bij hun leefwereld."
    },
    {
      "id": "ad-6626737809",
      "source": "AD",
      "title": "‘Schuimpartij’ in Leeuwarden: zeep in ‘Vogel-fontein’ zorgt voor dikke laag schuim",
      "description": "Wie zich zondagochtend eens flink met zeep wil schrobben, zou eens naar de Vogel Fontein Wiersma Fokma in Leeuwarden moeten gaan. Er ligt een dikke laag schuim op het water van de fontein. Vermoedelijk is er in de nacht van zaterdag op zondag zeep in het water gegooid.",
      "url": "https://www.ad.nl/binnenland/schuimpartij-in-leeuwarden-zeep-in-vogel-fontein-zorgt-voor-dikke-laag-schuim~af63bb8d/",
      "pubDate": "2026-07-05T08:48:00+00:00",
      "image": "https://images.ad.nl/ZjMxZmM1Mjk0MDljZWU1NTY3NzUvZGlvLzI3NTU4NjQxOS9maXQtd2lkdGgvNDAw/de-vogel-fontein-in-leeuwarden",
      "duplicate_sources": [
        "BN De Stem",
        "De Stentor",
        "PZC"
      ],
      "score": 65,
      "category": "Opmerkelijk",
      "location": "Friesland",
      "reason": "Bizarre lokale incident met humoristische waarde, goed regionaal spotwerk voor PowNed.",
      "summary": "Een fontein in Leeuwarden raakte vol schuim nadat er vermoedelijk zeep in werd gegooid. Het incident vond plaats in de nacht van zaterdag op zondag."
    },
    {
      "id": "trouw-2902074081",
      "source": "Trouw",
      "title": "Zeker acht gewonden bij schietpartij tijdens vuurwerk in New York",
      "description": "",
      "url": "https://archive.ph/newest/https://www.trouw.nl/buitenland/live-vs-zeker-acht-gewonden-bij-schietpartij-tijdens-vuurwerk-in-new-york~bbc0cf3d/",
      "pubDate": "2026-07-05T08:48:00+00:00",
      "image": "https://image.trouw.nl/275581453/roi/320/320/3060/1400/a-tribute-to-america-on-the-national-mall-in-d-c-celebrates",
      "score": 0,
      "category": "Overig",
      "location": "Internationaal",
      "reason": "Beschrijving ontbreekt; buitenlands incident zonder Nederlandse relevantie.",
      "summary": ""
    },
    {
      "id": "nu.nl-2189879798",
      "source": "NU.nl",
      "title": "Kind omgekomen bij ongeluk op A13 bij Delft",
      "description": "Bij een ongeluk op de A13 ter hoogte van Delft is zaterdagavond een kind om het leven gekomen. De politie zoekt naar getuigen.",
      "url": "https://www.nu.nl/binnenland/6401962/kind-omgekomen-bij-ongeluk-op-a13-bij-delft.html",
      "pubDate": "2026-07-05T08:46:08+00:00",
      "image": "https://images.nu.nl/m/skjxdmra2l6n_sqr256/1893/0/4323/4323/kind-omgekomen-bij-ongeluk-op-a13-bij-delft.jpg",
      "score": 72,
      "category": "Misdaad",
      "location": "Zuid-Holland",
      "reason": "Fataal verkeersongeval met kind; ernstig incident maar routinematig misdaadnieuws.",
      "summary": "Een kind is om het leven gekomen bij een ongeluk op de A13 bij Delft zaterdagavond. De politie roept getuigen op zich te melden."
    },
    {
      "id": "ad-9507177749",
      "source": "AD",
      "title": "De afdeling hr heeft wat ‘leuks’ voor Katinka (51): ‘Ik dacht aan een zomerbonus, maar dat was het niet’",
      "description": "Katinka (51) ziet elk jaar als een berg op tegen de jaarlijkse sportdag met collega’s. Dit jaar kreeg de sportdag een extra vervelend staartje, vertelt ze aan Anne-Marije Buckens die sinds vijftien jaar een bedrijf heeft waarmee ze 50-plussers aan werk helpt. „Woede, schaamte, verdriet, alles ging tegelijk door me heen.”",
      "url": "https://www.ad.nl/economie/de-afdeling-hr-heeft-wat-leuks-voor-katinka-51-ik-dacht-aan-een-zomerbonus-maar-dat-was-het-niet~ad66714f/",
      "pubDate": "2026-07-05T08:45:21+00:00",
      "image": "https://images.ad.nl/OWUxOTJlOTdhOWMxMTI3NWVlOGEvZGlvLzI3NTU0ODAxMS9maXQtd2lkdGgvNDAw/a-multicultural-group-of-friends-celebrating-fitness-success-hands-clasped-after-a-joint-outdoor-jog",
      "duplicate_sources": [
        "BN De Stem",
        "De Stentor",
        "PZC"
      ],
      "score": 15,
      "category": "Opmerkelijk",
      "location": "Landelijk",
      "reason": "Persoonlijk mensinterest-verhaal zonder maatschappelijke relevantie voor PowNed-doelgroep.",
      "summary": "Een 51-jarige vrouw ervaart een bedrijfssportdag als vervelend en krijgt onverwacht nieuws van HR. Het artikel belicht generationele werkplekconflicten."
    },
    {
      "id": "pzc-8691159833",
      "source": "PZC",
      "title": "Op vakantie in eigen stad of land; deze app wil je hebben",
      "description": "Heb je het al gehoord? De staycation is helemaal 2026. En als je dan vakantie viert in eigen stad of land, dan kun je maar beter voorbereid zijn als een prof. En daar heeft indebuurt de ideale app voor.",
      "url": "https://www.pzc.nl/bergen-op-zoom/op-vakantie-in-eigen-stad-of-land-deze-app-wil-je-hebben~a649dd59/",
      "pubDate": "2026-07-05T08:43:00+00:00",
      "image": "https://images.pzc.nl/MTk0MjZkZGRhZmQyYWQ0NDlkNTkvZGlvLzI3MDA0MjcyNC9maXQtd2lkdGgvNDAw/bekijk-nu-onze-nieuwe-app",
      "duplicate_sources": [
        "AD Rotterdam"
      ],
      "score": 5,
      "category": "Overig",
      "location": "Zeeland",
      "reason": "Routineus lifestyleadvies zonder nieuws- of controversewaarde voor PowNed.",
      "summary": "Een app-aanbeveling voor staycations in eigen land of stad. Artikel geeft tips voor vakantieplannen."
    },
    {
      "id": "de-stentor-1873053128",
      "source": "De Stentor",
      "title": "Misstanden bij konijnenfokkerijen gefilmd, ook in Gelderland: dieren aan oren opgetild en in kratten gesmeten",
      "description": "Konijnen worden bij fokkerijen mishandeld en hardhandig vastgepakt tijdens transport. Dat stelt Animal Rights nadat de organisatie 26 keer transporten van slachthuizen naar konijnenfokkerijen en weer terug volgde. Dit is gefilmd vanuit de lucht met een drone, onder meer bij drie Gelderse fokkerijen. De beelden liegen er niet om.",
      "url": "https://www.destentor.nl/berkelland/misstanden-bij-konijnenfokkerijen-gefilmd-ook-in-gelderland-dieren-aan-oren-opgetild-en-in-kratten-gesmeten~a06e972c/",
      "pubDate": "2026-07-05T08:39:00+00:00",
      "image": "https://images.destentor.nl/YjI3YWZkZmQwZmUzNTM4ZTAyNTcvZGlvLzI3NTU3MjEzNC9maXQtd2lkdGgvNDAw/konijnen-mishandeld",
      "score": 68,
      "category": "Opmerkelijk",
      "location": "Gelderland",
      "reason": "Dierenmishandeling met regionaal houvast en video-bewijs; controversieel onderwerp voor PowNed.",
      "summary": "Animal Rights documenteert mishandelingen bij Gelderse konijnenfokkerijen via drone. 26 transporten werden gevolgd met footage van hardhandig transport."
    },
    {
      "id": "trouw-17763143",
      "source": "Trouw",
      "title": "Wimbledon, 25 jaar later. ‘De stilte is gebleven, zo mooi’",
      "description": "",
      "url": "https://archive.ph/newest/https://www.trouw.nl/sport/wimbledon-25-jaar-later-de-stilte-is-gebleven-zo-mooi~b3f57fba/",
      "pubDate": "2026-07-05T08:35:00+00:00",
      "image": "https://image.trouw.nl/275468380/feature-crop/320/320/afbeelding",
      "score": 0,
      "category": "Overig",
      "location": "Internationaal",
      "reason": "Lichte sports nostalgia zonder feitelijk nieuws; niet relevant voor PowNed.",
      "summary": "Artikel zonder beschrijving over Wimbledon 25 jaar later. Inhoud niet nader gespecificeerd."
    },
    {
      "id": "telegraaf-8977332923",
      "source": "Telegraaf",
      "title": "De bikini is 80 jaar jong en iedereen kan het hebben: dit model past bij jouw figuur",
      "description": "Vandaag bestaat de bikini op de officiële internationale bikinidag maar liefst 80 jaar! En dat we na al die jaren nog steeds veel plezier hebben van dit meest minuscule kledingstuk uit de garderobekast zegt eigenlijk wel genoeg over het grote succes. En ook dit jaar mag het setje weer volop gedragen worden op het strand, in het zwembad tijdens een festival, strandparty of een picknick.",
      "url": "https://www.telegraaf.nl/binnenland/de-bikini-is-80-jaar-jong-en-iedereen-kan-het-hebben-dit-model-past-bij-jouw-figuur/158196128.html",
      "pubDate": "2026-07-05T08:34:19+00:00",
      "image": "https://prod-img.telegraaf.nl/public/incoming/f17ier-annadiva-ss26-pink-garden-cerise-lucia-01932ces-kate-01913ces.jpg/alternates/BASE_SIXTEEN_NINE/Annadiva_SS26_PINK%20GARDEN_CERISE_LUCIA_01932CES_KATE_01913CES.jpg",
      "score": 8,
      "category": "Overig",
      "location": "Landelijk",
      "reason": "Triviale lifestylecontent over bikinimode; geen news- of opinieperspectief.",
      "summary": "De bikini bestaat 80 jaar en blijft populair op stranden en festivals. Artikel adviseert welk model past bij welke figuur."
    },
    {
      "id": "gooi--en-eemlander-4932567448",
      "source": "Gooi- en Eemlander",
      "title": "Kylian Mbappé prijst ploeggenoten die hoofd koel hielden tegen Paraguay: ’Iedereen dacht dat we in smoking kwamen spelen’",
      "description": "Kylian Mbappé moest het flink ontgelden in het gewonnen WK-duel met Paraguay.",
      "url": "https://www.gooieneemlander.nl/sport/kylian-mbappe-prijst-ploeggenoten-die-hoofd-koel-hielden-tegen-paraguay-iedereen-dacht-dat-we-in-smoking-kwamen-spelen/158283129.html",
      "pubDate": "2026-07-05T08:30:26+00:00",
      "image": "https://prod-img.telegraaf.nl/public/sport/m8cdv5-anp-562820518.jpg/alternates/BASE_SIXTEEN_NINE/ANP-562820518.jpg",
      "duplicate_sources": [
        "Telegraaf"
      ],
      "score": 2,
      "category": "Overig",
      "location": "Internationaal",
      "reason": "Voetbal-gossip zonder Nederlandse relevantie; volledig buiten PowNed-scope.",
      "summary": "Mbappé prijst ploeggenoten na WK-duel tegen Paraguay. Voetballer reageert op kritiek na wedstrijd."
    },
    {
      "id": "sleutelstad-211615425",
      "source": "Sleutelstad",
      "title": "Nieuwe videoserie Hortus belicht verborgen wereld van thee",
      "description": "Van een rustmoment op de bank tot internationale handel en grootschalige plantages: thee speelt wereldwijd een enorme rol in het dagelijks leven. In een nieuwe online videoserie van de Hortus botanicus Leiden duiken kijkers in de wereld achter de theeplant. In korte afleveringen vertelt de Hortus over de geschiedenis van thee. Over de culturele betekenis [&#8230;]",
      "url": "https://sleutelstad.nl/2026/07/05/nieuwe-videoserie-hortus-belicht-verborgen-wereld-van-thee/",
      "pubDate": "2026-07-05T08:30:13+00:00",
      "image": "",
      "score": 18,
      "category": "Overig",
      "location": "Zuid-Holland",
      "reason": "Cultureel-educatief content over thee zonder nieuws-, politiek- of controversewaarde.",
      "summary": "Hortus Leiden lanceert videoserie over geschiedenis en cultuur van thee. Serie verkent rol van thee in mondiale handel en dagelijks leven."
    },
    {
      "id": "nos-9732250218",
      "source": "NOS",
      "title": "Soesterberg is blij met komst van militairen, maar vreest voor leefbaarheid",
      "description": "Ruim dertig jaar na het vertrek van de laatste Amerikaanse soldaten uit Soesterberg komen er weer militaire uniformen in het straatbeeld. De oudere inwoners hebben goede herinneringen aan Defensie in hun dorp, maar nieuwe bewoners vragen zich af wat de komst van zoveel nieuwe inwoners doet met de leefbaarheid. Onlangs startte de verhuizing van het 45e Pantserinfanteriebataljon van de landmacht uit",
      "url": "https://nos.nl/artikel/2621714-soesterberg-is-blij-met-komst-van-militairen-maar-vreest-voor-leefbaarheid",
      "pubDate": "2026-07-05T08:30:02+00:00",
      "image": "https://images.cdn.nos.nl/5/5/c/Z/x/b/LhHBgDWsNKbCMx4V8VbuU2Q1nEX3hdebH8naBYK/7x78x1424x801-1024x576.webp",
      "score": 72,
      "category": "Opmerkelijk",
      "location": "Utrecht",
      "reason": "Lokaal Nederlands verhaal over militaire komst, leefbaarheid en gemeenschapsdynamiek in dorp.",
      "summary": "Soesterberg bereidt zich voor op komst van 45e Pantserinfanteriebataljon na 30 jaar zonder militaire aanwezigheid. Oudere inwoners zijn positief, maar nieuwe bewoners maken zich zorgen over gevolgen voor leefbaarheid."
    },
    {
      "id": "telegraaf-6582855990",
      "source": "Telegraaf",
      "title": "Michiel (62) woont al 23 jaar op Ibiza: ’Er is hier bijna geen pand meer te krijgen voor minder dan een miljoen’",
      "description": "Michiel Reinbergen (62) woont al sinds 2003 op Ibiza. Hij spreekt vol lof over het Spaanse feesteiland, al is er volgens hem wel een hoop veranderd. Zo zijn de huizenprijzen nu torenhoog! Michiel heeft een bouwonderneming en is gescheiden, zijn twee kinderen studeren in Amsterdam.",
      "url": "https://www.telegraaf.nl/vrouw/michiel-62-woont-al-23-jaar-op-ibiza-er-is-hier-bijna-geen-pand-meer-te-krijgen-voor-minder-dan-een-miljoen/153544778.html",
      "pubDate": "2026-07-05T08:30:00+00:00",
      "image": "https://prod-img.telegraaf.nl/public/incoming/h1jaeu-zomer-enkeltje-ibiza.jpg/alternates/BASE_SIXTEEN_NINE/ZOMER%20Enkeltje%20Ibiza.jpg",
      "score": 15,
      "category": "Overig",
      "location": "Internationaal",
      "reason": "Nederlandse expat op Ibiza zonder Nederlands politiek, mediaal of maatschappelijk relevantie.",
      "summary": "Michiel Reinbergen (62) woont al sinds 2003 op Ibiza. Hij spreekt vol lof over het Spaanse feesteiland, al is er volgens hem wel een hoop veranderd. Zo zijn de huizenprijzen nu torenhoog! Michiel heef"
    },
    {
      "id": "ad-6955824529",
      "source": "AD",
      "title": "Sven (23) verloor zijn been na vreselijk ongeluk tijdens training: ‘Ik zie mezelf nog onder die auto rollen’",
      "description": "Het beeld staat voor altijd op zijn netvlies gebrand: het moment dat Sven Pijnenburg (23) onder een vrachtauto rolt. Sindsdien moet de wielrenner uit Raamsdonksveer leven met één been. Een verhaal van horror, boosheid en positiviteit. Met een nieuw doel: de Paralympics van Los Angeles in 2028.",
      "url": "https://www.ad.nl/wielrennen/sven-23-verloor-zijn-been-na-vreselijk-ongeluk-tijdens-training-ik-zie-mezelf-nog-onder-die-auto-rollen~a1e94a95/",
      "pubDate": "2026-07-05T08:30:00+00:00",
      "image": "https://images.ad.nl/MDE2YjMxMGJkOWVlNWU2MGFmMjkvZGlvLzI3NTQ2OTEzMi9maXQtd2lkdGgvNDAw/nlbeeld-raamsdonksveer-01-07-2026-wielrenner-sven-pijnenburg-is-begin-februari-zwaargewond-geraakt-bij-een-botsing-met-een-vrachtwagen-in-waspik-in-het-ziekenhuis-is-uiteindelijk-zijn-been-geamputeerd-foto-pix4profs-joyce-van-belkom",
      "duplicate_sources": [
        "De Stentor",
        "PZC"
      ],
      "score": 45,
      "category": "Opmerkelijk",
      "location": "Noord-Brabant",
      "reason": "Human interest verhaal over trainingsongeluk en ambitie, beperkte nieuwswaarde voor opiniesite.",
      "summary": "Wielrenner Sven Pijnenburg verloor zijn been bij ernstig verkeersongeluk en richt zich nu op Paralympics 2028. Het verhaal van trauma en positiviteit gecentreerd rond atleet uit Raamsdonksveer."
    },
    {
      "id": "ad-rotterdam-2143472764",
      "source": "AD Rotterdam",
      "title": "Ook Florabuurt getroffen door isolatieschuim: Havensteder laat deze week lucht meten in woningen",
      "description": "Ook in de Capelse Florabuurt is het ongezonde UF-schuim gebruikt om buitenmuren mee te isoleren. Woningcorporatie Havensteder gaat in een aantal woningen luchtmetingen doen.",
      "url": "https://www.ad.nl/capelle-aan-den-ijssel/ook-florabuurt-getroffen-door-isolatieschuim-havensteder-laat-deze-week-lucht-meten-in-woningen~a019ca83/",
      "pubDate": "2026-07-05T08:30:00+00:00",
      "image": "https://images.ad.nl/ZDIwZmU3N2U5Yzc1MWEwNGYwY2YvZGlvLzI3MDY4MzI2NC9maXQtd2lkdGgvNDAw/uf-schuim",
      "score": 68,
      "category": "Misdaad",
      "location": "Zuid-Holland",
      "reason": "Lokaal Rotterdam-schandaal over giftig isolatieschuim in woningen, leeft in publieke debat.",
      "summary": "Ook in de Capelse Florabuurt is het ongezonde UF-schuim gebruikt om buitenmuren mee te isoleren. Woningcorporatie Havensteder gaat in een aantal woningen luchtmetingen doen."
    },
    {
      "id": "telegraaf-6767625348",
      "source": "Telegraaf",
      "title": "Zo vierden de Verenigde Staten hun 250e verjaardag",
      "description": "De Verenigde Staten hebben groots uitgepakt voor hun 250e Onafhankelijkheidsdag. In Washington en New York kwamen honderdduizenden mensen samen voor militaire vliegshows, een vlootparade en spectaculaire vuurwerkshows. Ondanks onweer en extreme hitte gingen de festiviteiten uiteindelijk gewoon door.",
      "url": "https://www.telegraaf.nl/video/zo-vierden-de-verenigde-staten-hun-250e-verjaardag/158283110.html",
      "pubDate": "2026-07-05T08:29:55+00:00",
      "image": "https://prod-img.telegraaf.nl/public/incoming/iagtv2-865.jpeg/alternates/BASE_SIXTEEN_NINE/865.jpeg",
      "score": 5,
      "category": "Overig",
      "location": "Internationaal",
      "reason": "Amerikaanse nationale feestdag zonder Nederlands perspectief of politieke relevantie.",
      "summary": "De Verenigde Staten hebben groots uitgepakt voor hun 250e Onafhankelijkheidsdag. In Washington en New York kwamen honderdduizenden mensen samen voor militaire vliegshows, een vlootparade en spectacula"
    },
    {
      "id": "gooi--en-eemlander-7907886325",
      "source": "Gooi- en Eemlander",
      "title": "Analisten hekelen ’antivoetbal’ Paraguay tegen Frankrijk op WK: ’Moet iemand Mbappé eerst het ziekenhuis inslaan?’",
      "description": "Frankrijk heeft zich op het WK 2026 niet laten verleiden tot het fysieke en provocerende spel van Paraguay. De Zuid-Amerikanen gooiden vanaf de eerste minuut alle aanvallende ambities overboord en probeerden met een stevige dosis overtredingen en tijdrekken de Franse sterren uit hun ritme te halen.",
      "url": "https://www.gooieneemlander.nl/sport/analisten-hekelen-antivoetbal-paraguay-tegen-frankrijk-op-wk-moet-iemand-mbappe-eerst-het-ziekenhuis-inslaan/158283052.html",
      "pubDate": "2026-07-05T08:27:37+00:00",
      "image": "https://prod-img.telegraaf.nl/public/sport/k3cd2g-gettyimages-2284135436.jpg/alternates/BASE_SIXTEEN_NINE/GettyImages-2284135436.jpg",
      "duplicate_sources": [
        "Telegraaf"
      ],
      "score": 8,
      "category": "Overig",
      "location": "Internationaal",
      "reason": "Voetbal WK-analyse zonder Nederlandse relevantie voor opiniesite.",
      "summary": "Frankrijk heeft zich op het WK 2026 niet laten verleiden tot het fysieke en provocerende spel van Paraguay. De Zuid-Amerikanen gooiden vanaf de eerste minuut alle aanvallende ambities overboord en pro"
    },
    {
      "id": "ad-rotterdam-2094165737",
      "source": "AD Rotterdam",
      "title": "Voetbalfeest eindigt in inzet van politiemacht, meerdere arrestaties in Rotterdam",
      "description": "Het voetbalfeest vanwege de WK-winst van Marokko (3-0) eindigde in de wijk Rotterdam-Middelland met de inzet van een politiemacht. Tien mensen werden in de nacht van zaterdag op zondag opgepakt in Rotterdam en regio, onder meer vanwege het afsteken van vuurwerk.",
      "url": "https://www.ad.nl/rotterdam/voetbalfeest-eindigt-in-inzet-van-politiemacht-meerdere-arrestaties-in-rotterdam~a07f7ebd/",
      "pubDate": "2026-07-05T08:27:00+00:00",
      "image": "https://images.ad.nl/NzExMGZkODEyYjFjOGFmZDlhMzUvZGlvLzI3NTU4NTkzMi9maXQtd2lkdGgvNDAw/me-rs-in-actie-op-de-1e-middellandstraat",
      "score": 75,
      "category": "Misdaad",
      "location": "Zuid-Holland",
      "reason": "Lokale ongeregeldheden in Rotterdam met politie-inzet en arrestaties, sterke nieuwswaarde.",
      "summary": "Het voetbalfeest vanwege de WK-winst van Marokko (3-0) eindigde in de wijk Rotterdam-Middelland met de inzet van een politiemacht. Tien mensen werden in de nacht van zaterdag op zondag opgepakt in Rot"
    },
    {
      "id": "omroep-brabant-2435181411",
      "source": "Omroep Brabant",
      "title": "Van der Poel tevreden na tijdrit, maar tempert verwachtingen voor gele trui",
      "description": "Mathieu van der Poel kijkt terug op een 'ok&eacute; tijdrit' bij de start van de Tour de France in Barcelona. Hij hoopte zaterdag in de strijd om de gele trui niet meer dan een halve minuut tot een minuut te moeten toegeven en dat werden 39 seconden op winnaar Jonas Vingegaard. \"Zo sta ik er toch nog een beetje tussen om zondag iets te proberen, maar die etappe is toch nog lastiger dan iedereen de",
      "url": "https://www.omroepbrabant.nl/nieuws/6016114/van-der-poel-tevreden-na-tijdrit-maar-tempert-verwachtingen-voor-gele-trui",
      "pubDate": "2026-07-05T08:26:50+00:00",
      "image": "https://api.omroepbrabant.nl/img/f/1280/720/0.50/0.50/cmV2aXNpb25zLzQ5MjkwNzUtMS5qcGc_c2U9MjA0NS0wMS0wMVQxMCUzQTQwJTNBMDBaJnNpZz10VkZ5bXBuMHZjd2hCaE1YOFJvQkJkNGQ5WVBSSjNuRDBBWnRDbEdhSmdRJTNEJnNwPXImc3ByPWh0dHBzJnNyPWImc3Q9MjAyNS0wMS0wMVQxMCUzQTQwJTNBMDBaJnN2PTIwMjYtMDItMDY=",
      "score": 12,
      "category": "Overig",
      "location": "Internationaal",
      "reason": "Wielrennen/Tour de France zonder Nederlandse politieke of maatschappelijke relevantie.",
      "summary": "Mathieu van der Poel kijkt terug op een 'ok&eacute; tijdrit' bij de start van de Tour de France in Barcelona. Hij hoopte zaterdag in de strijd om de gele trui niet meer dan een halve minuut tot een mi"
    },
    {
      "id": "gooi--en-eemlander-8606196821",
      "source": "Gooi- en Eemlander",
      "title": "Kylian Mbappé schiet Frankrijk vanaf de stip langs vervelend Paraguay: dit heb je vannacht gemist op het WK 2026",
      "description": "Frankrijk heeft in de verzengende hitte van Philadelphia in de achtste finale van het WK 2026 met de nodige moeite Paraguay aan de kant gezet: 1-0 door een benutte strafschop van Kylian Mbappé in de tweede helft.",
      "url": "https://www.gooieneemlander.nl/sport/kylian-mbappe-schiet-frankrijk-vanaf-de-stip-langs-vervelend-paraguay-dit-heb-je-vannacht-gemist-op-het-wk-2026/158282991.html",
      "pubDate": "2026-07-05T08:26:17+00:00",
      "image": "https://prod-img.telegraaf.nl/public/sport/ruuaca-gettyimages-2284675481.jpg/alternates/BASE_SIXTEEN_NINE/GettyImages-2284675481.jpg",
      "duplicate_sources": [
        "Telegraaf"
      ],
      "score": 5,
      "category": "Overig",
      "location": "Internationaal",
      "reason": "Sport zonder Nederlandse relevantie, niet relevant voor PowNed-doelstelling.",
      "summary": "Frankrijk versloeg Paraguay in de achtste finale van het WK 2026 via een strafschop van Mbappé. De wedstrijd vond plaats in Philadelphia."
    },
    {
      "id": "gooi--en-eemlander-4202963402",
      "source": "Gooi- en Eemlander",
      "title": "Marokko verslaat thuisland Canada en staat in kwartfinale WK 2026, maar ziet Ismael Saibari geblesseerd uitvallen",
      "description": "Marokko - dat Nederland versloeg in de achtste finales na strafschoppen - heeft met de nodige pijn en moeite de kwartfinale van het WK 2026 gehaald. Thuisland Canada werd in de achtste finale na een matige eerste helft met 3-0 verslagen. De Marokkanen kregen in de eerste helft wel een domper te verwerken, toen sterspeler Ismael Saibari met een – op het oog – spierblessure het veld in tranen moest ",
      "url": "https://www.gooieneemlander.nl/sport/marokko-verslaat-thuisland-canada-en-staat-in-kwartfinale-wk-2026-maar-ziet-ismael-saibari-geblesseerd-uitvallen/158282949.html",
      "pubDate": "2026-07-05T08:25:14+00:00",
      "image": "https://prod-img.telegraaf.nl/public/sport/uqnuxb-gettyimages-2284650048.jpg/alternates/BASE_SIXTEEN_NINE/GettyImages-2284650048.jpg",
      "duplicate_sources": [
        "Telegraaf"
      ],
      "score": 25,
      "category": "Overig",
      "location": "Internationaal",
      "reason": "Sport WK 2026 met enige Nederland-link, maar te sporadisch relevant voor core PowNed.",
      "summary": "Marokko versloeg Canada in de achtste finale van het WK 2026 en plaatste zich voor de kwartfinale. De selectie verloor wel sterspeler Saibari aan blessure."
    },
    {
      "id": "bn-de-stem-8678118165",
      "source": "BN De Stem",
      "title": "Ex-profvoetballer (53) in coma na verkeersruzie in Turnhout: ‘Mijn dochter was helemaal in paniek’",
      "description": "De man die zaterdagnamiddag levensgevaarlijk gewond raakte bij een verkeersruzie in het Belgische Turnhout, is de 53-jarige ex-profvoetballer Karel Snoeckx. Hij ligt momenteel in coma. Zijn familie is enorm aangedaan. „We zijn kapot van verdriet. Karel is de zachtheid zelve”, zegt zijn echtgenote Lindsy tegen de Belgische krant HLN. „Het had een prachtige dag moeten worden met onze dochter en scho",
      "url": "https://www.bndestem.nl/buitenland/ex-profvoetballer-53-in-coma-na-verkeersruzie-in-turnhout-mijn-dochter-was-helemaal-in-paniek~ab18de92/",
      "pubDate": "2026-07-05T08:23:35+00:00",
      "image": "https://images.bndestem.nl/NzIxNWNjZGEzZmI3ODhiNTE1NzAvZGlvLzI3NTU4NDAwMy9maXQtd2lkdGgvNDAw/verkeersagressie-op-het-kruispunt-van-de-steenweg-op-oosthoven-en-de-hogestraat-in-turnhout-inzet-karel-snoeckx-en-zijn-vouw-lindsy",
      "score": 15,
      "category": "Misdaad",
      "location": "Internationaal",
      "reason": "Belgisch incident zonder Nederlandse relevantie of politieke/maatschappelijke impact.",
      "summary": "Een 53-jarige Belgische ex-profvoetballer raakte ernstig gewond bij een verkeersruzie in Turnhout. Hij ligt momenteel in coma."
    },
    {
      "id": "telegraaf-1313099208",
      "source": "Telegraaf",
      "title": "Eurosport-commentator Karsten Kroon over de Tour: ’Er is weinig aan Tadej Pogacar te doen, vrees ik’",
      "description": "Hij wilde de zomers vaak vrijhouden om vooral tijd met z’n kinderen door te brengen. Maar nu de oudste dochters van Karsten Kroon de leeftijd hebben om zonder ouders de vakantieperiode te beleven, heeft de oud-renner eindelijk tijd de Tour de France te becommentariëren.",
      "url": "https://www.telegraaf.nl/sport/wielrennen/eurosport-commentator-karsten-kroon-over-de-tour-er-is-weinig-aan-tadej-pogacar-te-doen-vrees-ik/158265181.html",
      "pubDate": "2026-07-05T08:21:57+00:00",
      "image": "https://prod-img.telegraaf.nl/public/sport/3cweur-karsten-kroon-eurosport-hbo-max-2.jpg/alternates/BASE_SIXTEEN_NINE/Karsten%20Kroon_Eurosport_HBO%20Max%202.jpg",
      "score": 8,
      "category": "Overig",
      "location": "Landelijk",
      "reason": "Sportjournalistiek-profiel zonder nieuwswaarde of maatschappelijk belang.",
      "summary": "Karsten Kroon, oud-renner en Eurosport-commentator, zal dit zomer de Tour de France becommentariëren. Hij heeft nu meer tijd door volwassen kinderen."
    },
    {
      "id": "gooi--en-eemlander-2729219957",
      "source": "Gooi- en Eemlander",
      "title": "Nieuwe regels kunnen nabestaanden duizenden euro’s pensioen kosten: ’Wie dit niet op tijd regelt, laat partner met flink gat achter’",
      "description": "Nadenken over de dood is voor niemand leuk, maar van levensbelang. Want stellen die zich niet voorbereiden op een financieel gezonde toekomst, kunnen duizenden euro’s mislopen aan nabestaandenpensioen als een van de twee plots overlijdt. Het nieuwe pensioenstelsel vraagt om actie.",
      "url": "https://www.gooieneemlander.nl/uitgelicht/nieuwe-regels-kunnen-nabestaanden-duizenden-euros-pensioen-kosten-wie-dit-niet-op-tijd-regelt-laat-partner-met-flink-gat-achter/158282811.html",
      "pubDate": "2026-07-05T08:20:25+00:00",
      "image": "https://prod-img.telegraaf.nl/public/incoming/ftq4rd-gettyimages-104302941.jpg/alternates/BASE_SIXTEEN_NINE/GettyImages-104302941.jpg",
      "duplicate_sources": [
        "Telegraaf"
      ],
      "score": 35,
      "category": "Overig",
      "location": "Landelijk",
      "reason": "Praktische pensioeninfo met maatschappelijk belang, maar geen controverse of nieuws.",
      "summary": "Nieuwe pensioenstelsel-regels kunnen nabestaanden duizenden euro's kosten zonder voorbereiding. Experts waarschuwen voor financiële gevolgen."
    },
    {
      "id": "ad-3247230159",
      "source": "AD",
      "title": "Dankzij het gaatje in het vliegtuigraam kun je naar buiten kijken, maar dat is niet het enige waar het voor is",
      "description": "Stap jij binnenkort in het vliegtuig? In elk vliegtuigraam zit een piepklein gaatje. Dat lijkt misschien geen goed idee, maar de gaatjes onderin het vliegtuigraam spelen een belangrijke rol voor onder meer de veiligheid aan boord.",
      "url": "https://www.ad.nl/reizen/dankzij-het-gaatje-in-het-vliegtuigraam-kun-je-naar-buiten-kijken-maar-dat-is-niet-het-enige-waar-het-voor-is~a10b7d84/",
      "pubDate": "2026-07-05T08:15:00+00:00",
      "image": "https://images.ad.nl/MjU5YjBiMTRkYmMyMTA1OWE2MGEvZGlvLzI3NTA3OTYxNS9maXQtd2lkdGgvNDAw/het-kleine-gaatje-onderin-een-vliegtuigraam-heeft-twee-belangrijke-functies",
      "duplicate_sources": [
        "BN De Stem"
      ],
      "score": 5,
      "category": "Overig",
      "location": "Internationaal",
      "reason": "Algemene vluchtvaartcuriositeit zonder Nederlandse of maatschappelijk-kritieke relevantie.",
      "summary": "Vliegtuigramen bevatten kleine gaatjes die onder meer veiligheid en drukregeling beïnvloeden. Dit artikel legt de functie uit."
    },
    {
      "id": "nu.nl-1933828768",
      "source": "NU.nl",
      "title": "Twee doden bij auto-ongeluk in Noord-Brabant, onder wie 15-jarige jongen",
      "description": "Bij een ongeluk in de Noord-Brabantse gemeente Maashorst zijn zondagochtend vroeg twee mensen om het leven gekomen. Een van hen is een vijftienjarige jongen uit Uden.",
      "url": "https://www.nu.nl/binnenland/6401956/twee-doden-bij-auto-ongeluk-in-noord-brabant-onder-wie-15-jarige-jongen.html",
      "pubDate": "2026-07-05T08:04:43+00:00",
      "image": "https://images.nu.nl/m/l29xpeqapzu1_sqr256/29/0/3377/3377/twee-doden-bij-auto-ongeluk-in-noord-brabant-onder-wie-15-jarige-jongen.jpg",
      "duplicate_sources": [
        "AD",
        "PZC"
      ],
      "score": 72,
      "category": "Misdaad",
      "location": "Noord-Brabant",
      "reason": "Ernstig ongeval met fatale afloop, lokaal nieuws met maatschappelijk belang.",
      "summary": "Twee personen, onder wie een 15-jarige jongen uit Uden, kwamen om het leven bij een auto-ongeluk in Maashorst. Het incident vond zondagochtend plaats."
    },
    {
      "id": "de-stentor-4500627746",
      "source": "De Stentor",
      "title": "Zwolle wil meer historische schepen naar de binnenstad lokken",
      "description": "Meer historische schepen in de binnenstad van Zwolle. Dat was een wens van de politiek en de gemeente gaat daar nu meer aan de slag. Op drie plekken wordt ruim baan gemaakt.",
      "url": "https://www.destentor.nl/zwolle/zwolle-wil-meer-historische-schepen-naar-de-binnenstad-lokken~a7e157a6/",
      "pubDate": "2026-07-05T08:00:59+00:00",
      "image": "https://images.destentor.nl/ZDA0OGE3MjE5NWQ0YWRmNTg0ZDEvZGlvLzI3NTU2NTk3NC9maXQtd2lkdGgvNDAw/st20260704-3581-zwolle-czwolle-wil-plek-creeren-waar-historische-schepen-tijdelijk-kunnen-aanleggen-aan-de-schuttevaerkade-voor-de-parkeerplaats-en-aan-de-thorbeckewal-en-buitenkant-2026-fotopersburo-frans-paalman-zwolle",
      "score": 28,
      "category": "Overig",
      "location": "Overijssel",
      "reason": "Lokaal stadsontwikkelings-initiatief zonder controverse of satirische insteek.",
      "summary": "Zwolle wil meer historische schepen naar de binnenstad lokken en maakt op drie plekken ruimte vrij. Dit volgt op politieke wensen."
    },
    {
      "id": "nos-4641395878",
      "source": "NOS",
      "title": "Ongeluk in dorp Zeeland kost twee mensen het leven, onder wie 15-jarige",
      "description": "In het Brabantse dorp Zeeland is vanochtend een verkeersongeluk gebeurd waarbij twee mensen om het leven zijn gekomen. De auto waarin ze zaten, botste op de Boekelsedijk tegen een boom en vloog in brand. Een van de slachtoffers is een 15-jarige jongen uit Uden. De identiteit van het tweede slachtoffer is nog niet bekend, meldt de politie aan Omroep Brabant. De weg ligt bezaaid met brokstukken en i",
      "url": "https://nos.nl/artikel/2621711-ongeluk-in-dorp-zeeland-kost-twee-mensen-het-leven-onder-wie-15-jarige",
      "pubDate": "2026-07-05T08:00:22+00:00",
      "image": "https://images.cdn.nos.nl/6/4/5/m/n/4/P84HPuPfth7iPnr1KayZuwhnV9HaKTYCTFpkbSR/0x96x1920x1080-1024x576.webp",
      "score": 68,
      "category": "Misdaad",
      "location": "Noord-Brabant",
      "reason": "Tragisch verkeersongeluk met dodelijke afloop; lokaal nieuwswaarde maar geen PowNed-kernthema's.",
      "summary": "Een auto botste tegen een boom in het Brabantse dorp Zeeland en vloog in brand. Twee personen, onder wie een 15-jarige jongen, kwamen om het leven."
    },
    {
      "id": "telegraaf-133536367",
      "source": "Telegraaf",
      "title": "Prins Pieter-Christiaan feest in Johan Cruijff ArenA: Bruno Mars is ’magnifiek’",
      "description": "Prins Pieter-Christiaan heeft zaterdagavond het concert van Bruno Mars bezocht in de Johan Cruijff ArenA in Amsterdam. De derde zoon van prinses Margriet deelde op Instagram beelden van het optreden.",
      "url": "https://www.telegraaf.nl/entertainment/royals/prins-pieter-christiaan-feest-in-johan-cruijff-arena-bruno-mars-is-magnifiek/158282294.html",
      "pubDate": "2026-07-05T08:00:00+00:00",
      "image": "https://prod-img.telegraaf.nl/public/entertainment/sterren/e86tfp-anp-562148533.jpg/alternates/BASE_SIXTEEN_NINE/ANP-562148533.jpg",
      "score": 12,
      "category": "Opmerkelijk",
      "location": "Noord-Holland",
      "reason": "Royalty op concert is showbiz-roddel; geen satirische waarde of PowNed-relevantie.",
      "summary": "Prins Pieter-Christiaan bezocht het Bruno Mars-concert in de Johan Cruijff ArenA. Hij deelde beelden van het optreden op Instagram."
    },
    {
      "id": "ad-1645804917",
      "source": "AD",
      "title": "Klasgenootjes Krajicek en Boogerd zien elkaar 30 jaar na doorbraak weer: ‘Na carrière lang een schuldgevoel’",
      "description": "Dertig zomers geleden zetten twee oud-klasgenootjes uit Den Haag met hun prestaties op Wimbledon en in de Tour de France de internationale sportwereld op z’n kop. We brachten Richard Krajicek (54) en Michael Boogerd (54) na lange tijd bij elkaar voor een reünie-interview. Een goed gesprek over plantjes op tafel, tattoos op armen, meester Bob en George Washington.",
      "url": "https://www.ad.nl/tennis/klasgenootjes-krajicek-en-boogerd-zien-elkaar-30-jaar-na-doorbraak-weer-na-carriere-lang-een-schuldgevoel~a221b01a/",
      "pubDate": "2026-07-05T08:00:00+00:00",
      "image": "https://images.ad.nl/NmQxOGNmMWE3NmI0OTA2MjMzNzcvZGlvLzI3NTQ3MDcyMS9maXQtd2lkdGgvNDAw/cvdv",
      "duplicate_sources": [
        "BN De Stem",
        "De Stentor",
        "PZC"
      ],
      "score": 18,
      "category": "Overig",
      "location": "Zuid-Holland",
      "reason": "Nostalgie-artikel over oude sporters; puur human interest zonder controversiële of satirische lading.",
      "summary": "Oud-klasgenootjes Richard Krajicek en Michael Boogerd zien elkaar 30 jaar later weer na hun successen. Het artikel bevat een reünie-interview tussen de twee sporters."
    },
    {
      "id": "bn-de-stem-6093498023",
      "source": "BN De Stem",
      "title": "Wat Eten We Vandaag: Geroosterde bloemkool met gnocchi cacio e pepe van Hugo Kennis",
      "description": "Hugo: ‘Bloemkool past perfect bij gnocchi, en door de ansjovisdressing krijgt hij een heerlijk ziltige umamismaak. Eet je liever vega, vervang de ansjovis dan door miso. De dressing is trouwens ook heerlijk bij spitskool!’",
      "url": "https://www.bndestem.nl/koken-en-eten/wat-eten-we-vandaag-geroosterde-bloemkool-met-gnocchi-cacio-e-pepe-van-hugo-kennis~afc3c549a/",
      "pubDate": "2026-07-05T08:00:00+00:00",
      "image": "https://images.bndestem.nl/ODQ3MGJhN2EwZTgzZGEwYjY2MmYvZGlvLzI3NTE1MjY2Ni9maXQtd2lkdGgvNDAw/e",
      "duplicate_sources": [
        "De Stentor",
        "PZC"
      ],
      "score": 2,
      "category": "Overig",
      "location": "Overig",
      "reason": "Recept-artikel zonder nieuws-, controversie- of maatschappelijke relevantie.",
      "summary": "Een kookkolom presenteert een recept voor geroosterde bloemkool met gnocchi cacio e pepe. Hugo Kennis geeft voedingstips en vegetarische alternatieven."
    }
  ]
}