{
  "generatedAt": "2026-06-05T16:20:54.971907+00:00",
  "stats": {
    "feeds_total": 43,
    "feeds_succeeded": 26,
    "feeds_failed": 17,
    "items_collected": 715,
    "items_after_dedupe": 60,
    "items_scored": 60,
    "items_high_score": 15
  },
  "fetchedFeeds": [
    {
      "source": "NOS",
      "url": "https://feeds.nos.nl/nosnieuwsalgemeen",
      "count": 20
    },
    {
      "source": "NOS",
      "url": "https://feeds.nos.nl/nosnieuwsbinnenland",
      "count": 20
    },
    {
      "source": "NOS",
      "url": "https://feeds.nos.nl/nosnieuwspolitiek",
      "count": 8
    },
    {
      "source": "NOS",
      "url": "https://feeds.nos.nl/nosnieuwsopmerkelijk",
      "count": 2
    },
    {
      "source": "NU.nl",
      "url": "https://www.nu.nl/rss/algemeen",
      "count": 30
    },
    {
      "source": "Telegraaf",
      "url": "https://www.telegraaf.nl/rss",
      "count": 50
    },
    {
      "source": "Telegraaf",
      "url": "https://www.telegraaf.nl/binnenland/rss",
      "count": 50
    },
    {
      "source": "AD",
      "url": "https://www.ad.nl/home/rss.xml",
      "count": 30
    },
    {
      "source": "AD",
      "url": "https://www.ad.nl/binnenland/rss.xml",
      "count": 30
    },
    {
      "source": "Volkskrant",
      "url": "https://www.volkskrant.nl/nieuws-achtergrond/rss.xml",
      "count": 0
    },
    {
      "source": "Trouw",
      "url": "https://www.trouw.nl/home/rss.xml",
      "count": 71
    },
    {
      "source": "BN De Stem",
      "url": "https://www.bndestem.nl/home/rss.xml",
      "count": 30
    },
    {
      "source": "De Stentor",
      "url": "https://www.destentor.nl/home/rss.xml",
      "count": 30
    },
    {
      "source": "PZC",
      "url": "https://www.pzc.nl/home/rss.xml",
      "count": 30
    },
    {
      "source": "Gooi- en Eemlander",
      "url": "https://www.gooieneemlander.nl/rss",
      "count": 50
    },
    {
      "source": "Omroep Brabant",
      "url": "https://www.omroepbrabant.nl/rss",
      "count": 25
    },
    {
      "source": "RTV Noord",
      "url": "https://www.rtvnoord.nl/rss",
      "count": 49
    },
    {
      "source": "Crimesite",
      "url": "https://www.crimesite.nl/feed/",
      "count": 14
    },
    {
      "source": "Regio 15 (Den Haag)",
      "url": "https://regio15.nl/feed/",
      "count": 0
    },
    {
      "source": "AD Den Haag",
      "url": "https://www.ad.nl/den-haag/rss.xml",
      "count": 30
    },
    {
      "source": "AD Rotterdam",
      "url": "https://www.ad.nl/rotterdam/rss.xml",
      "count": 30
    },
    {
      "source": "Dagblad010",
      "url": "https://dagblad010.nl/feed/",
      "count": 59
    },
    {
      "source": "Den Haag Centraal",
      "url": "https://www.denhaagcentraal.net/feed/",
      "count": 6
    },
    {
      "source": "Dordt Centraal",
      "url": "https://dordtcentraal.nl/feed/",
      "count": 10
    },
    {
      "source": "OPEN Rotterdam",
      "url": "https://openrotterdam.nl/feed/",
      "count": 10
    },
    {
      "source": "Sleutelstad",
      "url": "https://sleutelstad.nl/feed/",
      "count": 31
    }
  ],
  "failedFeeds": [
    {
      "source": "RTL",
      "url": "https://www.rtlnieuws.nl/service/rss/nieuws/index.xml",
      "error": "http: 404 Client Error: Not Found for url: https://www.rtl.nl/service/rss/nieuws/index.xml"
    },
    {
      "source": "Hart van Nederland",
      "url": "https://www.hartvannederland.nl/nieuws/rss.xml",
      "error": "http: 404 Client Error: Not Found for url: https://www.hartvannederland.nl/nieuws/rss.xml"
    },
    {
      "source": "Omroep West",
      "url": "https://www.omroepwest.nl/rss",
      "error": "http: 404 Client Error: Not Found for url: https://www.omroepwest.nl/rss"
    },
    {
      "source": "NH Nieuws",
      "url": "https://www.nhnieuws.nl/rss",
      "error": "parse: <unknown>:2:5449: not well-formed (invalid token)"
    },
    {
      "source": "L1 Limburg",
      "url": "https://www.l1.nl/rss",
      "error": "http: 404 Client Error: Not Found for url: https://www.l1.nl/rss"
    },
    {
      "source": "AT5",
      "url": "https://www.at5.nl/rss",
      "error": "parse: <unknown>:2:4943: not well-formed (invalid token)"
    },
    {
      "source": "Rijnmond",
      "url": "https://www.rijnmond.nl/rss",
      "error": "http: 404 Client Error: Not Found for url: https://www.rijnmond.nl/rss"
    },
    {
      "source": "RTV Utrecht",
      "url": "https://www.rtvutrecht.nl/rss",
      "error": "parse: <unknown>:2:0: syntax error"
    },
    {
      "source": "Politie",
      "url": "https://www.politie.nl/rss/nieuws/",
      "error": "http: 404 Client Error: Not Found for url: https://www.politie.nl/rss/nieuws/"
    },
    {
      "source": "De Havenloods",
      "url": "https://www.dehavenloods.nl/feed/",
      "error": "http: 404 Client Error: Not Found for url: https://www.dehavenloods.nl/feed"
    },
    {
      "source": "Leidsch Dagblad",
      "url": "https://www.leidschdagblad.nl/rss.xml",
      "error": "http: 403 Client Error: Forbidden for url: https://www.leidschdagblad.nl/rss.xml"
    },
    {
      "source": "Hart van Holland",
      "url": "https://www.hartvanzuidplas.nl/feed/",
      "error": "http: 404 Client Error: Not Found for url: https://www.hartvanzuidplas.nl/feed"
    },
    {
      "source": "Briels Nieuwsland",
      "url": "https://www.brielsnieuwsland.nl/feed/",
      "error": "http: 404 Client Error: Not Found for url: https://www.brielsnieuwsland.nl/feed"
    },
    {
      "source": "Delft op Zondag",
      "url": "https://www.delftopzondag.nl/feed/",
      "error": "http: 404 Client Error: Not Found for url: https://www.delftopzondag.nl/feed"
    },
    {
      "source": "Het Kontakt",
      "url": "https://www.hetkontakt.nl/feed/",
      "error": "http: 404 Client Error: Not Found for url: https://www.hetkontakt.nl/feed"
    },
    {
      "source": "Kijk op Zuid-Holland",
      "url": "https://www.kijkopzuid-holland.nl/feed/",
      "error": "http: HTTPSConnectionPool(host='www.kijkopzuid-holland.nl', port=443): Max retries exceeded with url: /feed/ (Caused by NewConnectionError(\"HTTPSConnection(host='www.kijkopzuid-holland.nl', port=443): Failed to establish a new connection: [Errno 101] Network is unreachable\"))"
    },
    {
      "source": "RTV Dordrecht",
      "url": "https://www.rtvdordrecht.nl/feed/",
      "error": "http: 404 Client Error: Not Found for url: https://www.rtvdordrecht.nl/404"
    }
  ],
  "items": [
    {
      "id": "dagblad010-7488551831",
      "source": "Dagblad010",
      "title": "Dader (37) kunstroof Assen verkoopt vanuit de gevangenis T-shirts",
      "description": "Dader (37) kunstroof Assen verkoopt vanuit de gevangenis T-shirts",
      "url": "https://dagblad010.nl/landelijk/dader-37-kunstroof-assen-verkoopt-vanuit-de-gevangenis-t-shirts",
      "pubDate": "2026-06-05T17:07:00+00:00",
      "image": "https://media.digitaaldagblad.nl/files/shares/dagblad070/kunstroof6a22e5d588872.jpg",
      "score": 72,
      "category": "Misdaad",
      "location": "Drenthe",
      "reason": "Lokaal misdaadverhaal met bizarre twist: kunstroover verkoopt merchandise vanuit cel.",
      "summary": "Een 37-jarige dader van een kunstroof in Assen verkoopt T-shirts vanuit de gevangenis. Het verhaal combineert criminaliteit met opmerkelijke details."
    },
    {
      "id": "ad-3495519565",
      "source": "AD",
      "title": "Zo laat komt Max Verstappen zaterdag in actie tijdens eerste Europese race van het seizoen",
      "description": "Het Formule 1-circus gaat de oversteek maken van Noord-Amerika naar Europa. Voor Max Verstappen en zijn collega’s staat misschien wel de meest prestigieuze race van de kalender op het programma: de Grand Prix van Monaco. Lees hieronder hoe laat de coureurs in actie komen.",
      "url": "https://www.ad.nl/formule-1/zo-laat-komt-max-verstappen-zaterdag-in-actie-tijdens-eerste-europese-race-van-het-seizoen~aa97896b/",
      "pubDate": "2026-06-05T16:15:00+00:00",
      "image": "https://images.ad.nl/YTdjMGNjZDhmNzMyNjRhMTA0NmQvZGlvLzI3NDQxOTI3Ny9maXQtd2lkdGgvNDAw/2026-06-05-16-57-07-monaco-max-verstappen-red-bull-racing-voorafgaand-aan-de-tweede-vrije-training-op-het-circuit-de-monaco-in-aanloop-naar-de-monaco-grand-prix-anp-sem-van-der-wal",
      "score": 5,
      "category": "Overig",
      "location": "Internationaal",
      "reason": "Standaard Formule 1-berichtgeving zonder Nederlandse relevantie of controversieel element.",
      "summary": "Max Verstappen rijdt dit weekend in Monaco. Het artikel geeft starttijden voor de Grand Prix."
    },
    {
      "id": "nu.nl-819880603",
      "source": "NU.nl",
      "title": "Staalslakken vanaf volgend jaar niet helemaal verboden, wel vergunning nodig",
      "description": "Het gebruik van staalslakken als bouwstof wordt vanaf volgend jaar niet helemaal verboden, maar mag alleen nog als kan worden bewezen dat milieu en gezondheid niet worden geschaad. Dat is het voornemen van staatssecretaris Annet Bertram (Milieu).",
      "url": "https://www.nu.nl/klimaat/6398373/staalslakken-vanaf-volgend-jaar-niet-helemaal-verboden-wel-vergunning-nodig.html",
      "pubDate": "2026-06-05T16:07:03+00:00",
      "image": "https://images.nu.nl/m/3hyxb1sakywa_sqr256/263/0/4232/4232/staalslakken-vanaf-volgend-jaar-niet-helemaal-verboden-wel-vergunning-nodig.jpg",
      "score": 48,
      "category": "Politiek",
      "location": "Landelijk",
      "reason": "Beleidsbesluit over staalslakken relevant voor milieubeleid, maar niet urgent of scandaleus.",
      "summary": "Staatssecretaris Bertram kondigt aan dat staalslakken vanaf volgend jaar niet volledig verboden worden. Het gebruik vereist voortaan vergunning en milieubewijs."
    },
    {
      "id": "nos-9268334919",
      "source": "NOS",
      "title": "Franse nazaat d'Artagnan boos over fouten bij opgraven botresten in Maastricht",
      "description": "In de geboortestreek van d'Artagnan, de beroemde Franse musketier van wie mogelijk het skelet in Maastricht is ontdekt, wordt met verbazing en verontrusting gekeken naar de gang van zaken rondom het onderzoek. Bij de opgraving zouden ernstige fouten zijn gemaakt , waardoor een aanzienlijk deel van de botresten mogelijk niet meer kan worden geïdentificeerd. \"Wat me kwaad zou maken, is als de beende",
      "url": "https://nos.nl/artikel/2617284-franse-nazaat-d-artagnan-boos-over-fouten-bij-opgraven-botresten-in-maastricht",
      "pubDate": "2026-06-05T16:05:11+00:00",
      "image": "https://images.cdn.nos.nl/8/6/r/d/C/R/fBPQ614mYXsjX8SUP8CYe5ZAYn1FZgjr6gtBbgs/1x7x2240x1260-1024x576.webp",
      "score": 58,
      "category": "Opmerkelijk",
      "location": "Limburg",
      "reason": "Intrigerend historisch verhaal met kritiek op onderzoeksfouten in Maastricht.",
      "summary": "Franse nazaat van d'Artagnan kritiseert ernstige fouten bij opgraving van skeletten in Maastricht. Mogelijk kunnen botresten niet meer goed worden geïdentificeerd."
    },
    {
      "id": "nu.nl-7235845709",
      "source": "NU.nl",
      "title": "Alleen Ferrari-coureurs sneller dan Verstappen in tweede training Monaco",
      "description": "Max Verstappen heeft vrijdag de derde tijd genoteerd in de tweede vrije training voor de Grand Prix van Monaco. Alleen beide Ferrari-coureurs waren sneller dan de Red Bull-rijder.",
      "url": "https://www.nu.nl/formule-1/6398375/alleen-ferrari-coureurs-sneller-dan-verstappen-in-tweede-training-monaco.html",
      "pubDate": "2026-06-05T16:03:27+00:00",
      "image": "https://images.nu.nl/m/7ouxhu7aj6kr_sqr256/387/0/4312/4312/alleen-ferrari-coureurs-sneller-dan-verstappen-in-tweede-training-monaco.jpg",
      "score": 3,
      "category": "Overig",
      "location": "Internationaal",
      "reason": "Routinematige Formule 1-trainingsresultaten zonder controversie of Nederlands belang.",
      "summary": "Verstappen eindigde derde in de tweede vrije training voor Monaco. Alleen Ferrari-coureurs waren sneller."
    },
    {
      "id": "ad-2640008284",
      "source": "AD",
      "title": "Oranje Leeuwinnen hervatten jacht op WK-ticket tegen Ierland, concurrent Frankrijk speelt in Polen",
      "description": "De Oranje Leeuwinnen hervatten vanavond de jacht op een ticket voor het WK voetbal van 2027. De ploeg van bondscoach Arjan Veurink neemt het in Cork op tegen Ierland. Volg het hier vanaf 20.30 uur live!",
      "url": "https://www.ad.nl/voetbal/oranje-leeuwinnen-hervatten-jacht-op-wk-ticket-tegen-ierland-concurrent-frankrijk-speelt-in-polen~a5613f1b/",
      "pubDate": "2026-06-05T16:02:00+00:00",
      "image": "https://images.ad.nl/OTlmYThkMWYwODczMGI4OGU2ODcvZGlvLzI3MDg4ODYzMy9maXQtd2lkdGgvNDAw/utrecht-07-03-2026-stadium-galgenwaard-season-2025-2026-women-s-european-qualifiers-match-between-the-netherlands-and-republic-of-ireland-picture-shows-netherlands-player-dominique-janssen",
      "score": 8,
      "category": "Overig",
      "location": "Landelijk",
      "reason": "Standaard sportberichtgeving over voetbalwedstrijd zonder controversieel element.",
      "summary": "Oranje Leeuwinnen spelen tegen Ierland voor WK-kwalificatie. De wedstrijd begint om 20:30 uur."
    },
    {
      "id": "telegraaf-3444525637",
      "source": "Telegraaf",
      "title": "Max Verstappen doet goed mee in Monaco, Lewis Hamilton rijdt snelste tijd in tweede vrije training",
      "description": "Max Verstappen doet vooralsnog verrassend goed mee in Monaco, richting de Grand Prix in het prinsdom van komende zondag. Ook tijdens de tweede vrije training reed hij de derde tijd.",
      "url": "https://www.telegraaf.nl/sport/autosport/max-verstappen-doet-goed-mee-in-monaco-lewis-hamilton-rijdt-snelste-tijd-in-tweede-vrije-training/155426314.html",
      "pubDate": "2026-06-05T16:01:12+00:00",
      "image": "https://prod-img.telegraaf.nl/public/sport/autosport/9lkvsl-gettyimages-2280018436.jpg/alternates/BASE_SIXTEEN_NINE/GettyImages-2280018436.jpg",
      "score": 4,
      "category": "Overig",
      "location": "Internationaal",
      "reason": "Routinematige F1-trainingsberichtgeving zonder Nederlands of controversieel belang.",
      "summary": "Verstappen haalde derde tijd in tweede vrije training Monaco. Hamilton reed de snelste tijd."
    },
    {
      "id": "ad-6452587875",
      "source": "AD",
      "title": "Max Verstappen eindigt eerste dag sterk met derde tijd in tweede training, verschil met beide Ferrari’s klein",
      "description": "Max Verstappen is al derde geëindigd in de tweede vrije training voor de GP van Monaco. De viervoudig wereldkampioen was net als eerder vandaag alleen trager dan Lewis Hamilton en Charles Leclerc, maar het verschil met de Ferrari’s is klein (een dikke tiende met Hamilton). Dat biedt dus hoop voor Verstappen voor de rest van het weekend.",
      "url": "https://www.ad.nl/formule-1/max-verstappen-eindigt-eerste-dag-sterk-met-derde-tijd-in-tweede-training-verschil-met-beide-ferraris-klein~acb9d7a2/",
      "pubDate": "2026-06-05T16:01:00+00:00",
      "image": "https://images.ad.nl/ODY2YmJkYzg3YzJlYmVmOGExZDAvZGlvLzI3NDQxOTQ4OC9maXQtd2lkdGgvNDAw/2026-06-05-17-08-19-monaco-max-verstappen-red-bull-racing-tijdens-de-tweede-vrije-training-op-het-circuit-de-monaco-in-aanloop-naar-de-monaco-grand-prix-anp-sem-van-der-wal",
      "duplicate_sources": [
        "BN De Stem",
        "De Stentor",
        "PZC"
      ],
      "score": 5,
      "category": "Overig",
      "location": "Internationaal",
      "reason": "Standaard Formule 1-trainingsverslag zonder controversie, politieke of maatschappelijke relevantie.",
      "summary": "Verstappen eindigt derde in tweede vrije training Monaco met klein verschil tot Ferrari. Weekend biedt kansen."
    },
    {
      "id": "ad-rotterdam-4446462198",
      "source": "AD Rotterdam",
      "title": "Lijken op Ruud Gullit in de stijl van EK ’88? Jasper bedenkt website die dat mogelijk maakt",
      "description": "De legendarische volley van Marco van Basten tijdens het EK ’88: wie kent dat voetbalmoment niet? Maar dat gevoel van euforie, hoe krijg je dat weer terug? Daar had Jasper Verbunt (51), mede-eigenaar van het Rotterdamse bedrijf Redkiwi, wel een leuk idee voor. Zijn site waarop je jezelf kunt omtoveren in EK88-stijl is nu een online hit.",
      "url": "https://www.ad.nl/rotterdam/lijken-op-ruud-gullit-in-de-stijl-van-ek-88-jasper-bedenkt-website-die-dat-mogelijk-maakt~a914fc6b/",
      "pubDate": "2026-06-05T16:00:29+00:00",
      "image": "https://images.ad.nl/OGRjM2MzNmZjNDU4ZTljZjAwM2QvZGlvLzI3NDQwNTUxNi9maXQtd2lkdGgvNDAw/ek-88-look",
      "score": 15,
      "category": "Overig",
      "location": "Zuid-Holland",
      "reason": "Lokaal tech-verhaal zonder politieke, maatschappelijke of controversiële relevantie.",
      "summary": "Een Rotterdamse ondernemer heeft een website gelanceerd waarmee gebruikers zichzelf kunnen omtoveren in EK '88-stijl. Het project is online populair geworden en aangeboden als een nostalgische interactieve tool."
    },
    {
      "id": "pzc-5813440401",
      "source": "PZC",
      "title": "Bergenaar die vrouw in Vlissingen neerstak, blijft voorlopig in de cel, maar gaat nu wel praten met de politie",
      "description": "Wat bezielde de man die vorig jaar september in Vlissingen een 63-jarige vrouw zomaar in haar hals stak? Die vraag hangt al negen maanden als een donkere wolk boven de strafzaak tegen Noel D. (29).",
      "url": "https://www.pzc.nl/vlissingen/bergenaar-die-vrouw-in-vlissingen-neerstak-blijft-voorlopig-in-de-cel-maar-gaat-nu-wel-praten-met-de-politie~a56da91e/",
      "pubDate": "2026-06-05T16:00:25+00:00",
      "image": "https://images.pzc.nl/ZjhjZjY5NGU2NmMyNjU2MGQxMGIvZGlvLzI3NDQwNTg0Mi9maXQtd2lkdGgvNDAw/verdachte-aangehouden-bij-station-souburg-de-rechtbank-in-middelburg",
      "score": 72,
      "category": "Misdaad",
      "location": "Zeeland",
      "reason": "Ernstig misdrijf (poging doodslag) met emotionele achtergrond; lokale true crime van belang.",
      "summary": "Een 29-jarige man uit Bergen staat terecht voor het neersteken van een 63-jarige vrouw in Vlissingen in september vorig jaar. Na negen maanden gaat verdachte Noel D. nu met politie praten over het motief."
    },
    {
      "id": "ad-den-haag-245281035",
      "source": "AD Den Haag",
      "title": "Voetbalvrienden van GONA verenigen voor ernstig zieke Mick: ‘Eerder maanden dan jaren te leven’",
      "description": "Voor de zestiende keer vindt zaterdag de Dag van de Haagse Voetbalhistorie plaats. Een dag in het teken van verdwenen Haagse voetbalclubs. Ter ere van de ernstig zieke Mick Mallander (69), die niet lang meer te leven heeft, doet er dit jaar ook een team van GONA mee. „Het moet een gezellige dag worden, zonder poespas.”",
      "url": "https://www.ad.nl/regiosport-den-haag/voetbalvrienden-van-gona-verenigen-voor-ernstig-zieke-mick-eerder-maanden-dan-jaren-te-leven~a30e38fa/",
      "pubDate": "2026-06-05T16:00:25+00:00",
      "image": "https://images.ad.nl/ZTc4Y2U3M2M5YTlhZGFlZmYzNzMvZGlvLzI3NDM4OTc5OC9maXQtd2lkdGgvNDAw/ar20260604-0773-20260603-haagse-voetbal-history-v-l-n-r-jan-renirie-mick-mallander-en-dennis-elsinga",
      "score": 25,
      "category": "Overig",
      "location": "Zuid-Holland",
      "reason": "Lokaal voetbaleveneiment met humanintrest, maar geen politieke of controversiële waarde.",
      "summary": "De zestiende editie van de Dag van de Haagse Voetbalhistorie vindt zaterdag plaats ter ere van de zieke Mick Mallander. Een GONA-team doet dit jaar voor het eerst mee aan het evenement."
    },
    {
      "id": "gooi--en-eemlander-9049004474",
      "source": "Gooi- en Eemlander",
      "title": "Voor een tientje dronken worden lukt niet meer, maar de Baarnse barman Koen Witteveen scoort er wel een nieuwe single mee: ’Zo blauw als een tientje’",
      "description": "De Baarnse zingende barman Koen Witteveen (24) heeft een nieuwe single uitgebracht: ’Zo blauw als een tientje’. Hij presenteerde zijn derde lied in café Prins Hendrik, de kroeg waar hij nog altijd met veel plezier achter de bar staat. Na de singles ’Samen’ en ’Ons Mooie Stamcafé’ hoopt hij met zijn nieuwste nummer opnieuw een stap te zetten in zijn muzikale carrière.",
      "url": "https://www.gooieneemlander.nl/regio/gooi-en-eemland/voor-een-tientje-dronken-worden-lukt-niet-meer-maar-de-baarnse-barman-koen-witteveen-scoort-er-wel-een-nieuwe-single-mee-zo-blauw-als-een-tientje/155351653.html",
      "pubDate": "2026-06-05T16:00:00+00:00",
      "image": "https://prod-img.gooieneemlander.nl/public/incoming/tmuiv4-4d6a3502.jpg/alternates/BASE_SIXTEEN_NINE/4D6A3502.JPG",
      "score": 10,
      "category": "Overig",
      "location": "Noord-Holland",
      "reason": "Lokaal cultuurnieuws zonder maatschappelijke of controversiële lading.",
      "summary": "Een 24-jarige barman uit Baarn heeft zijn derde single 'Zo blauw als een tientje' uitgebracht en gepresenteerd in zijn stamcafé. Hij hoopt hiermee een volgende stap in zijn muziekcarrière te zetten."
    },
    {
      "id": "omroep-brabant-2747249731",
      "source": "Omroep Brabant",
      "title": "Upcycling bij de kringloop: van bankstel naar barbecueschort",
      "description": "De circulaire economie krijgt bij kringloopwinkel Verderest in Valkenswaard op vele manieren een gezicht. \"Spullen die anders in de verbrandingsoven belanden, halen we nu uit elkaar om te hergebruiken&rdquo;, vertelt eigenaar Marina Liebregts. Zo kan het dat er ineens een nieuw pareltje opduikt te midden van de oude leren bankstellen: een zelfgemaakt barbecueschort van leer.&nbsp; 'Upcycling' word",
      "url": "https://www.omroepbrabant.nl/nieuws/6012091/upcycling-bij-de-kringloop-van-bankstel-naar-barbecueschort",
      "pubDate": "2026-06-05T16:00:00+00:00",
      "image": "https://api.omroepbrabant.nl/img/f/1280/720/0.50/0.40/cmV2aXNpb25zLzQ5MTE0NTQtMS5qcGc_c2U9MjA0NS0wMS0wMVQxMCUzQTQwJTNBMDBaJnNpZz0zZ3hRc2VTNHpUcUNQWXFqcFNubHBzVSUyRnZqaFBBWCUyQjF6VG5BT2d3TjFsSSUzRCZzcD1yJnNwcj1odHRwcyZzcj1iJnN0PTIwMjUtMDEtMDFUMTAlM0E0MCUzQTAwWiZzdj0yMDI2LTAyLTA2",
      "score": 20,
      "category": "Overig",
      "location": "Noord-Brabant",
      "reason": "Lokaal human interest over duurzaamheid; interessant maar geen PowNed-kernthema's.",
      "summary": "Een kringloopwinkel in Valkenswaard zet in op upcycling door oude spullen te hergebruiken. Een voorbeeld hiervan is een zelfgemaakte barbecueschort van leer uit oude bankstellen."
    },
    {
      "id": "ad-890988457",
      "source": "AD",
      "title": "LIVE Oorlog Oekraïne | Poetin ziet nog geen reden om Zelensky persoonlijk te spreken",
      "description": "De Russische president Vladimir Poetin ziet vooralsnog geen reden om persoonlijk zijn Oekraïense ambtgenoot Volodymyr Zelensky te ontmoeten. Die publiceerde donderdag een open brief aan de Russische leider met dat verzoek en de vraag om een concrete afspraak te maken. Volg alle ontwikkelingen over de oorlog in Oekraïne in ons liveblog.",
      "url": "https://www.ad.nl/buitenland/live-oorlog-oekraine-poetin-ziet-nog-geen-reden-om-zelensky-persoonlijk-te-spreken~adfb97be/",
      "pubDate": "2026-06-05T15:58:00+00:00",
      "image": "https://images.ad.nl/Yjk3NzI4NTlkNDI3N2U5NmY4MTAvZGlvLzI3NDQxODkyOS9maXQtd2lkdGgvNDAw/epa13018128-russian-president-vladimir-putin-deliveries-his-speech-on-the-main-session-of-the-st-petersburg-international-economic-forum-spief-in-st-petersburg-russia-05-june-2026-the-29th-st-petersburg-international-economic-forum-runs-from-03-to-06-june-2026-epa-anatoly-maltsev",
      "duplicate_sources": [
        "PZC",
        "Gooi- en Eemlander"
      ],
      "score": 5,
      "category": "Overig",
      "location": "Internationaal",
      "reason": "Buitenlands nieuws zonder Nederlandse dimensie; geen PowNed-relevantie.",
      "summary": "Vladimir Poetin ziet geen reden om persoonlijk met Volodymyr Zelensky te spreken na een open brief van de Oekraïense president. Het liveblog volgt alle ontwikkelingen rond de oorlog in Oekraïne."
    },
    {
      "id": "ad-2840656562",
      "source": "AD",
      "title": "Dood Marlies in Colombia blijft door raadsels omgeven, lichaam nog steeds niet vrijgegeven",
      "description": "De dood van de Nederlandse Marlies in Colombia is nog steeds omgeven door raadsels. Een woordvoerder van de familie laat weten dat er nog geen duidelijke antwoorden zijn gekomen uit het Latijns-Amerikaanse land. De 41-jarige vrouw raakte vorige week maandag vermist toen zij een wandeling maakte. Zes dagen later werd haar lichaam teruggevonden in een meer.",
      "url": "https://www.ad.nl/buitenland/dood-marlies-in-colombia-blijft-door-raadsels-omgeven-lichaam-nog-steeds-niet-vrijgegeven~a817b4f1/",
      "pubDate": "2026-06-05T15:57:08+00:00",
      "image": "https://images.ad.nl/Y2U1NTVhZWRmYTJkNjljMzI1YWQvZGlvLzI3NDI4ODQxMS9maXQtd2lkdGgvNDAw/marlies",
      "duplicate_sources": [
        "BN De Stem",
        "De Stentor",
        "PZC"
      ],
      "score": 68,
      "category": "Misdaad",
      "location": "Internationaal",
      "reason": "Nederlandse betrokken bij mysterieuze dood buitenland; true crime met Nederlandse interesse.",
      "summary": "Een Nederlandse vrouw van 41 jaar oud is dood aangetroffen in Colombia nadat zij vermist was geraakt tijdens een wandeling. Het lichaam is nog niet vrijgegeven en veel raadsels blijven onopgelost."
    },
    {
      "id": "open-rotterdam-9900701723",
      "source": "OPEN Rotterdam",
      "title": "Schouten over vernielingen Mevlana-moskee: ‘De politie heeft niet goed gereageerd’",
      "description": "“De politie heeft niet goed gereageerd na de vernielingen bij de Mevlana-moskee vorige week”, zegt burgemeester Carola Schouten tijdens het debat dat aangevraagd was door DENK. “De politie erkent dat dit anders had gemoeten.” Zes personen richtten in de nacht van donderdag 28 mei op vrijdag 29 mei schade aan. Rond 00.40 uur gedroeg de [&#8230;] Het bericht Schouten over vernielingen Mevlana-moskee",
      "url": "https://openrotterdam.nl/schouten-over-vernielingen-mevlana-moskee-de-politie-heeft-niet-goed-gereageerd/",
      "pubDate": "2026-06-05T15:56:56+00:00",
      "image": "",
      "score": 78,
      "category": "Misdaad",
      "location": "Zuid-Holland",
      "reason": "Moskee-vernielingen, politieke respons (burgemeester, DENK), maatschappelijke relevantie.",
      "summary": "Burgemeester Schouten kritiseert de politierespons op vernielingen bij de Mevlana-moskee in Rotterdam vorige week. Zes personen veroorzaakten schade en de politie erkent dat zij beter had kunnen reageren."
    },
    {
      "id": "nu.nl-8386202183",
      "source": "NU.nl",
      "title": "Eurovisie Songfestival trok dit jaar 35 miljoen minder kijkers dan vorig jaar",
      "description": "Het Eurovisie Songfestival heeft dit jaar fors minder kijkers getrokken dan vorig jaar. Er keken vorige maand in totaal 131 miljoen mensen naar het liedjesfestijn. Dat heeft omroepenkoepel European Broadcasting Union (EBU) vrijdag bekendgemaakt. In 2025 ging het nog om 166 miljoen kijkers.",
      "url": "https://www.nu.nl/songfestival/6398372/eurovisie-songfestival-trok-dit-jaar-35-miljoen-minder-kijkers-dan-vorig-jaar.html",
      "pubDate": "2026-06-05T15:56:32+00:00",
      "image": "https://images.nu.nl/m/0r4xdlyafr9m_sqr256/535/0/3515/3515/eurovisie-songfestival-trok-dit-jaar-35-miljoen-minder-kijkers-dan-vorig-jaar.jpg",
      "score": 50,
      "category": "Overig",
      "location": "Landelijk",
      "reason": "Geen score beschikbaar.",
      "summary": "Het Eurovisie Songfestival heeft dit jaar fors minder kijkers getrokken dan vorig jaar. Er keken vorige maand in totaal 131 miljoen mensen naar het liedjesfestijn. Dat heeft omroepenkoepel European Br"
    },
    {
      "id": "telegraaf-6599294045",
      "source": "Telegraaf",
      "title": "Acteur Anthony Head (72), bekend van Ted Lasso en Buffy the vampire slayer, overleden",
      "description": "Acteur Anthony Head, vooral bekend van zijn rollen in de populaire series Buffy the vampire slayer en Ted Lasso, is overleden. De Britse acteur werd 72 jaar oud. Dat meldt de Britse krant Daily Mail op basis van een verklaring van zijn familie.",
      "url": "https://www.telegraaf.nl/entertainment/sterren/acteur-anthony-head-72-bekend-van-ted-lasso-en-buffy-the-vampire-slayer-overleden/155434200.html",
      "pubDate": "2026-06-05T15:56:30+00:00",
      "image": "https://prod-img.telegraaf.nl/public/entertainment/media/a8mmiq-gettyimages-684903052.jpg/alternates/BASE_SIXTEEN_NINE/GettyImages-684903052.jpg",
      "score": 50,
      "category": "Overig",
      "location": "Landelijk",
      "reason": "Geen score beschikbaar.",
      "summary": "Acteur Anthony Head, vooral bekend van zijn rollen in de populaire series Buffy the vampire slayer en Ted Lasso, is overleden. De Britse acteur werd 72 jaar oud. Dat meldt de Britse krant Daily Mail o"
    },
    {
      "id": "ad-310730700",
      "source": "AD",
      "title": "Persoonlijke aanvallen rondom corona-enquête vertroebelen het zicht op een haperend systeem",
      "description": "Özcan Akyol schrijft drie keer per week over wat hem bezighoudt.",
      "url": "https://www.ad.nl/binnenland/persoonlijke-aanvallen-rondom-corona-enquete-vertroebelen-het-zicht-op-een-haperend-systeem~a9cc9d805/",
      "pubDate": "2026-06-05T15:54:58+00:00",
      "image": "https://images.ad.nl/N2E4MDdlMGU5ZmMwZTc3ZjE3ZDMvZGlvLzIzNjA0MTk0OC9maXQtd2lkdGgvNDAw/pushfoto-eus-ozcan-akyol-eus-voor-zijn-column-in-de-stentor-foto-joost-hoving-push",
      "duplicate_sources": [
        "BN De Stem",
        "De Stentor",
        "PZC"
      ],
      "score": 50,
      "category": "Overig",
      "location": "Landelijk",
      "reason": "Geen score beschikbaar.",
      "summary": "Özcan Akyol schrijft drie keer per week over wat hem bezighoudt."
    },
    {
      "id": "ad-6545329906",
      "source": "AD",
      "title": "Real Madrid wil Olise losweken bij Bayern, Marinus Dijkhuizen heeft nieuwe club, Spurs maakt komst Robertson bekend",
      "description": "De transfermarkt is weliswaar gesloten, de geruchtenmolen draait op volle toeren. Wie gaan er komende zomer een stap maken? Hier blijf je op de hoogte van alle ontwikkelingen.",
      "url": "https://www.ad.nl/voetbal/real-madrid-wil-olise-losweken-bij-bayern-marinus-dijkhuizen-heeft-nieuwe-club-spurs-maakt-komst-robertson-bekend~a488141d/",
      "pubDate": "2026-06-05T15:54:00+00:00",
      "image": "https://images.ad.nl/NzhhNzAyZDJkZDJhOWEyYWEwMzkvZGlvLzI3MzI5MDgxNy9maXQtd2lkdGgvNDAw/ismael-saibari-memphis-depay-en-givairo-read",
      "score": 50,
      "category": "Overig",
      "location": "Landelijk",
      "reason": "Geen score beschikbaar.",
      "summary": "De transfermarkt is weliswaar gesloten, de geruchtenmolen draait op volle toeren. Wie gaan er komende zomer een stap maken? Hier blijf je op de hoogte van alle ontwikkelingen."
    },
    {
      "id": "ad-6088609901",
      "source": "AD",
      "title": "Nederlands elftal begint eerste training in Verenigde Staten met een moment van stilte",
      "description": "De spelers, technische staf en begeleiders van het Nederlands elftal hebben voor de eerste training in de Verenigde Staten voor het WK in Orangeburg een moment van stilte gehouden voor Hans Jorritsma.",
      "url": "https://www.ad.nl/wk-voetbal/nederlands-elftal-begint-eerste-training-in-verenigde-staten-met-een-moment-van-stilte~a21aca85/",
      "pubDate": "2026-06-05T15:52:00+00:00",
      "image": "https://images.ad.nl/NDRlZjFiZDAyNTRlN2JlYWYyMzkvZGlvLzI3NDQyMTE1Ni9maXQtd2lkdGgvNDAw/wk-voetbal-2026-voor-de-eerste-training-van-oranje-op-het-trainingscomplex-van-de-new-york-city-fc-werd-door-staf-en-spelers-hans-jorritsma-herdacht-foto-pim-ras",
      "duplicate_sources": [
        "BN De Stem",
        "PZC"
      ],
      "score": 50,
      "category": "Overig",
      "location": "Landelijk",
      "reason": "Geen score beschikbaar.",
      "summary": "De spelers, technische staf en begeleiders van het Nederlands elftal hebben voor de eerste training in de Verenigde Staten voor het WK in Orangeburg een moment van stilte gehouden voor Hans Jorritsma."
    },
    {
      "id": "dagblad010-6294176744",
      "source": "Dagblad010",
      "title": "Nachtelijke werkzaamheden Algerabrug in juni en juli 2026",
      "description": "Nachtelijke werkzaamheden Algerabrug in juni en juli 2026",
      "url": "https://dagblad010.nl/rotterdam%20%26%20regio/nachtelijke-werkzaamheden-algerabrug-in-juni-en-juli-2026",
      "pubDate": "2026-06-05T15:48:00+00:00",
      "image": "https://media.digitaaldagblad.nl/files/shares/goudsdagblad/algerabrug_lucht5ef7336852499.jpg",
      "score": 50,
      "category": "Overig",
      "location": "Landelijk",
      "reason": "Geen score beschikbaar.",
      "summary": "Nachtelijke werkzaamheden Algerabrug in juni en juli 2026"
    },
    {
      "id": "telegraaf-7601959712",
      "source": "Telegraaf",
      "title": "Jurriën Timber met Oranje het veld op voor eerste training op Amerikaanse bodem",
      "description": "Het Nederlands elftal is het veld opgegaan voor de eerste training op Amerikaanse bodem. Het Nederlands elftal ging met een complete groep het veld op op de Etihad City Football Academy. Dat is het complex van New York City, de club van voormalig AZ-trainer Pascal Jansen.",
      "url": "https://www.telegraaf.nl/sport/voetbal/jurrien-timber-met-oranje-het-veld-op-voor-eerste-training-op-amerikaanse-bodem/155426653.html",
      "pubDate": "2026-06-05T15:46:20+00:00",
      "image": "https://prod-img.telegraaf.nl/public/sport/o0893e-anp-560181769.jpg/alternates/BASE_SIXTEEN_NINE/ANP-560181769.jpg",
      "score": 50,
      "category": "Overig",
      "location": "Landelijk",
      "reason": "Geen score beschikbaar.",
      "summary": "Het Nederlands elftal is het veld opgegaan voor de eerste training op Amerikaanse bodem. Het Nederlands elftal ging met een complete groep het veld op op de Etihad City Football Academy. Dat is het co"
    },
    {
      "id": "gooi--en-eemlander-6593045694",
      "source": "Gooi- en Eemlander",
      "title": "Ook Von der Leyen staat open voor flexibel toetredingsproces EU",
      "description": "Voorzitter van de Europese Commissie Ursula von der Leyen staat open voor een „dynamischer” toetredingsproces voor landen die lid willen worden van de Europese Unie. Ze zei na de top van de EU en de Westelijke Balkan dat de wens is om hervormingen van toekomstige leden te belonen met „echte integratie” in de EU.",
      "url": "https://www.gooieneemlander.nl/buitenland/ook-von-der-leyen-staat-open-voor-flexibel-toetredingsproces-eu/155433379.html",
      "pubDate": "2026-06-05T15:42:28+00:00",
      "image": "https://prod-img.gooieneemlander.nl/public/buitenland/clelv1-6ba933a9-18c7-4563-b309-496d310064c5-tmg-webfeed-bui-anp050626171-1.jpeg/alternates/BASE_SIXTEEN_NINE/6ba933a9-18c7-4563-b309-496d310064c5_tmg-webfeed-bui_ANP050626171-1.jpeg",
      "score": 50,
      "category": "Overig",
      "location": "Landelijk",
      "reason": "Geen score beschikbaar.",
      "summary": "Voorzitter van de Europese Commissie Ursula von der Leyen staat open voor een „dynamischer” toetredingsproces voor landen die lid willen worden van de Europese Unie. Ze zei na de top van de EU en de W"
    },
    {
      "id": "telegraaf-4682510262",
      "source": "Telegraaf",
      "title": "Titelfavoriet Alexander Zverev als eerste naar finale van Roland Garros",
      "description": "Alexander Zverev heeft zich als eerste geplaatst voor de finale van Roland Garros. De 29-jarige Duitser, die nog nooit een grandslamtoernooi won, klopte de Tsjech Jakub Mensik uiteindelijk vrij eenvoudig in vier sets: 7-5, 6-2, 3-6, 6-3.",
      "url": "https://www.telegraaf.nl/sport/tennis/titelfavoriet-alexander-zverev-als-eerste-naar-finale-van-roland-garros/155358763.html",
      "pubDate": "2026-06-05T15:41:19+00:00",
      "image": "https://prod-img.telegraaf.nl/public/sport/7yehrl-anp-560164066.jpg/alternates/BASE_SIXTEEN_NINE/ANP-560164066.jpg",
      "score": 5,
      "category": "Overig",
      "location": "Internationaal",
      "reason": "Internationale sport zonder Nederlandse link, niet relevant voor PowNed.",
      "summary": "Alexander Zverev bereikt de finale van Roland Garros door Jakub Mensik in vier sets te verslaan. De Duitse tennisser jaagt nog altijd op zijn eerste grandslamtitel."
    },
    {
      "id": "bn-de-stem-5219446720",
      "source": "BN De Stem",
      "title": "De WK-route van Oranje richting finale: na groepsfase wacht waarschijnlijk meteen een zware kluif",
      "description": "Het Nederlands elftal neemt het in de poulefase van het WK op tegen Zweden, Japan en Tunesië. De ploeg van bondscoach Ronald Koeman zal streven naar groepswinst, en anders sowieso de knock-outfase willen bereiken. Maar hoe ziet de route van het Nederlands elftal eruit?",
      "url": "https://www.bndestem.nl/wk-voetbal/de-wk-route-van-oranje-richting-finale-na-groepsfase-wacht-waarschijnlijk-meteen-een-zware-kluif~adf3ca91/",
      "pubDate": "2026-06-05T15:41:04+00:00",
      "image": "https://images.bndestem.nl/M2M1Zjk1ZDNhNTA0OWMwNmRhNjEvZGlvLzI3NDM1OTE3NS9maXQtd2lkdGgvNDAw/nederland-algerije-uitzwaaiwedstrijd-voor-wkl-2026-usa-donyell-malen-schiet-voorlangs-foto-pim-ras",
      "duplicate_sources": [
        "PZC"
      ],
      "score": 8,
      "category": "Overig",
      "location": "Internationaal",
      "reason": "Voetbal zonder actueel nieuwswaarde of Nederlands politiek/maatschappelijk belang.",
      "summary": "Het Nederlands voetbalelftal speelt in de WK-groepsfase tegen Zweden, Japan en Tunesië. De ploeg van bondscoach Ronald Koeman streeft naar groepswinst."
    },
    {
      "id": "ad-5409008273",
      "source": "AD",
      "title": "Alexander Zverev bereikt finale ten koste van jonge Tsjech (20) en blijft dromen van eerste grandslamtitel",
      "description": "Alexander Zverev is nog altijd in de race voor zijn eerste grandslamtitel. De 29-jarige Duitser bereikte vrijdag ten koste van de jonge Tsjech Jakub Mensik (20) de finale van Roland Garros. Zverev, de nummer 3 van de wereld, won op het gravel in Parijs in vier sets: 7-5, 6-2, 3-6, 6-3.",
      "url": "https://www.ad.nl/tennis/alexander-zverev-bereikt-finale-ten-koste-van-jonge-tsjech-20-en-blijft-dromen-van-eerste-grandslamtitel~a5be627b/",
      "pubDate": "2026-06-05T15:41:00+00:00",
      "image": "https://images.ad.nl/ODM2MTZiMzljMWRlNzM5YzI1ZWIvZGlvLzI3NDQxOTIyNi9maXQtd2lkdGgvNDAw/germany-s-alexander-zverev-reacts-after-a-point-as-he-plays-against-czech-republic-s-jakub-mensik-during-their-men-s-semi-final-singles-match-on-day-13-of-the-french-open-tennis-tournament-on-court-philippe-chatrier-at-the-roland-garros-complex-in-paris-on-june-5-2026-photo-by-alain-jocard-afp",
      "duplicate_sources": [
        "De Stentor",
        "PZC"
      ],
      "score": 5,
      "category": "Overig",
      "location": "Internationaal",
      "reason": "Internationale tennissport zonder relevantie voor PowNed-lezers.",
      "summary": "Alexander Zverev bereikte de Roland Garros-finale na overwinning op Jakub Mensik. De Duitse nummer 3 van de wereld wint in vier sets."
    },
    {
      "id": "gooi--en-eemlander-6950434178",
      "source": "Gooi- en Eemlander",
      "title": "NPO ziet geen mogelijkheden om omroepen en ON! samen te brengen",
      "description": "De NPO ziet op dit moment geen mogelijkheden om de ledenomroepen en aspirant-omroep Ongehoord Nederland (ON!) nader tot elkaar te brengen. Dat schrijft de NPO vrijdag in een reactie op het advies dat een onafhankelijke commissie een maand geleden uitbracht over de werkwijze van de NPO. Daarin staat dat bij ON! „substantiële tekortkomingen” zijn vastgesteld „in de naleving van journalistieke normen",
      "url": "https://www.gooieneemlander.nl/regio/gooi-en-eemland/npo-ziet-geen-mogelijkheden-om-omroepen-en-on-samen-te-brengen/155429022.html",
      "pubDate": "2026-06-05T15:39:59+00:00",
      "image": "https://prod-img.gooieneemlander.nl/public/incoming/qdxq0o-anp-550590288.jpg/alternates/BASE_SIXTEEN_NINE/ANP-550590288.jpg",
      "score": 72,
      "category": "Media",
      "location": "Landelijk",
      "reason": "NPO en Ongehoord Nederland-conflict past bij PowNed's media- en cancelcultureberichtgeving.",
      "summary": "De NPO ziet geen mogelijkheden om ledenomroepen en Ongehoord Nederland dichter tot elkaar te brengen. Een onafhankelijke commissie constateerde substantiële tekortkomingen in ON!'s journalistieke normen."
    },
    {
      "id": "trouw-4689761651",
      "source": "Trouw",
      "title": "Wie maakte het coronabeleid: de regering of het OMT?",
      "description": "",
      "url": "https://archive.ph/newest/https://www.trouw.nl/politiek/wie-maakte-het-coronabeleid-de-regering-of-het-omt~b6c2493e/",
      "pubDate": "2026-06-05T15:36:00+00:00",
      "image": "https://image.trouw.nl/274411877/feature-crop/320/320/afbeelding",
      "score": 78,
      "category": "Politiek",
      "location": "Landelijk",
      "reason": "Coronabeleid-verantwoordelijkheidsvraag past bij PowNed's kritische Den Haag-berichtgeving.",
      "summary": "Artikel onderzoekt wie verantwoordelijk was voor het Nederlandse coronabeleid: regering of OMT. Vraag naar afwegingen en besluitvorming staat centraal."
    },
    {
      "id": "de-stentor-7141416897",
      "source": "De Stentor",
      "title": "Drama in Duitsland: hart van vrouw (47) stond mogelijk stil toen zij twee 12-jarigen doodreed",
      "description": "Zestien seconden. Zo lang stond het hart van een 47-jarige vrouw stil op de ochtend dat zij twee kinderen doodreed. De Duitse autoriteiten delen nu meer informatie over het dramatische ongeval in Dinslaken.",
      "url": "https://www.destentor.nl/buitenland/drama-in-duitsland-hart-van-vrouw-47-stond-mogelijk-stil-toen-zij-twee-12-jarigen-doodreed~a5e5518f/",
      "pubDate": "2026-06-05T15:36:00+00:00",
      "image": "https://images.destentor.nl/MTA4MmFlZDNiOTMxNWQ4MDZkNTYvZGlvLzI3NDE0NDAxNi9maXQtd2lkdGgvNDAw/kaarsen-op-de-plek-waar-de-12-jarigen-werden-aangereden-in-dinslaken",
      "score": 15,
      "category": "Overig",
      "location": "Internationaal",
      "reason": "Dramatisch Duits verkeersincident zonder Nederlandse link of bijzondere relevantie.",
      "summary": "Een 47-jarige vrouw reed in Dinslaken twee 12-jarige kinderen dood. Haar hart stond mogelijk 16 seconden stil op het moment van het ongeval."
    },
    {
      "id": "nos-4042978982",
      "source": "NOS",
      "title": "Surfer overleden op strand van Ouddorp, bewusteloos in water gevonden",
      "description": "Op het strand bij Ouddorp (Zuid-Holland) is een surfer overleden. Het slachtoffer werd bewusteloos in het water gevonden bij de Brouwersdam, de verbinding tussen Zeeland en Zuid-Holland. De eerste melding kwam rond 12.30 uur binnen. Er werd een traumahelikopter opgeroepen. Het slachtoffer is gereanimeerd, maar hulp mocht niet meer baten. Wat er met de surfer is gebeurd, is nog onduidelijk. De poli",
      "url": "https://nos.nl/artikel/2617279-surfer-overleden-op-strand-van-ouddorp-bewusteloos-in-water-gevonden",
      "pubDate": "2026-06-05T15:35:49+00:00",
      "image": "https://images.cdn.nos.nl/8/H/f/f/h/U/Sps9thQEVmZcSJyFRpBa2XZHu58GTmCsZ7Sk4jL/0x86x1104x621-1024x576.webp",
      "score": 45,
      "category": "Misdaad",
      "location": "Zuid-Holland",
      "reason": "Lokaal drama in Zuid-Holland met onheldere omstandigheden; mogelijke nieuwswaarde voor regionaal bereik.",
      "summary": "Een surfer is overleden nadat hij bewusteloos in het water bij Ouddorp werd gevonden. De oorzaak van het voorval is nog onduidelijk."
    },
    {
      "id": "telegraaf-5789779116",
      "source": "Telegraaf",
      "title": "LIVE | Techbedrijven bezorgen AEX verlies",
      "description": "De AEX is vrijdag lager gesloten, vooral door de stevige neergang van Adyen na een analistenrapport van een Amerikaanse zakenbank. Ook de chipbedrijven drukten op de index. Tegenwicht kwam er vooral van Unilever.",
      "url": "https://www.telegraaf.nl/financieel/live-techbedrijven-bezorgen-aex-verlies/155325830.html",
      "pubDate": "2026-06-05T15:35:11+00:00",
      "image": "https://prod-img.telegraaf.nl/public/incoming/ba7tqq-vgt-dft-beursblog-online-01.jpg/alternates/BASE_SIXTEEN_NINE/vgt%20DFT%20beursblog%20ONLINE%2001.jpg",
      "score": 2,
      "category": "Overig",
      "location": "Landelijk",
      "reason": "Financiële markten/beurs-berichtgeving buiten PowNed-focus.",
      "summary": "De AEX sloot vrijdag lager door verliezen bij Adyen en chipbedrijven. Unilever zorgde voor tegenwicht in de index."
    },
    {
      "id": "telegraaf-9529861815",
      "source": "Telegraaf",
      "title": "Mathieu van der Poel rijdt Ronde van Zwitserland in aanloop naar Tour de France",
      "description": "Mathieu van der Poel bereidt zich in de Ronde van Zwitserland voor op de Tour de France. De 31-jarige Nederlander maakt in de vijfdaagse rittenkoers, van 17 tot en met 21 juni, zijn rentree in het wielerpeloton na een afwezigheid van ruim twee maanden. Van der Poel reed op 12 april met Parijs-Roubaix zijn laatste wedstrijd.",
      "url": "https://www.telegraaf.nl/sport/wielrennen/mathieu-van-der-poel-rijdt-ronde-van-zwitserland-in-aanloop-naar-tour-de-france/155429069.html",
      "pubDate": "2026-06-05T15:33:00+00:00",
      "image": "https://prod-img.telegraaf.nl/public/incoming/xatigq-file85t1koeedeb11z1a85c/alternates/BASE_SIXTEEN_NINE/file85t1koeedeb11z1a85c",
      "score": 5,
      "category": "Overig",
      "location": "Internationaal",
      "reason": "Routine sportnieuws zonder Nederlandse politieke of maatschappelijke relevantie.",
      "summary": "Mathieu van der Poel rijdt de Ronde van Zwitserland van 17-21 juni als voorbereiding op de Tour de France. Het is zijn eerste wedstrijd na een afwezigheid van ruim twee maanden."
    },
    {
      "id": "telegraaf-3685098655",
      "source": "Telegraaf",
      "title": "Emotionele Anna Dobber vertelt alles: ’Toen wist ik dat het uit zou lekken’",
      "description": "Influencer Anna Dobber ligt deze week onder een vergrootglas. Nadat eerder haar verhaal over de veelbesproken influencertrip naar buiten kwam, vertelt ze nu ook openhartig over een ernstig delict uit haar verleden. In een gesprek met verslaggever Max van den Broek doet ze haar verhaal.",
      "url": "https://www.telegraaf.nl/video/emotionele-anna-dobber-vertelt-alles-toen-wist-ik-dat-het-uit-zou-lekken/155429883.html",
      "pubDate": "2026-06-05T15:32:35+00:00",
      "image": "https://prod-img.telegraaf.nl/public/incoming/nyy6w2-anna-still.jpg/alternates/BASE_SIXTEEN_NINE/ANNA_STILL.jpg",
      "score": 72,
      "category": "Opmerkelijk",
      "location": "Landelijk",
      "reason": "BN'er-schandaal en influencer-controverse past in PowNed-profiel; potentieel woke/cancel-culture-angle.",
      "summary": "Influencer Anna Dobber geeft openhartig interview over een veelbesproken trip en ernstig delict uit haar verleden. Het verhaal doet actueel de ronde op sociale media."
    },
    {
      "id": "telegraaf-5903414454",
      "source": "Telegraaf",
      "title": "Duitsland negeert Brussel en gaat door met grenscontroles: spanning en irritatie in Nederlandse dorpen lopen op",
      "description": "De irritatie in de grensregio’s neemt verder toe. Duitsland is niet van plan om de grenscontroles af te schaffen, ondanks een oproep van Brussel deze week. Dit betekent dat de overlast voortduurt. Van dodelijke ongelukken tot vrachtverkeer dat door dorpen en over binnenwegen raast. Montferland roept op de website reizigers op om om te rijden via Babberich, waardoor het dáár weer drukker wordt.",
      "url": "https://www.telegraaf.nl/binnenland/duitsland-negeert-brussel-en-gaat-door-met-grenscontroles-spanning-en-irritatie-in-nederlandse-dorpen-lopen-op/155332134.html",
      "pubDate": "2026-06-05T15:32:00+00:00",
      "image": "https://prod-img.telegraaf.nl/public/incoming/x7t62y-online-grenscontroles.jpg/alternates/BASE_SIXTEEN_NINE/ONLINE%20-%20Grenscontroles.jpg",
      "score": 78,
      "category": "Politiek",
      "location": "Gelderland",
      "reason": "Grensconflict met Brussel en Duitsland; lokale overlast in Nederlandse grensregio's; politiek-bestuurlijk.",
      "summary": "Duitsland handhaaft grenscontroles ondanks kritiek van Brussel, wat leidt tot overlast in Nederlandse grensplaatsen. Montferland vraagt reizigers om uit te wijken."
    },
    {
      "id": "pzc-7558330044",
      "source": "PZC",
      "title": "Waterschap spreekt zich uit tegen ontpoldering: ‘Vandaag is er geen draagvlak, morgen kan dat anders zijn’",
      "description": "Dat het algemeen bestuur van waterschap Scheldestromen niet enthousiast is over kustversterking door middel van het tijdelijk onder water zetten van polders, was al wel duidelijk. Toch vond een ruime meerderheid het donderdag nodig zich opnieuw uit te spreken tegen de zogeheten wisselpolder. De aanleiding? Zeeland 2050.",
      "url": "https://www.pzc.nl/middelburg/waterschap-spreekt-zich-uit-tegen-ontpoldering-vandaag-is-er-geen-draagvlak-morgen-kan-dat-anders-zijn~aaf2c1ba/",
      "pubDate": "2026-06-05T15:31:32+00:00",
      "image": "https://images.pzc.nl/NzYwMTg1YjI1YzAwMWI4MDU1MDMvZGlvLzI1ODk2OTU0NS9maXQtd2lkdGgvNDAw/serie-afgekocht-pzc-nlbeeld-pz20250616-1101-16-6-2025-wisselpolder-hoedekenskerke-foto-dirk-jan-gjeltema",
      "score": 48,
      "category": "Overig",
      "location": "Zeeland",
      "reason": "Lokaal waterschap-bestuurlijk; interessant voor regio, maar beperkt bredere Nederlandse relevantie.",
      "summary": "Waterschap Scheldestromen spreekt zich opnieuw tegen ontpoldering uit als kustversterking. De discussie maakt deel uit van Zeeland 2050."
    },
    {
      "id": "ad-den-haag-8502717162",
      "source": "AD Den Haag",
      "title": "De Pier krijgt een make-over: dit gaat er de komende jaren veranderen",
      "description": "Wie regelmatig over De Pier in Scheveningen wandelt, heeft het misschien al gezien: de gekleurde palen zijn verdwenen en hebben plaatsgemaakt voor wit. Dat is geen spontane verfbeurt, maar een voorproefje van grote verbouwplannen.",
      "url": "https://www.ad.nl/den-haag/de-pier-krijgt-een-make-over-dit-gaat-er-de-komende-jaren-veranderen~accf6add/",
      "pubDate": "2026-06-05T15:31:06+00:00",
      "image": "https://images.ad.nl/NmU3NzdkYTFkMWQzMjMzZGQ3ZTcvZGlvLzI2NTMyNDYxMC9maXQtd2lkdGgvNDAw/de-pier-op-scheveningen-kan-wel-een-opknapbeurt-gebruiken-foto-indebuurt",
      "score": 22,
      "category": "Overig",
      "location": "Zuid-Holland",
      "reason": "Routinenieuws over lokale infrastructuurverbouwing zonder satirische of controversiële hoek.",
      "summary": "De Pier in Scheveningen ondergaat een make-over; gekleurde palen zijn vervangen door wit. Grootschalige verbouwplannen staan gepland voor komende jaren."
    },
    {
      "id": "telegraaf-2955512433",
      "source": "Telegraaf",
      "title": "’Dat ik nog maagd ben, vinden mannen heel interessant’",
      "description": "In de rubriek ’Tussen de lakens’ vertellen vrouwen over hun seksleven. Dit verhaal komt van Anita (42). Ze is al haar hele leven vrijgezel en nog maagd. ’Dit is iets waar ik het met niemand over heb. Toen ik het ergens begin 20 nog wel eens deelde, merkte ik dat mannen juist dat aspect aan mij interessant vonden. Daar kreeg ik een heel naar gevoel over.’",
      "url": "https://www.telegraaf.nl/vrouw/seks-en-relaties/dat-ik-nog-maagd-ben-vinden-mannen-heel-interessant/155234263.html",
      "pubDate": "2026-06-05T15:30:00+00:00",
      "image": "https://prod-img.telegraaf.nl/public/incoming/f2ldi3-gettyimages-548591415.jpg/alternates/BASE_SIXTEEN_NINE/GettyImages-548591415.jpg",
      "score": 15,
      "category": "Overig",
      "location": "Landelijk",
      "reason": "Persoonlijk lifestyle-verhaal zonder politieke of maatschappelijke impact; niet relevant voor PowNed.",
      "summary": "Een 42-jarige vrouw vertelt in rubriek 'Tussen de lakens' over haar maagdelijkheid en ervaringen met mannen. Het is een persoonlijk intiem verhaal."
    },
    {
      "id": "gooi--en-eemlander-3434179327",
      "source": "Gooi- en Eemlander",
      "title": "Staalslak gebruiken kan straks alleen nog met vergunning. Staatssecretaris Annet Bertram werkt aan ’Nee/tenzij-verbod’",
      "description": "Staatssecretaris Annet Bertram van I en W werkt aan nieuwe regels voor staalslakken. Die komen neer op een ’Nee/tenzij-verbod’. Alleen als kan worden aangetoond dat het veilig kan voor mens en milieu, krijgen toepassers een vergunning om staalslak te gebruiken. Dat gaat ook gelden voor toepassing in water.",
      "url": "https://www.gooieneemlander.nl/uitgelicht/staalslak-gebruiken-kan-straks-alleen-nog-met-vergunning.-staatssecretaris-annet-bertram-werkt-aan-neetenzij-verbod/155434724.html",
      "pubDate": "2026-06-05T15:30:00+00:00",
      "image": "https://prod-img.noordhollandsdagblad.nl/public/incoming/2plez9-img-20250213-105533143-edited.jpg/alternates/BASE_SIXTEEN_NINE/IMG_20250213_105533143_edited.jpg",
      "score": 64,
      "category": "Politiek",
      "location": "Noord-Holland",
      "reason": "Staatssecretaris-beleid (Bertram) over milieuregulering; regelgeving met praktische impact.",
      "summary": "Staatssecretaris Annet Bertram werkt aan 'Nee/tenzij-verbod' voor staalslakken, wat alleen onder vergunning gebruikt mag worden. Nieuwe regels richten zich op veiligheid voor mens en milieu."
    },
    {
      "id": "ad-den-haag-1670890179",
      "source": "AD Den Haag",
      "title": "Inbrekers in Den Haag vaker succesvol dan vijf jaar geleden",
      "description": "Inbrekers in Den Haag hebben vorig jaar in verhouding vaker succes gehad dan vijf jaar geleden. Of ze die statistiek zelf ook hebben opgemerkt is de vraag: het aantal inbraakmeldingen ligt dit jaar tot nu toe net zo hoog als in 2025.",
      "url": "https://www.ad.nl/den-haag/inbrekers-in-den-haag-vaker-succesvol-dan-vijf-jaar-geleden~ae2b1417/",
      "pubDate": "2026-06-05T15:30:00+00:00",
      "image": "https://images.ad.nl/YjdkMTVhZDJmZmIzZmM4OTQyOGYvZGlvLzI0ODg2NDI5MC9maXQtd2lkdGgvNDAw/inbreker",
      "score": 58,
      "category": "Misdaad",
      "location": "Zuid-Holland",
      "reason": "Lokale criminaliteitsstatistiek interessant; inbraakontwikkeling in Den Haag relevant voor veiligheid.",
      "summary": "Inbrekers in Den Haag hebben vorig jaar in verhouding vaker succes gehad dan vijf jaar geleden. Het aantal inbraakmeldingen ligt dit jaar tot nu toe gelijk aan 2025."
    },
    {
      "id": "ad-rotterdam-3680479893",
      "source": "AD Rotterdam",
      "title": "Inbrekers in Rotterdam vaker succesvol dan vijf jaar geleden, en dit jaar minder actief",
      "description": "Inbrekers in Rotterdam hebben vorig jaar in verhouding vaker succes gehad dan vijf jaar geleden. Of ze die statistiek zelf ook hebben opgemerkt is de vraag: het aantal inbraakmeldingen ligt dit jaar tot nu toe lager dan in 2025.",
      "url": "https://www.ad.nl/rotterdam/inbrekers-in-rotterdam-vaker-succesvol-dan-vijf-jaar-geleden-en-dit-jaar-minder-actief~ab657f48/",
      "pubDate": "2026-06-05T15:30:00+00:00",
      "image": "https://images.ad.nl/YjdkMTVhZDJmZmIzZmM4OTQyOGYvZGlvLzI0ODg2NDI5MC9maXQtd2lkdGgvNDAw/inbreker",
      "score": 62,
      "category": "Misdaad",
      "location": "Zuid-Holland",
      "reason": "Lokaal misdaadnieuws met statistisch hoek, maar vooral routinerapportage zonder schandaal.",
      "summary": "Inbrekers in Rotterdam hebben vorig jaar vaker succes gehad dan vijf jaar terug. Dit jaar daalt het aantal inbraakmeldingen echter tot nu toe."
    },
    {
      "id": "gooi--en-eemlander-5822223508",
      "source": "Gooi- en Eemlander",
      "title": "Ierland legt twee Israëlische ministers inreisverbod op",
      "description": "Ierland heeft een inreisverbod afgekondigd voor de Israëlische ministers Itamar Ben-Gvir (Nationale Veiligheid) en Bezalel Smotrich (Financiën). Beiden staan te boek als extreem in hun opvattingen. Premier Micheál Martin zei eerder al met maatregelen te komen tegen Israëlische functionarissen die volgens Ierland het conflict in Gaza aanwakkeren.",
      "url": "https://www.gooieneemlander.nl/buitenland/ierland-legt-twee-israelische-ministers-inreisverbod-op/155430885.html",
      "pubDate": "2026-06-05T15:29:26+00:00",
      "image": "https://prod-img.gooieneemlander.nl/public/buitenland/zcr4fu-8640af3d-1956-4bf1-ae19-d09ff3a58fd1-tmg-webfeed-bui-anp050626168-1.jpeg/alternates/BASE_SIXTEEN_NINE/8640af3d-1956-4bf1-ae19-d09ff3a58fd1_tmg-webfeed-bui_ANP050626168-1.jpeg",
      "score": 15,
      "category": "Overig",
      "location": "Internationaal",
      "reason": "Buitenlands nieuws zonder Nederlandse link of relevantie voor Nederlands publiek.",
      "summary": "Ierland heeft een inreisverbod afgekondigd voor de Israëlische ministers Itamar Ben-Gvir (Nationale Veiligheid) en Bezalel Smotrich (Financiën). Beiden staan te boek als extreem in hun opvattingen. Pr"
    },
    {
      "id": "gooi--en-eemlander-5921033773",
      "source": "Gooi- en Eemlander",
      "title": "Volgende week coronaverhoren met Rutte, Schoof en Koolmees",
      "description": "Tijdens de verhoren van volgende week moeten Mark Rutte, Dick Schoof en Wouter Koolmees voor de parlementaire enquêtecommissie corona verschijnen. Het is de tweede volle verhoorweek en deze staat in het teken van de organisatie van de corona-aanpak.",
      "url": "https://www.gooieneemlander.nl/binnenland/volgende-week-coronaverhoren-met-rutte-schoof-en-koolmees/155429706.html",
      "pubDate": "2026-06-05T15:29:14+00:00",
      "image": "https://prod-img.noordhollandsdagblad.nl/public/binnenland/rb3572-8e9426e3-2bf1-4636-b072-16a28b425b23-tmg-webfeed-bin-anp050626167-1.jpeg/alternates/BASE_SIXTEEN_NINE/8e9426e3-2bf1-4636-b072-16a28b425b23_tmg-webfeed-bin_ANP050626167-1.jpeg",
      "score": 88,
      "category": "Politiek",
      "location": "Landelijk",
      "reason": "Coronaverhoren met top-politici zijn direct Den Haag-relevant; PowNed volgt enquêtes intensief.",
      "summary": "Tijdens de verhoren van volgende week moeten Mark Rutte, Dick Schoof en Wouter Koolmees voor de parlementaire enquêtecommissie corona verschijnen. Het is de tweede volle verhoorweek en deze staat in h"
    },
    {
      "id": "bn-de-stem-5100798003",
      "source": "BN De Stem",
      "title": "Dit Nederlands elftal komt op het WK niet verder dan de poulefase",
      "description": "Hoe denk jij over het nieuws van de dag? Elke dag legt BN DeStem een prikkelende stelling voor, waarop jij kan reageren. Ben je het eens, of juist niet?",
      "url": "https://www.bndestem.nl/opinie/dit-nederlands-elftal-komt-op-het-wk-niet-verder-dan-de-poulefase~aa2d0d2f3/",
      "pubDate": "2026-06-05T15:27:22+00:00",
      "image": "https://images.bndestem.nl/NmU2ZWNmZDhkMGQ0ZDliOTFjNDEvZGlvLzI2NDcwMTIwNC9maXQtd2lkdGgvNDAw/stelling-een-sen-oneens-bndestem",
      "score": 5,
      "category": "Overig",
      "location": "Landelijk",
      "reason": "Sport-stellingname zonder nieuws; volledig buiten PowNed-focus.",
      "summary": "Hoe denk jij over het nieuws van de dag? Elke dag legt BN DeStem een prikkelende stelling voor, waarop jij kan reageren. Ben je het eens, of juist niet?"
    },
    {
      "id": "nos-8940391363",
      "source": "NOS",
      "title": "Kabinet werkt aan plan om duizenden statushouders te helpen aan werk",
      "description": "Het kabinet wil in de komende vier jaar 75.000 statushouders aan het werk helpen. Dat schrijft minister Aartsen van Werk en Participatie in een brief aan de Tweede Kamer, waarin hij de hoofdlijnen van de plannen schetst. Hij wil na de zomer de plannen verder uitwerken. Het kabinet vindt dat er te veel nieuwkomers in Nederland verblijven die niet werken. Het kabinet vindt dat niet uit te leggen in ",
      "url": "https://nos.nl/artikel/2617277-kabinet-werkt-aan-plan-om-duizenden-statushouders-te-helpen-aan-werk",
      "pubDate": "2026-06-05T15:25:45+00:00",
      "image": "https://images.cdn.nos.nl/5/7/C/n/r/3/LVNTNDapEQNM7NbfHLKkR4cvQkMNLB12SsTv3SD/0x127x4000x2250-1024x576.webp",
      "score": 73,
      "category": "Politiek",
      "location": "Landelijk",
      "reason": "Kabinetsbesluit over statushouders en werkgelegenheid; rechtstreeks beleid onder huidige regering.",
      "summary": "Het kabinet wil in de komende vier jaar 75.000 statushouders aan het werk helpen. Dat schrijft minister Aartsen van Werk en Participatie in een brief aan de Tweede Kamer, waarin hij de hoofdlijnen van"
    },
    {
      "id": "telegraaf-4089160756",
      "source": "Telegraaf",
      "title": "Betalingenverwerker Adyen stort in na analistenrapport: ’Koersval overdreven’",
      "description": "Het koers van de Amsterdamse betalingenverwerker Adyen glipte vrijdag hard onderuit op het Damrak, nadat een Amerikaans onderzoeksbureau in een vernietigend rapport zijn zorgen meldde over zijn marktaandeel, marges en groeikansen.",
      "url": "https://www.telegraaf.nl/financieel/betalingenverwerker-adyen-stort-in-na-analistenrapport-koersval-overdreven/155394423.html",
      "pubDate": "2026-06-05T15:25:00+00:00",
      "image": "https://prod-img.telegraaf.nl/public/incoming/yligbf-anp-537510299.jpg/alternates/BASE_SIXTEEN_NINE/ANP-537510299.jpg",
      "score": 22,
      "category": "Overig",
      "location": "Landelijk",
      "reason": "Bedrijfsnieuws zonder politieke, maatschappelijke of controversiële dimensie.",
      "summary": "Het koers van de Amsterdamse betalingenverwerker Adyen glipte vrijdag hard onderuit op het Damrak, nadat een Amerikaans onderzoeksbureau in een vernietigend rapport zijn zorgen meldde over zijn markta"
    },
    {
      "id": "ad-3332283902",
      "source": "AD",
      "title": "Coronaverhoren gaan nieuwe week in: Rutte, Schoof en Koolmees moeten verschijnen voor enquêtecommissie",
      "description": "Tijdens de verhoren van volgende week moeten Mark Rutte, Dick Schoof en Wouter Koolmees voor de parlementaire enquêtecommissie corona verschijnen. Het is de tweede volle verhoorweek en deze staat in het teken van de organisatie van de corona-aanpak.",
      "url": "https://www.ad.nl/binnenland/coronaverhoren-gaan-nieuwe-week-in-rutte-schoof-en-koolmees-moeten-verschijnen-voor-enquetecommissie~a55625ed/",
      "pubDate": "2026-06-05T15:23:00+00:00",
      "image": "https://images.ad.nl/MzViYjFjMTU4NGViMTQxNTYyODgvZGlvLzI3NDQxOTgyNi9maXQtd2lkdGgvNDAw/den-haag-portret-wouter-koolmees-foto-guus-schoonewille-handout-photo-dated-on-june-3-2026-shows-ukrainian-president-volodymyr-zelensky-meets-nato-secretary-general-mark-rutte-during-a-visit-in-kyiv-kyiv-ukraine-june-3-2026-photo-by-press-service-of-the-president-of-ukraine-via-abacapress-com-netherlands-outgoing-prime-minister-dick-schoof-arrives-at-the-general-plenary-of-leaders-in-the-framework-of-the-cop30-un-climate-change-conference-in-belem-para-state-brazil-on-november-6-2025-photo-by-pablo-porciuncula-afp",
      "duplicate_sources": [
        "BN De Stem",
        "De Stentor",
        "PZC"
      ],
      "score": 88,
      "category": "Politiek",
      "location": "Landelijk",
      "reason": "Coronaverhoren met Rutte, Schoof, Koolmees; major politiek-onderzoeksnieuws voor PowNed.",
      "summary": "Tijdens de verhoren van volgende week moeten Mark Rutte, Dick Schoof en Wouter Koolmees voor de parlementaire enquêtecommissie corona verschijnen. Het is de tweede volle verhoorweek en deze staat in h"
    },
    {
      "id": "bn-de-stem-7576766042",
      "source": "BN De Stem",
      "title": "Getroffen lunchroom krijgt steun van gemeente: ‘We zijn niet gek, hier is gewoon maatwerk nodig’",
      "description": "De gemeente Oosterhout onderzoekt of ondernemers die direct worden geraakt door de verbouwing van Arendshof II tot gemeentehuis eerder financiële ondersteuning kunnen krijgen. Wethouder Dees Melsen deed die toezegging nadat horecazaak Mad Hat een noodkreet sloeg over de overlast door sloopwerk.",
      "url": "https://www.bndestem.nl/oosterhout/getroffen-lunchroom-krijgt-steun-van-gemeente-we-zijn-niet-gek-hier-is-gewoon-maatwerk-nodig~a72704cf/",
      "pubDate": "2026-06-05T15:21:00+00:00",
      "image": "https://images.bndestem.nl/MTMwMDgzOTUzYjdlMmQwZDM0NmYvZGlvLzI3NDM3NjYwNy9maXQtd2lkdGgvNDAw/sloop-arendshof-ii-inzet-serie-afgekocht-bnds-nlbeeld-oosterhout-28-05-026-ondernemers-audrey-kroon-met-dochter-ilvy-en-johan-veld-van-koffiehuis-mad-hat-aan-de-nieuwstraat-in-oosterhout-de-werkzaamheden-naast-hun-terras-duren-langer-dan-verwacht-en-zorgen-voor-omzetverlies-foto-pix4profs-joyce-van-belkom",
      "score": 35,
      "category": "Overig",
      "location": "Noord-Brabant",
      "reason": "Lokaal ondernemersnieuws zonder bredere maatschappelijke impact of controverse.",
      "summary": "De gemeente Oosterhout onderzoekt of ondernemers die direct worden geraakt door de verbouwing van Arendshof II tot gemeentehuis eerder financiële ondersteuning kunnen krijgen. Wethouder Dees Melsen de"
    },
    {
      "id": "gooi--en-eemlander-6011109828",
      "source": "Gooi- en Eemlander",
      "title": "Oud-NCTV: lobby had steeds meer invloed op maatregelen",
      "description": "Hoe langer de coronacrisis duurde, hoe meer belangen er speelden en die hadden invloed op de politieke besluitvorming rond de coronamaatregelen. Dat zei Pieter-Jaap Aalbersberg vrijdag tegen de parlementaire enquêtecommissie corona. Hij was tijdens de coronacrisis de Nationaal Coördinator Terrorismebestrijding en Veiligheid (NCTV).",
      "url": "https://www.gooieneemlander.nl/binnenland/oud-nctv-lobby-had-steeds-meer-invloed-op-maatregelen/155428399.html",
      "pubDate": "2026-06-05T15:19:30+00:00",
      "image": "https://prod-img.noordhollandsdagblad.nl/public/binnenland/1uxcjp-6b79d9f1-e784-4ace-b659-f3fdca16f864-tmg-webfeed-bin-anp050626166-1.jpeg/alternates/BASE_SIXTEEN_NINE/6b79d9f1-e784-4ace-b659-f3fdca16f864_tmg-webfeed-bin_ANP050626166-1.jpeg",
      "score": 78,
      "category": "Politiek",
      "location": "Landelijk",
      "reason": "Oud-NCTV getuigt voor coronacommissie over lobbyinvloed op beleid; relevant Den Haag-onderzoek.",
      "summary": "Pieter-Jaap Aalbersberg (oud-NCTV) vertelt parlementaire enquêtecommissie dat lobbybelangen steeds meer invloed hadden op coronabesluitvorming naarmate de crisis langer duurde. Zijn getuigenis ondersteunt kritiek op de politieke besluitvormingsprocessen tijdens de pandemie."
    },
    {
      "id": "nos-4551673342",
      "source": "NOS",
      "title": "Te veel eengezinswoningen? We moeten 'echt spaarzaam' zijn met bijbouwen",
      "description": "Heeft Nederland inderdaad \"te veel eengezinswoningen voor te weinig gezinnen\", zoals woningmarktanalisten van ABN Amro vanochtend stelden? Beleidsmakers en hun adviseurs zeggen dat we sowieso goed moeten kijken wat we nog bijbouwen. En dat dat vaker iets anders moet zijn dan de eengezinswoning. Rijksbouwmeester Francesco Veenstra vindt ook dat we moeten oppassen met het bouwen van eengezinswoninge",
      "url": "https://nos.nl/artikel/2617276-te-veel-eengezinswoningen-we-moeten-echt-spaarzaam-zijn-met-bijbouwen",
      "pubDate": "2026-06-05T15:19:21+00:00",
      "image": "https://images.cdn.nos.nl/7/D/J/u/i/T/kfAZjczx7QS6ELFihKKHbLosMpUoTecoFE4Ldra/0x387x4000x2250-1024x576.webp",
      "score": 45,
      "category": "Overig",
      "location": "Landelijk",
      "reason": "Woningmarktanalyse zonder politieke controverse of schandaal; te beleidsmatig.",
      "summary": "ABN Amro-analisten stellen dat Nederland mogelijk te veel eengezinswoningen bouwt en pleiten voor meer seniorenwoningen. Beleidsmakers ondersteunen het advies dat Nederland voorzichtiger moet zijn met bijbouwen."
    },
    {
      "id": "bn-de-stem-6390137767",
      "source": "BN De Stem",
      "title": "Eerst promotie met Unitas’30, nu knokt Sven tegen degradatie: ‘Geen ramp als het gebeurt, wel een teleurstelling’",
      "description": "Het is erop of eronder voor Unitas’30. Bij Roda Boys/Bommelerwaard moet de club uit Etten-Leur vandaag een 0-1 achterstand wegpoetsen, anders is degradatie uit de Vierde Divisie onafwendbaar. Dan zou Sven van Zwam binnen een jaar het mooiste en het lelijkste binnen het voetbal meemaken.",
      "url": "https://www.bndestem.nl/amateurvoetbal/eerst-promotie-met-unitas30-nu-knokt-sven-tegen-degradatie-geen-ramp-als-het-gebeurt-wel-een-teleurstelling~ab302577/",
      "pubDate": "2026-06-05T15:15:16+00:00",
      "image": "https://images.bndestem.nl/ZWJkZGI1NTI5YjdhZDYyMjRiY2MvZGlvLzI3NDM1ODMyNi9maXQtd2lkdGgvNDAw/nlbeeld-etten-leur-3-6-2026-foto-pix4profs-marcel-otterspeer-nacompetitiewedstrijd-tussen-unitas-30-en-roda-boys-centraal-in-beeld-sven-van-zwam-unitas",
      "score": 15,
      "category": "Overig",
      "location": "Noord-Brabant",
      "reason": "Routineus amateurvoetbalnieuws zonder maatschappelijke relevantie voor PowNed.",
      "summary": "Unitas'30 uit Etten-Leur speelt tegen Roda Boys/Bommelerwaard om degradatie te voorkomen uit de Vierde Divisie. Speler Sven van Zwam zou binnen een jaar promotie én degradatie meemaken."
    },
    {
      "id": "omroep-brabant-1380378201",
      "source": "Omroep Brabant",
      "title": "Man (31) uit Helmond opgepakt nadat politie kilo's drugs en wapens vindt",
      "description": "Een 31-jarige man uit Helmond is woensdag opgepakt. Dit schrijft de politie uit de stad in een bericht op sociale media. Bij een controle en huisdoorzoeking zijn kilo's harddrugs, wapens, illegale sigaretten, medicijnen en ongeveer 4000 euro aan contant geld gevonden.&nbsp; Agenten zouden eerst een voertuig hebben gecontroleerd, wat later zou hebben geleid tot de aanhouding van de man. Op foto's d",
      "url": "https://www.omroepbrabant.nl/nieuws/6012199/man-31-uit-helmond-opgepakt-nadat-politie-kilos-drugs-en-wapens-vindt",
      "pubDate": "2026-06-05T15:15:00+00:00",
      "image": "https://api.omroepbrabant.nl/img/f/1280/720/0.50/0.50/cmV2aXNpb25zLzQ5MTE3NzktMS5qcGc_c2U9MjA0NS0wMS0wMVQxMCUzQTQwJTNBMDBaJnNpZz1COWl6bXhrNXJRRTZ3QmhYM2lmN3Zab1hYUGpidWlEVDlCTHNnYTdUcHJzJTNEJnNwPXImc3ByPWh0dHBzJnNyPWImc3Q9MjAyNS0wMS0wMVQxMCUzQTQwJTNBMDBaJnN2PTIwMjYtMDItMDY=",
      "score": 72,
      "category": "Misdaad",
      "location": "Noord-Brabant",
      "reason": "Drugsaanhouding met wapens en contanten; lokale criminaliteitsbeat met concrete zaak.",
      "summary": "Politie in Helmond arresteert 31-jarige man na voertuigcontrole en huisdoorzoeking. Bij de inval worden kilo's harddrugs, wapens, illegale sigaretten en ongeveer 4000 euro in beslag genomen."
    },
    {
      "id": "ad-2384164304",
      "source": "AD",
      "title": "Zelfs de oersaaie beelden van voetballers op een vliegtuigtrap voelden plots als quasi-wereldnieuws",
      "description": "Columnist Sjoerd Mossou verheugt zich op zes weken lang ongevaarlijk en relativerend vermaak tijdens het WK. „Zelfs de oersaaie beelden van voetballers op een vliegtuigtrap voelden plots als quasi-wereldnieuws.’’",
      "url": "https://www.ad.nl/voetbal/zelfs-de-oersaaie-beelden-van-voetballers-op-een-vliegtuigtrap-voelden-plots-als-quasi-wereldnieuws~ae9afeba/",
      "pubDate": "2026-06-05T15:11:00+00:00",
      "image": "https://images.ad.nl/YzRjMTM5OWQ5YmI0ZjJkOGIzNGEvZGlvLzI3NDQxODkzMS9maXQtd2lkdGgvNDAw/ronald-koeman-zwaait-nog-een-keer-voor-hij-het-vliegtuig-naar-new-york-binnenstapt",
      "duplicate_sources": [
        "BN De Stem",
        "De Stentor",
        "PZC"
      ],
      "score": 5,
      "category": "Overig",
      "location": "Internationaal",
      "reason": "Sportcolumn over WK voetbal; niet relevant voor PowNed-richtlijnen.",
      "summary": "Columnist Sjoerd Mossou schrijft over het aankomende WK voetbal als ontspannend vermaak. Hij verheugt zich op zes weken lang 'ongevaarlijk en relativerend entertainment'."
    },
    {
      "id": "gooi--en-eemlander-8677978078",
      "source": "Gooi- en Eemlander",
      "title": "’Pak woningnood aan en bouw seniorenwoningen, geen gezinswoningen. Die komen al genoeg vrij als ouderen kunnen verhuizen, vindt ABN Amro",
      "description": "Woningmarktanalisten van ABN Amro waarschuwen voor leegstand en waardedaling door een dreigend overschot aan eengezinswoningen Gemeenten moeten inzetten op de bouw van seniorenwoningen, is hun dringend advies.",
      "url": "https://www.gooieneemlander.nl/uitgelicht/pak-woningnood-aan-en-bouw-seniorenwoningen-geen-gezinswoningen.-die-komen-al-genoeg-vrij-als-ouderen-kunnen-verhuizen-vindt-abn-amro/155424811.html",
      "pubDate": "2026-06-05T15:10:51+00:00",
      "image": "https://prod-img.noordhollandsdagblad.nl/public/incoming/46huke-woningverkoop-plust-opnieuw-in-februari.jpg/alternates/BASE_SIXTEEN_NINE/Woningverkoop_plust_opnieuw_in_februari.JPG",
      "score": 48,
      "category": "Overig",
      "location": "Landelijk",
      "reason": "Woningmarktanalyse zonder controverse; beleid-gericht zonder PowNed-relevantie.",
      "summary": "ABN Amro waarschuwt voor dreigend overschot aan eengezinswoningen en pleiten voor meer seniorenwoningen. Analisten adviseren gemeenten zich te richten op huisvesting voor ouderen."
    },
    {
      "id": "telegraaf-836812730",
      "source": "Telegraaf",
      "title": "Giro d'Italia: Lucinda Brand moet ritzege aan Célia Gery laten, valpartij rozetruidraagster Anna van der Breggen",
      "description": "Lucinda Brand (36) is er vrijdag net niet in geslaagd de zevende etappe van de Giro d’Italia op haar naam te schrijven. De zestien jaar jongere Française Célia Gery (FDJ United - SUEZ) was in Salice Terme na 159 kilometer te sterk in de sprint. De Italiaanse Chantal Pegolo werd derde.",
      "url": "https://www.telegraaf.nl/sport/wielrennen/giro-ditalia-lucinda-brand-moet-ritzege-aan-celia-gery-laten-valpartij-rozetruidraagster-anna-van-der-breggen/155358265.html",
      "pubDate": "2026-06-05T15:09:56+00:00",
      "image": "https://prod-img.telegraaf.nl/public/sport/65l10x-gettyimages-2280015252.jpg/alternates/BASE_SIXTEEN_NINE/GettyImages-2280015252.jpg",
      "score": 10,
      "category": "Overig",
      "location": "Internationaal",
      "reason": "Buitenlandse wielrensport zonder Nederlandse politieke of maatschappelijke relevantie.",
      "summary": "Lucinda Brand verliest ritzege in Giro d'Italia aan Française Célia Gery na 159 kilometer. Anna van der Breggen maakt valpartij mee in dezelfde etappe."
    },
    {
      "id": "trouw-1098325066",
      "source": "Trouw",
      "title": "Politie ontdekt ‘Nederlandse Pélicot-zaak’: ‘Deze mannen zijn niet bezig met wat ze hun partner aandoen’",
      "description": "",
      "url": "https://archive.ph/newest/https://www.trouw.nl/binnenland/politie-ontdekt-nederlandse-pelicot-zaak-deze-mannen-zijn-niet-bezig-met-wat-ze-hun-partner-aandoen~b9a5eea9/",
      "pubDate": "2026-06-05T15:08:02+00:00",
      "image": "https://image.trouw.nl/274415295/feature-crop/320/320/afbeelding",
      "score": 82,
      "category": "Misdaad",
      "location": "Landelijk",
      "reason": "Ernstige zedenszaak ('Nederlandse Pélicot'); maatschappelijk relevante crime-zaak.",
      "summary": "Politie ontdekt zaak vergelijkbaar met de Franse Pélicot-case met meerdere verdachten. Het artikel wijst op het patroon dat daders zich onvoldoende bewust zijn van het leed dat zij hun partners aanrichten."
    },
    {
      "id": "ad-7495302117",
      "source": "AD",
      "title": "Lucinda Brand grijpt net naast ritzege in Giro d’Italia, roze Anna van der Breggen onderuit",
      "description": "Lucinda Brand heeft net naast de winst gegrepen in de zevende etappe van de Giro d’Italia. Ze sprintte vanuit een kopgroep van zes naar de tweede plaats in Salice Terme. De Française Célia Gery, ploeggenote van Demi Vollering, was sneller. Anna van der Breggen ging met nog ruim vijftig kilometer te gaan onderuit, maar keerde terug in het peloton en bleef in het bezit van de roze trui.",
      "url": "https://www.ad.nl/wielrennen/lucinda-brand-grijpt-net-naast-ritzege-in-giro-ditalia-roze-anna-van-der-breggen-onderuit~a6d712ac/",
      "pubDate": "2026-06-05T15:07:00+00:00",
      "image": "https://images.ad.nl/ZjJkMzk5OTFjZDU3NTA3Nzk5MTEvZGlvLzI3NDQxOTQ3My9maXQtd2lkdGgvNDAw/giro-doitalia-women-2026-37th-edition-7th-stage-sorbolo-mezzani-salice-terme-159km-5-06-2026-celia-gery-fra-fdj-united-suez-photo-rafa-gomez-sca-cor-vos-2026",
      "duplicate_sources": [
        "BN De Stem",
        "De Stentor",
        "PZC"
      ],
      "score": 5,
      "category": "Overig",
      "location": "Internationaal",
      "reason": "Sport zonder Nederlands politieke of maatschappelijke relevantie; PowNed focust niet op routine sportnieuws",
      "summary": "Lucinda Brand finishte tweede in etappe zeven van de Giro d'Italia. Anna van der Breggen behield ondanks een valpartij de roze trui."
    },
    {
      "id": "nos-4401987771",
      "source": "NOS",
      "title": "China heeft Nederlands fregat opnieuw gevolgd, nu in Straat van Taiwan",
      "description": "Het Nederlandse fregat Zr. Ms. De Ruyter is net als vorige week gevolgd door de Chinese strijdkrachten, melden Chinese autoriteiten. Dat zou zijn gebeurd tijdens een doorvaart door de Straat van Taiwan. Volgens een Chinese verklaring zijn marine- en luchtmachteenheden ingezet om het schip \"te volgen en monitoren\" tijdens de doorvaart. De Chinese strijdkrachten blijven volgens de verklaring \"te all",
      "url": "https://nos.nl/artikel/2617274-china-heeft-nederlands-fregat-opnieuw-gevolgd-nu-in-straat-van-taiwan",
      "pubDate": "2026-06-05T15:06:27+00:00",
      "image": "https://images.cdn.nos.nl/5/D/9/B/h/N/e8GpEbkxjkxhTfv525bUXFrzMVphFzvK5p7dLnP/0x100x4000x2250-1024x576.webp",
      "score": 62,
      "category": "Politiek",
      "location": "Landelijk",
      "reason": "Nederlands defensie- en buitenlandbeleid, Nederlands fregat, geopolitieke spanning; relevant voor PowNed-publiek",
      "summary": "Het Nederlandse fregat De Ruyter werd opnieuw door Chinese strijdkrachten gevolgd tijdens passage door de Straat van Taiwan. China stelde dat marine- en luchtmachteenheden het schip hebben gemonitord."
    },
    {
      "id": "omroep-brabant-9489914810",
      "source": "Omroep Brabant",
      "title": "Aanstaand coalitie klapt op thema asiel: 'PVV wil geen asielportefeuille'",
      "description": "De Volkspartij, de PVV en de VVD in Steenbergen stevenden samen af op een nieuwe coalitie. Er lag al een akkoord op hoofdlijnen, maar vrijdag is de formatie toch misgelopen. De Volkspartij, de winnaar in Steenbergen tijdens de gemeenteraadsverkiezingen, trok de stekker eruit. Afgelopen maandag spraken de VVD, PVV en formateurs met elkaar zonder de Volkspartij. &ldquo;Een achterkamertjesgesprek&rdq",
      "url": "https://www.omroepbrabant.nl/nieuws/6012195/aanstaand-coalitie-klapt-op-thema-asiel-pvv-wil-geen-asielportefeuille",
      "pubDate": "2026-06-05T15:03:00+00:00",
      "image": "https://api.omroepbrabant.nl/img/f/1280/720/0.43/0.49/cmV2aXNpb25zLzQ4NTc0MTEtMS5qcGc_c2U9MjA0NS0wMS0wMVQxMCUzQTQwJTNBMDBaJnNpZz1XZ0IzUmxNZmclMkY3QUtmenlKYUhrUGRCVkpHbnhRJTJCM2V2MXdSNXoxZjZtNCUzRCZzcD1yJnNwcj1odHRwcyZzcj1iJnN0PTIwMjUtMDEtMDFUMTAlM0E0MCUzQTAwWiZzdj0yMDI2LTAyLTA2",
      "score": 78,
      "category": "Politiek",
      "location": "Noord-Brabant",
      "reason": "Lokale coalitieonderhandelingen met PVV/VVD; eigen stijl politieke crisis en asielthematiek passen goed",
      "summary": "Coalitieonderhandelingen in Steenbergen zijn afgesproken; de Volkspartij trok zich terug uit gesprekken met PVV en VVD. Verschil over asielportefeuille ligt aan basis van breuk."
    },
    {
      "id": "crimesite-2746936783",
      "source": "Crimesite",
      "title": "Verdachten kunstroof Assen krijgen bijna vier jaar cel na procesafspraken met OM",
      "description": "De rechtbank in Assen heeft vrijdag drie jaar en elf maanden celstraf opgelegd aan drie mannen voor hun betrokkenheid bij de kunstroof in het Drents Museum op 25 januari 2025. Het Openbaar Ministerie had tot 5,5 jaar cel geëist tegen Bernhard Z. (35), Jan B. (21) en Douglas Chesley W. (37). Z. sloot als enige [&#8230;] Het bericht Verdachten kunstroof Assen krijgen bijna vier jaar cel na procesafs",
      "url": "https://www.crimesite.nl/verdachten-kunstroof-assen-krijgen-bijna-vier-jaar-cel-na-procesafspraken-met-om/",
      "pubDate": "2026-06-05T15:01:13+00:00",
      "image": "https://www.crimesite.nl/wp-content/uploads/2025/05/Helmet_of_Cotofenesti_-_Graphical_Reconstruction_by_Radu_Oltean-150x150.jpg",
      "score": 85,
      "category": "Misdaad",
      "location": "Drenthe",
      "reason": "Kunstroof Drents Museum; sensationeel misdaadnieuws, veroordeling, media-aandacht past PowNed-profiel",
      "summary": "Rechtbank Assen veroordeelde drie mannen tot bijna vier jaar celstraf voor kunstroof in het Drents Museum van januari 2025. Het OM had tot 5,5 jaar geëist."
    }
  ]
}